Workbook
Name SUG_A: Lists!$J$4:INDEX(Lists!$J$4:$J$40,MAX(Lists!$I$4:$I$40))
Name SUG_D: Lists!$GB$4:INDEX(Lists!$GB$4:$GB$42,MAX(Lists!$GA$4:$GA$40)+2)
Name SUG_MAIN: Lists!$E$4:INDEX(Lists!$E$4:$E$114,MAX(Lists!$D$4:$D$114))
Name SUG_B: Lists!$GF$4:INDEX(Lists!$GF$4:$GF$42,MAX(Lists!$GE$4:$GE$40)+2)
Name SUG_C: Lists!$GJ$4:INDEX(Lists!$GJ$4:$GJ$42,MAX(Lists!$GI$4:$GI$40)+2)
Name SUG_E: Lists!$GN$4:INDEX(Lists!$GN$4:$GN$42,MAX(Lists!$GM$4:$GM$40)+2)
Name SUG_F: Lists!$GR$4:INDEX(Lists!$GR$4:$GR$42,MAX(Lists!$GQ$4:$GQ$40)+2)
Name SUG_G: Lists!$GV$4:INDEX(Lists!$GV$4:$GV$42,MAX(Lists!$GU$4:$GU$40)+2)
Name SUG_H: Lists!$GZ$4:INDEX(Lists!$GZ$4:$GZ$42,MAX(Lists!$GY$4:$GY$40)+2)
Name SUG_I: Lists!$HD$4:INDEX(Lists!$HD$4:$HD$42,MAX(Lists!$HC$4:$HC$40)+2)
Name SUG_J: Lists!$HH$4:INDEX(Lists!$HH$4:$HH$42,MAX(Lists!$HG$4:$HG$40)+2)
Name SUG_K: Lists!$HL$4:INDEX(Lists!$HL$4:$HL$42,MAX(Lists!$HK$4:$HK$40)+2)
Name SUG_L: Lists!$HP$4:INDEX(Lists!$HP$4:$HP$42,MAX(Lists!$HO$4:$HO$40)+2)
Name SUG_M: Lists!$HT$4:INDEX(Lists!$HT$4:$HT$42,MAX(Lists!$HS$4:$HS$40)+2)
Name SUG_N: Lists!$HX$4:INDEX(Lists!$HX$4:$HX$42,MAX(Lists!$HW$4:$HW$40)+2)
Name SUG_O: Lists!$IB$4:INDEX(Lists!$IB$4:$IB$42,MAX(Lists!$IA$4:$IA$40)+2)
Name SUG_P: Lists!$IF$4:INDEX(Lists!$IF$4:$IF$42,MAX(Lists!$IE$4:$IE$40)+2)
Name SUG_Q: Lists!$IJ$4:INDEX(Lists!$IJ$4:$IJ$42,MAX(Lists!$II$4:$II$40)+2)
Name SUG_R: Lists!$IN$4:INDEX(Lists!$IN$4:$IN$42,MAX(Lists!$IM$4:$IM$40)+2)
Name SUG_S: Lists!$IR$4:INDEX(Lists!$IR$4:$IR$42,MAX(Lists!$IQ$4:$IQ$40)+2)
Name SUG_T: Lists!$IV$4:INDEX(Lists!$IV$4:$IV$42,MAX(Lists!$IU$4:$IU$40)+2)
Name SUG_U: Lists!$IZ$4:INDEX(Lists!$IZ$4:$IZ$42,MAX(Lists!$IY$4:$IY$40)+2)
Name SUG_V: Lists!$JD$4:INDEX(Lists!$JD$4:$JD$42,MAX(Lists!$JC$4:$JC$40)+2)
Name SUG_W: Lists!$JH$4:INDEX(Lists!$JH$4:$JH$42,MAX(Lists!$JG$4:$JG$40)+2)
Name SUG_X: Lists!$JL$4:INDEX(Lists!$JL$4:$JL$42,MAX(Lists!$JK$4:$JK$40)+2)
Name SUG_Y: Lists!$JP$4:INDEX(Lists!$JP$4:$JP$42,MAX(Lists!$JO$4:$JO$40)+2)
Name SUG_Z: Lists!$JT$4:INDEX(Lists!$JT$4:$JT$42,MAX(Lists!$JS$4:$JS$40)+2)
Name SUG_AA: Lists!$JX$4:INDEX(Lists!$JX$4:$JX$42,MAX(Lists!$JW$4:$JW$40)+2)
Name SUG_AB: Lists!$KB$4:INDEX(Lists!$KB$4:$KB$42,MAX(Lists!$KA$4:$KA$40)+2)
Name SUG_AC: Lists!$KF$4:INDEX(Lists!$KF$4:$KF$42,MAX(Lists!$KE$4:$KE$40)+2)
Name SUG_AD: Lists!$KJ$4:INDEX(Lists!$KJ$4:$KJ$42,MAX(Lists!$KI$4:$KI$40)+2)
Name SUG_AE: Lists!$KN$4:INDEX(Lists!$KN$4:$KN$42,MAX(Lists!$KM$4:$KM$40)+2)
Name SUG_AI: Lists!$KR$4:INDEX(Lists!$KR$4:$KR$42,MAX(Lists!$KQ$4:$KQ$40)+2)
Name SUG_AF: Lists!$KV$4:INDEX(Lists!$KV$4:$KV$42,MAX(Lists!$KU$4:$KU$40)+2)
Name SUG_AG: Lists!$KZ$4:INDEX(Lists!$KZ$4:$KZ$42,MAX(Lists!$KY$4:$KY$40)+2)
Name SUG_AH: Lists!$LD$4:INDEX(Lists!$LD$4:$LD$42,MAX(Lists!$LC$4:$LC$40)+2)
Name SUGN_B: Lists!$LH$4:INDEX(Lists!$LH$4:$LH$42,MAX(Lists!$LG$4:$LG$40)+2)
Name SUGN_C: Lists!$LL$4:INDEX(Lists!$LL$4:$LL$42,MAX(Lists!$LK$4:$LK$40)+2)
Name SUGN_D: Lists!$LP$4:INDEX(Lists!$LP$4:$LP$42,MAX(Lists!$LO$4:$LO$40)+2)
Name SUGN_E: Lists!$LT$4:INDEX(Lists!$LT$4:$LT$42,MAX(Lists!$LS$4:$LS$40)+2)
Name SUGN_F: Lists!$LX$4:INDEX(Lists!$LX$4:$LX$42,MAX(Lists!$LW$4:$LW$40)+2)
Name SUGN_G: Lists!$MB$4:INDEX(Lists!$MB$4:$MB$42,MAX(Lists!$MA$4:$MA$40)+2)
Name SUGN_H: Lists!$MF$4:INDEX(Lists!$MF$4:$MF$42,MAX(Lists!$ME$4:$ME$40)+2)
Name SUGN_I: Lists!$MJ$4:INDEX(Lists!$MJ$4:$MJ$42,MAX(Lists!$MI$4:$MI$40)+2)
Name SUGN_J: Lists!$MN$4:INDEX(Lists!$MN$4:$MN$42,MAX(Lists!$MM$4:$MM$40)+2)
Name SUGN_K: Lists!$MR$4:INDEX(Lists!$MR$4:$MR$42,MAX(Lists!$MQ$4:$MQ$40)+2)
Name SUGN_L: Lists!$MV$4:INDEX(Lists!$MV$4:$MV$42,MAX(Lists!$MU$4:$MU$40)+2)
Name SUGN_M: Lists!$MZ$4:INDEX(Lists!$MZ$4:$MZ$42,MAX(Lists!$MY$4:$MY$40)+2)
Name SUGN_N: Lists!$ND$4:INDEX(Lists!$ND$4:$ND$42,MAX(Lists!$NC$4:$NC$40)+2)
Name SUGN_O: Lists!$NH$4:INDEX(Lists!$NH$4:$NH$42,MAX(Lists!$NG$4:$NG$40)+2)
Name SUGN_P: Lists!$NL$4:INDEX(Lists!$NL$4:$NL$42,MAX(Lists!$NK$4:$NK$40)+2)
Name SUGN_Q: Lists!$NP$4:INDEX(Lists!$NP$4:$NP$42,MAX(Lists!$NO$4:$NO$40)+2)
Name SUGN_R: Lists!$NT$4:INDEX(Lists!$NT$4:$NT$42,MAX(Lists!$NS$4:$NS$40)+2)
Name SUGN_S: Lists!$NX$4:INDEX(Lists!$NX$4:$NX$42,MAX(Lists!$NW$4:$NW$40)+2)
Name SUGN_T: Lists!$OB$4:INDEX(Lists!$OB$4:$OB$42,MAX(Lists!$OA$4:$OA$40)+2)
Name SUGN_U: Lists!$OF$4:INDEX(Lists!$OF$4:$OF$42,MAX(Lists!$OE$4:$OE$40)+2)
Name SUGN_V: Lists!$OJ$4:INDEX(Lists!$OJ$4:$OJ$42,MAX(Lists!$OI$4:$OI$40)+2)
Name SUGN_W: Lists!$ON$4:INDEX(Lists!$ON$4:$ON$42,MAX(Lists!$OM$4:$OM$40)+2)
Name SUGN_X: Lists!$OR$4:INDEX(Lists!$OR$4:$OR$42,MAX(Lists!$OQ$4:$OQ$40)+2)
Name SUGN_Y: Lists!$OV$4:INDEX(Lists!$OV$4:$OV$42,MAX(Lists!$OU$4:$OU$40)+2)

Sheet Final Calculation Sheet
B1: MSTC LIMITED - COMBINED BID SHEET (Auctions 21977, 21978, 21979, 21980)
AI2: =IF(COUNTIF($A$2:$AH$2,"<>")=0,"🔍 SEARCH - nothing typed yet, all 37 rows are shown. · type in any yellow box above a column, or pick from its dropdown: every column is searched, the boxes are ANDed together, (blank)/(nonblank) and * / ? work as usual","🔍 MATCHED "&SUM($BT$4:$BT$40)&" of 37 row(s) · the rows that miss are greyed out, nothing is hidden and the totals still cover all 37 · clear a box to widen the dropdowns again")
A3: Quantity | B3: Lot No. | C3: Rate | D3: Bid Sheet | E3: Unit | F3: Lot No. | G3: Buyer | H3: Mat. Value | I3: GST | J3: Mat. Value + GST | K3: TCS | L3: TDS u/s 194(O) | M3: Service Charge to MSTC | N3: TDS u/s 194(H) | O3: Net Service Charge (post TDS 194H) | P3: Service charge to MSTC | Q3: GST TDS Rate | R3: GST TDS | S3: Total Receivables in Cash | T3: Security Deposit (Expected) | U3: Security Deposit (Received) | V3: Date of Receipt | W3: Final Payment (Expected) | X3: Final Payment (Received) | Y3: Date of Receipt | Z3: LPP Expected | AA3: LPP Received | AB3: Date of Recepit of LPP | AC3: Total Received | AD3: Outstanding | AE3: Payment Status | AF3: Invoice No. | AG3: SAP Document | AH3: Doc./Invoice Date
A4: 669 | B4: SCRAP COPPER OF T/F WINDING (Oil impregnated paper insulated T/F winding) | C4: 1181 | D4: 21980 | E4: KG | F4: 1763 | G4: AL HAMD TRADE CORPORATION | H4: 790089 | I4: =ROUND(H4*18%,0) | J4: =+H4+I4 | K4: =ROUND((H4+I4)*2%,0) | L4: =H4*0.1% | M4: =H4*2.25%*118% | N4: =H4*2.25%*2% | O4: =M4-N4 | P4: =ROUND(O4+L4,0) | Q4: 0.02 | R4: =ROUND(H4*Q4,0) | S4: =ROUND(H4*117.65%-R4,0) | T4: =ROUND(H4*25%,0) | U4: 197522 | V4: 24.08.2026 | W4: =ROUND(H4*92.65%-R4,0) | X4: 716216 | Y4: 18.08.2026 | Z4: =IF(IF(OR(AB4="",AB4=0),TODAY(),DATE(VALUE(RIGHT(AB4,4)),VALUE(MID(AB4,4,2)),VALUE(LEFT(AB4,2))))<=DATE(2026,8,24),0,H4*0.0118*CEILING((IF(OR(AB4="",AB4=0),TODAY(),DATE(VALUE(RIGHT(AB4,4)),VALUE(MID(AB4,4,2)),VALUE(LEFT(AB4,2))))-DATE(2026,8,22))/7,1)) | AC4: =U4+X4+AA4 | AD4: =S4-AC4 | AE4: =IF(AD4="","",IF(AD4<=5,"SETTLED","OUTSTANDING")) | AF4: DR2640100029 | AG4: 1800003271 | AH4: 24.08.2026 | AL4: =IF($A$2="",1,IF($A$2="(blank)",--(A4=""),IF($A$2="(nonblank)",--(A4<>""),--ISNUMBER(SEARCH($A$2,A4))))) | AM4: =IF($B$2="",1,IF($B$2="(blank)",--(B4=""),IF($B$2="(nonblank)",--(B4<>""),--ISNUMBER(SEARCH($B$2,B4))))) | AN4: =IF($C$2="",1,IF($C$2="(blank)",--(C4=""),IF($C$2="(nonblank)",--(C4<>""),--ISNUMBER(SEARCH($C$2,C4))))) | AO4: =IF($D$2="",1,IF($D$2="(blank)",--(D4=""),IF($D$2="(nonblank)",--(D4<>""),--ISNUMBER(SEARCH($D$2,D4))))) | AP4: =IF($E$2="",1,IF($E$2="(blank)",--(E4=""),IF($E$2="(nonblank)",--(E4<>""),--ISNUMBER(SEARCH($E$2,E4))))) | AQ4: =IF($F$2="",1,IF($F$2="(blank)",--(F4=""),IF($F$2="(nonblank)",--(F4<>""),--ISNUMBER(SEARCH($F$2,F4))))) | AR4: =IF($G$2="",1,IF($G$2="(blank)",--(G4=""),IF($G$2="(nonblank)",--(G4<>""),--ISNUMBER(SEARCH($G$2,G4))))) | AS4: =IF($H$2="",1,IF($H$2="(blank)",--(H4=""),IF($H$2="(nonblank)",--(H4<>""),--ISNUMBER(SEARCH($H$2,H4))))) | AT4: =IF($I$2="",1,IF($I$2="(blank)",--(I4=""),IF($I$2="(nonblank)",--(I4<>""),--ISNUMBER(SEARCH($I$2,I4))))) | AU4: =IF($J$2="",1,IF($J$2="(blank)",--(J4=""),IF($J$2="(nonblank)",--(J4<>""),--ISNUMBER(SEARCH($J$2,J4))))) | AV4: =IF($K$2="",1,IF($K$2="(blank)",--(K4=""),IF($K$2="(nonblank)",--(K4<>""),--ISNUMBER(SEARCH($K$2,K4))))) | AW4: =IF($L$2="",1,IF($L$2="(blank)",--(L4=""),IF($L$2="(nonblank)",--(L4<>""),--ISNUMBER(SEARCH($L$2,L4))))) | AX4: =IF($M$2="",1,IF($M$2="(blank)",--(M4=""),IF($M$2="(nonblank)",--(M4<>""),--ISNUMBER(SEARCH($M$2,M4))))) | AY4: =IF($N$2="",1,IF($N$2="(blank)",--(N4=""),IF($N$2="(nonblank)",--(N4<>""),--ISNUMBER(SEARCH($N$2,N4))))) | AZ4: =IF($O$2="",1,IF($O$2="(blank)",--(O4=""),IF($O$2="(nonblank)",--(O4<>""),--ISNUMBER(SEARCH($O$2,O4))))) | BA4: =IF($P$2="",1,IF($P$2="(blank)",--(P4=""),IF($P$2="(nonblank)",--(P4<>""),--ISNUMBER(SEARCH($P$2,P4))))) | BB4: =IF($Q$2="",1,IF($Q$2="(blank)",--(Q4=""),IF($Q$2="(nonblank)",--(Q4<>""),--ISNUMBER(SEARCH($Q$2,Q4))))) | BC4: =IF($R$2="",1,IF($R$2="(blank)",--(R4=""),IF($R$2="(nonblank)",--(R4<>""),--ISNUMBER(SEARCH($R$2,R4))))) | BD4: =IF($S$2="",1,IF($S$2="(blank)",--(S4=""),IF($S$2="(nonblank)",--(S4<>""),--ISNUMBER(SEARCH($S$2,S4))))) | BE4: =IF($T$2="",1,IF($T$2="(blank)",--(T4=""),IF($T$2="(nonblank)",--(T4<>""),--ISNUMBER(SEARCH($T$2,T4))))) | BF4: =IF($U$2="",1,IF($U$2="(blank)",--(U4=""),IF($U$2="(nonblank)",--(U4<>""),--ISNUMBER(SEARCH($U$2,U4))))) | BG4: =IF($V$2="",1,IF($V$2="(blank)",--(V4=""),IF($V$2="(nonblank)",--(V4<>""),--ISNUMBER(SEARCH($V$2,V4))))) | BH4: =IF($W$2="",1,IF($W$2="(blank)",--(W4=""),IF($W$2="(nonblank)",--(W4<>""),--ISNUMBER(SEARCH($W$2,W4))))) | BI4: =IF($X$2="",1,IF($X$2="(blank)",--(X4=""),IF($X$2="(nonblank)",--(X4<>""),--ISNUMBER(SEARCH($X$2,X4))))) | BJ4: =IF($Y$2="",1,IF($Y$2="(blank)",--(Y4=""),IF($Y$2="(nonblank)",--(Y4<>""),--ISNUMBER(SEARCH($Y$2,Y4))))) | BK4: =IF($Z$2="",1,IF($Z$2="(blank)",--(Z4=""),IF($Z$2="(nonblank)",--(Z4<>""),--ISNUMBER(SEARCH($Z$2,Z4))))) | BL4: =IF($AA$2="",1,IF($AA$2="(blank)",--(AA4=""),IF($AA$2="(nonblank)",--(AA4<>""),--ISNUMBER(SEARCH($AA$2,AA4))))) | BM4: =IF($AB$2="",1,IF($AB$2="(blank)",--(AB4=""),IF($AB$2="(nonblank)",--(AB4<>""),--ISNUMBER(SEARCH($AB$2,AB4))))) | BN4: =IF($AC$2="",1,IF($AC$2="(blank)",--(AC4=""),IF($AC$2="(nonblank)",--(AC4<>""),--ISNUMBER(SEARCH($AC$2,AC4))))) | BO4: =IF($AD$2="",1,IF($AD$2="(blank)",--(AD4=""),IF($AD$2="(nonblank)",--(AD4<>""),--ISNUMBER(SEARCH($AD$2,AD4))))) | BP4: =IF($AE$2="",1,IF($AE$2="(blank)",--(AE4=""),IF($AE$2="(nonblank)",--(AE4<>""),--ISNUMBER(SEARCH($AE$2,AE4))))) | BQ4: =IF($AF$2="",1,IF($AF$2="(blank)",--(AF4=""),IF($AF$2="(nonblank)",--(AF4<>""),--ISNUMBER(SEARCH($AF$2,AF4))))) | BR4: =IF($AG$2="",1,IF($AG$2="(blank)",--(AG4=""),IF($AG$2="(nonblank)",--(AG4<>""),--ISNUMBER(SEARCH($AG$2,AG4))))) | BS4: =IF($AH$2="",1,IF($AH$2="(blank)",--(AH4=""),IF($AH$2="(nonblank)",--(AH4<>""),--ISNUMBER(SEARCH($AH$2,AH4))))) | BT4: =IF(COUNTIF($AL4:$BS4,0)>0,0,1)
A5: 270 | B5: Scrap of Empty oil drum | C5: 580 | D5: 21977 | E5: NO | F5: 1874 | G5: NATIONAL ENTERPRISES | H5: 156600 | I5: =ROUND(H5*18%,0) | J5: =+H5+I5 | K5: =ROUND((H5+I5)*2%,0) | L5: =H5*0.1% | M5: =H5*2.25%*118% | N5: =H5*2.25%*2% | O5: =M5-N5 | P5: =ROUND(O5+L5,0) | Q5: 0 | R5: =ROUND(H5*Q5,0) | S5: =ROUND(H5*117.65%-R5,0) | T5: =ROUND(H5*25%,0) | U5: =+T5 | V5: 13.08.2026 | W5: =ROUND(H5*92.65%-R5,0) | X5: 145090 | Y5: 24.08.2026 | Z5: =IF(IF(OR(AB5="",AB5=0),TODAY(),DATE(VALUE(RIGHT(AB5,4)),VALUE(MID(AB5,4,2)),VALUE(LEFT(AB5,2))))<=DATE(2026,8,24),0,H5*0.0118*CEILING((IF(OR(AB5="",AB5=0),TODAY(),DATE(VALUE(RIGHT(AB5,4)),VALUE(MID(AB5,4,2)),VALUE(LEFT(AB5,2))))-DATE(2026,8,22))/7,1)) | AC5: =U5+X5+AA5 | AD5: =S5-AC5 | AE5: =IF(AD5="","",IF(AD5<=5,"SETTLED","OUTSTANDING")) | AF5: DR2640100030 | AG5: 1800003302 | AH5: 27.08.2026 | AL5: =IF($A$2="",1,IF($A$2="(blank)",--(A5=""),IF($A$2="(nonblank)",--(A5<>""),--ISNUMBER(SEARCH($A$2,A5))))) | AM5: =IF($B$2="",1,IF($B$2="(blank)",--(B5=""),IF($B$2="(nonblank)",--(B5<>""),--ISNUMBER(SEARCH($B$2,B5))))) | AN5: =IF($C$2="",1,IF($C$2="(blank)",--(C5=""),IF($C$2="(nonblank)",--(C5<>""),--ISNUMBER(SEARCH($C$2,C5))))) | AO5: =IF($D$2="",1,IF($D$2="(blank)",--(D5=""),IF($D$2="(nonblank)",--(D5<>""),--ISNUMBER(SEARCH($D$2,D5))))) | AP5: =IF($E$2="",1,IF($E$2="(blank)",--(E5=""),IF($E$2="(nonblank)",--(E5<>""),--ISNUMBER(SEARCH($E$2,E5))))) | AQ5: =IF($F$2="",1,IF($F$2="(blank)",--(F5=""),IF($F$2="(nonblank)",--(F5<>""),--ISNUMBER(SEARCH($F$2,F5))))) | AR5: =IF($G$2="",1,IF($G$2="(blank)",--(G5=""),IF($G$2="(nonblank)",--(G5<>""),--ISNUMBER(SEARCH($G$2,G5))))) | AS5: =IF($H$2="",1,IF($H$2="(blank)",--(H5=""),IF($H$2="(nonblank)",--(H5<>""),--ISNUMBER(SEARCH($H$2,H5))))) | AT5: =IF($I$2="",1,IF($I$2="(blank)",--(I5=""),IF($I$2="(nonblank)",--(I5<>""),--ISNUMBER(SEARCH($I$2,I5))))) | AU5: =IF($J$2="",1,IF($J$2="(blank)",--(J5=""),IF($J$2="(nonblank)",--(J5<>""),--ISNUMBER(SEARCH($J$2,J5))))) | AV5: =IF($K$2="",1,IF($K$2="(blank)",--(K5=""),IF($K$2="(nonblank)",--(K5<>""),--ISNUMBER(SEARCH($K$2,K5))))) | AW5: =IF($L$2="",1,IF($L$2="(blank)",--(L5=""),IF($L$2="(nonblank)",--(L5<>""),--ISNUMBER(SEARCH($L$2,L5))))) | AX5: =IF($M$2="",1,IF($M$2="(blank)",--(M5=""),IF($M$2="(nonblank)",--(M5<>""),--ISNUMBER(SEARCH($M$2,M5))))) | AY5: =IF($N$2="",1,IF($N$2="(blank)",--(N5=""),IF($N$2="(nonblank)",--(N5<>""),--ISNUMBER(SEARCH($N$2,N5))))) | AZ5: =IF($O$2="",1,IF($O$2="(blank)",--(O5=""),IF($O$2="(nonblank)",--(O5<>""),--ISNUMBER(SEARCH($O$2,O5))))) | BA5: =IF($P$2="",1,IF($P$2="(blank)",--(P5=""),IF($P$2="(nonblank)",--(P5<>""),--ISNUMBER(SEARCH($P$2,P5))))) | BB5: =IF($Q$2="",1,IF($Q$2="(blank)",--(Q5=""),IF($Q$2="(nonblank)",--(Q5<>""),--ISNUMBER(SEARCH($Q$2,Q5))))) | BC5: =IF($R$2="",1,IF($R$2="(blank)",--(R5=""),IF($R$2="(nonblank)",--(R5<>""),--ISNUMBER(SEARCH($R$2,R5))))) | BD5: =IF($S$2="",1,IF($S$2="(blank)",--(S5=""),IF($S$2="(nonblank)",--(S5<>""),--ISNUMBER(SEARCH($S$2,S5))))) | BE5: =IF($T$2="",1,IF($T$2="(blank)",--(T5=""),IF($T$2="(nonblank)",--(T5<>""),--ISNUMBER(SEARCH($T$2,T5))))) | BF5: =IF($U$2="",1,IF($U$2="(blank)",--(U5=""),IF($U$2="(nonblank)",--(U5<>""),--ISNUMBER(SEARCH($U$2,U5))))) | BG5: =IF($V$2="",1,IF($V$2="(blank)",--(V5=""),IF($V$2="(nonblank)",--(V5<>""),--ISNUMBER(SEARCH($V$2,V5))))) | BH5: =IF($W$2="",1,IF($W$2="(blank)",--(W5=""),IF($W$2="(nonblank)",--(W5<>""),--ISNUMBER(SEARCH($W$2,W5))))) | BI5: =IF($X$2="",1,IF($X$2="(blank)",--(X5=""),IF($X$2="(nonblank)",--(X5<>""),--ISNUMBER(SEARCH($X$2,X5))))) | BJ5: =IF($Y$2="",1,IF($Y$2="(blank)",--(Y5=""),IF($Y$2="(nonblank)",--(Y5<>""),--ISNUMBER(SEARCH($Y$2,Y5))))) | BK5: =IF($Z$2="",1,IF($Z$2="(blank)",--(Z5=""),IF($Z$2="(nonblank)",--(Z5<>""),--ISNUMBER(SEARCH($Z$2,Z5))))) | BL5: =IF($AA$2="",1,IF($AA$2="(blank)",--(AA5=""),IF($AA$2="(nonblank)",--(AA5<>""),--ISNUMBER(SEARCH($AA$2,AA5))))) | BM5: =IF($AB$2="",1,IF($AB$2="(blank)",--(AB5=""),IF($AB$2="(nonblank)",--(AB5<>""),--ISNUMBER(SEARCH($AB$2,AB5))))) | BN5: =IF($AC$2="",1,IF($AC$2="(blank)",--(AC5=""),IF($AC$2="(nonblank)",--(AC5<>""),--ISNUMBER(SEARCH($AC$2,AC5))))) | BO5: =IF($AD$2="",1,IF($AD$2="(blank)",--(AD5=""),IF($AD$2="(nonblank)",--(AD5<>""),--ISNUMBER(SEARCH($AD$2,AD5))))) | BP5: =IF($AE$2="",1,IF($AE$2="(blank)",--(AE5=""),IF($AE$2="(nonblank)",--(AE5<>""),--ISNUMBER(SEARCH($AE$2,AE5))))) | BQ5: =IF($AF$2="",1,IF($AF$2="(blank)",--(AF5=""),IF($AF$2="(nonblank)",--(AF5<>""),--ISNUMBER(SEARCH($AF$2,AF5))))) | BR5: =IF($AG$2="",1,IF($AG$2="(blank)",--(AG5=""),IF($AG$2="(nonblank)",--(AG5<>""),--ISNUMBER(SEARCH($AG$2,AG5))))) | BS5: =IF($AH$2="",1,IF($AH$2="(blank)",--(AH5=""),IF($AH$2="(nonblank)",--(AH5<>""),--ISNUMBER(SEARCH($AH$2,AH5))))) | BT5: =IF(COUNTIF($AL5:$BS5,0)>0,0,1)
A6: 28 | B6: Scrap of Copper of faulty AC compressor | C6: 1456 | D6: 21977 | E6: KG | F6: 1875 | G6: F R KHANS ENTERPRISES | H6: 40768 | I6: =ROUND(H6*18%,0) | J6: =+H6+I6 | K6: =ROUND((H6+I6)*2%,0) | L6: =H6*0.1% | M6: =H6*2.25%*118% | N6: =H6*2.25%*2% | O6: =M6-N6 | P6: =ROUND(O6+L6,0) | Q6: 0 | R6: =ROUND(H6*Q6,0) | S6: =ROUND(H6*117.65%-R6,0) | T6: =ROUND(H6*25%,0) | U6: 10192 | V6: 11.08.2026 | W6: =ROUND(H6*92.65%-R6,0) | X6: =+W6+R6 | Y6: 20.08.2026 | Z6: =IF(IF(OR(AB6="",AB6=0),TODAY(),DATE(VALUE(RIGHT(AB6,4)),VALUE(MID(AB6,4,2)),VALUE(LEFT(AB6,2))))<=DATE(2026,8,24),0,H6*0.0118*CEILING((IF(OR(AB6="",AB6=0),TODAY(),DATE(VALUE(RIGHT(AB6,4)),VALUE(MID(AB6,4,2)),VALUE(LEFT(AB6,2))))-DATE(2026,8,22))/7,1)) | AC6: =U6+X6+AA6 | AD6: =S6-AC6 | AE6: =IF(AD6="","",IF(AD6<=5,"SETTLED","OUTSTANDING")) | AF6: DR2640100047 | AG6: 1800003346 | AH6: 27.08.2026 | AL6: =IF($A$2="",1,IF($A$2="(blank)",--(A6=""),IF($A$2="(nonblank)",--(A6<>""),--ISNUMBER(SEARCH($A$2,A6))))) | AM6: =IF($B$2="",1,IF($B$2="(blank)",--(B6=""),IF($B$2="(nonblank)",--(B6<>""),--ISNUMBER(SEARCH($B$2,B6))))) | AN6: =IF($C$2="",1,IF($C$2="(blank)",--(C6=""),IF($C$2="(nonblank)",--(C6<>""),--ISNUMBER(SEARCH($C$2,C6))))) | AO6: =IF($D$2="",1,IF($D$2="(blank)",--(D6=""),IF($D$2="(nonblank)",--(D6<>""),--ISNUMBER(SEARCH($D$2,D6))))) | AP6: =IF($E$2="",1,IF($E$2="(blank)",--(E6=""),IF($E$2="(nonblank)",--(E6<>""),--ISNUMBER(SEARCH($E$2,E6))))) | AQ6: =IF($F$2="",1,IF($F$2="(blank)",--(F6=""),IF($F$2="(nonblank)",--(F6<>""),--ISNUMBER(SEARCH($F$2,F6))))) | AR6: =IF($G$2="",1,IF($G$2="(blank)",--(G6=""),IF($G$2="(nonblank)",--(G6<>""),--ISNUMBER(SEARCH($G$2,G6))))) | AS6: =IF($H$2="",1,IF($H$2="(blank)",--(H6=""),IF($H$2="(nonblank)",--(H6<>""),--ISNUMBER(SEARCH($H$2,H6))))) | AT6: =IF($I$2="",1,IF($I$2="(blank)",--(I6=""),IF($I$2="(nonblank)",--(I6<>""),--ISNUMBER(SEARCH($I$2,I6))))) | AU6: =IF($J$2="",1,IF($J$2="(blank)",--(J6=""),IF($J$2="(nonblank)",--(J6<>""),--ISNUMBER(SEARCH($J$2,J6))))) | AV6: =IF($K$2="",1,IF($K$2="(blank)",--(K6=""),IF($K$2="(nonblank)",--(K6<>""),--ISNUMBER(SEARCH($K$2,K6))))) | AW6: =IF($L$2="",1,IF($L$2="(blank)",--(L6=""),IF($L$2="(nonblank)",--(L6<>""),--ISNUMBER(SEARCH($L$2,L6))))) | AX6: =IF($M$2="",1,IF($M$2="(blank)",--(M6=""),IF($M$2="(nonblank)",--(M6<>""),--ISNUMBER(SEARCH($M$2,M6))))) | AY6: =IF($N$2="",1,IF($N$2="(blank)",--(N6=""),IF($N$2="(nonblank)",--(N6<>""),--ISNUMBER(SEARCH($N$2,N6))))) | AZ6: =IF($O$2="",1,IF($O$2="(blank)",--(O6=""),IF($O$2="(nonblank)",--(O6<>""),--ISNUMBER(SEARCH($O$2,O6))))) | BA6: =IF($P$2="",1,IF($P$2="(blank)",--(P6=""),IF($P$2="(nonblank)",--(P6<>""),--ISNUMBER(SEARCH($P$2,P6))))) | BB6: =IF($Q$2="",1,IF($Q$2="(blank)",--(Q6=""),IF($Q$2="(nonblank)",--(Q6<>""),--ISNUMBER(SEARCH($Q$2,Q6))))) | BC6: =IF($R$2="",1,IF($R$2="(blank)",--(R6=""),IF($R$2="(nonblank)",--(R6<>""),--ISNUMBER(SEARCH($R$2,R6))))) | BD6: =IF($S$2="",1,IF($S$2="(blank)",--(S6=""),IF($S$2="(nonblank)",--(S6<>""),--ISNUMBER(SEARCH($S$2,S6))))) | BE6: =IF($T$2="",1,IF($T$2="(blank)",--(T6=""),IF($T$2="(nonblank)",--(T6<>""),--ISNUMBER(SEARCH($T$2,T6))))) | BF6: =IF($U$2="",1,IF($U$2="(blank)",--(U6=""),IF($U$2="(nonblank)",--(U6<>""),--ISNUMBER(SEARCH($U$2,U6))))) | BG6: =IF($V$2="",1,IF($V$2="(blank)",--(V6=""),IF($V$2="(nonblank)",--(V6<>""),--ISNUMBER(SEARCH($V$2,V6))))) | BH6: =IF($W$2="",1,IF($W$2="(blank)",--(W6=""),IF($W$2="(nonblank)",--(W6<>""),--ISNUMBER(SEARCH($W$2,W6))))) | BI6: =IF($X$2="",1,IF($X$2="(blank)",--(X6=""),IF($X$2="(nonblank)",--(X6<>""),--ISNUMBER(SEARCH($X$2,X6))))) | BJ6: =IF($Y$2="",1,IF($Y$2="(blank)",--(Y6=""),IF($Y$2="(nonblank)",--(Y6<>""),--ISNUMBER(SEARCH($Y$2,Y6))))) | BK6: =IF($Z$2="",1,IF($Z$2="(blank)",--(Z6=""),IF($Z$2="(nonblank)",--(Z6<>""),--ISNUMBER(SEARCH($Z$2,Z6))))) | BL6: =IF($AA$2="",1,IF($AA$2="(blank)",--(AA6=""),IF($AA$2="(nonblank)",--(AA6<>""),--ISNUMBER(SEARCH($AA$2,AA6))))) | BM6: =IF($AB$2="",1,IF($AB$2="(blank)",--(AB6=""),IF($AB$2="(nonblank)",--(AB6<>""),--ISNUMBER(SEARCH($AB$2,AB6))))) | BN6: =IF($AC$2="",1,IF($AC$2="(blank)",--(AC6=""),IF($AC$2="(nonblank)",--(AC6<>""),--ISNUMBER(SEARCH($AC$2,AC6))))) | BO6: =IF($AD$2="",1,IF($AD$2="(blank)",--(AD6=""),IF($AD$2="(nonblank)",--(AD6<>""),--ISNUMBER(SEARCH($AD$2,AD6))))) | BP6: =IF($AE$2="",1,IF($AE$2="(blank)",--(AE6=""),IF($AE$2="(nonblank)",--(AE6<>""),--ISNUMBER(SEARCH($AE$2,AE6))))) | BQ6: =IF($AF$2="",1,IF($AF$2="(blank)",--(AF6=""),IF($AF$2="(nonblank)",--(AF6<>""),--ISNUMBER(SEARCH($AF$2,AF6))))) | BR6: =IF($AG$2="",1,IF($AG$2="(blank)",--(AG6=""),IF($AG$2="(nonblank)",--(AG6<>""),--ISNUMBER(SEARCH($AG$2,AG6))))) | BS6: =IF($AH$2="",1,IF($AH$2="(blank)",--(AH6=""),IF($AH$2="(nonblank)",--(AH6<>""),--ISNUMBER(SEARCH($AH$2,AH6))))) | BT6: =IF(COUNTIF($AL6:$BS6,0)>0,0,1)
A7: 3000 | B7: Scrap of MS (extracted from equip cage and empty Sf6 gas cylinder) | C7: 66 | D7: 21977 | E7: KG | F7: 1876 | G7: F R KHANS ENTERPRISES | H7: 198000 | I7: =ROUND(H7*18%,0) | J7: =+H7+I7 | K7: =ROUND((H7+I7)*2%,0) | L7: =H7*0.1% | M7: =H7*2.25%*118% | N7: =H7*2.25%*2% | O7: =M7-N7 | P7: =ROUND(O7+L7,0) | Q7: 0 | R7: =ROUND(H7*Q7,0) | S7: =ROUND(H7*117.65%-R7,0) | T7: =ROUND(H7*25%,0) | U7: 49500 | V7: 11.08.2026 | W7: =ROUND(H7*92.65%-R7,0) | X7: =+W7+R7-1 | Y7: 20.08.2026 | Z7: =IF(IF(OR(AB7="",AB7=0),TODAY(),DATE(VALUE(RIGHT(AB7,4)),VALUE(MID(AB7,4,2)),VALUE(LEFT(AB7,2))))<=DATE(2026,8,24),0,H7*0.0118*CEILING((IF(OR(AB7="",AB7=0),TODAY(),DATE(VALUE(RIGHT(AB7,4)),VALUE(MID(AB7,4,2)),VALUE(LEFT(AB7,2))))-DATE(2026,8,22))/7,1)) | AC7: =U7+X7+AA7 | AD7: =S7-AC7 | AE7: =IF(AD7="","",IF(AD7<=5,"SETTLED","OUTSTANDING")) | AF7: DR2640100048 | AG7: 1800003347 | AH7: 27.08.2026 | AL7: =IF($A$2="",1,IF($A$2="(blank)",--(A7=""),IF($A$2="(nonblank)",--(A7<>""),--ISNUMBER(SEARCH($A$2,A7))))) | AM7: =IF($B$2="",1,IF($B$2="(blank)",--(B7=""),IF($B$2="(nonblank)",--(B7<>""),--ISNUMBER(SEARCH($B$2,B7))))) | AN7: =IF($C$2="",1,IF($C$2="(blank)",--(C7=""),IF($C$2="(nonblank)",--(C7<>""),--ISNUMBER(SEARCH($C$2,C7))))) | AO7: =IF($D$2="",1,IF($D$2="(blank)",--(D7=""),IF($D$2="(nonblank)",--(D7<>""),--ISNUMBER(SEARCH($D$2,D7))))) | AP7: =IF($E$2="",1,IF($E$2="(blank)",--(E7=""),IF($E$2="(nonblank)",--(E7<>""),--ISNUMBER(SEARCH($E$2,E7))))) | AQ7: =IF($F$2="",1,IF($F$2="(blank)",--(F7=""),IF($F$2="(nonblank)",--(F7<>""),--ISNUMBER(SEARCH($F$2,F7))))) | AR7: =IF($G$2="",1,IF($G$2="(blank)",--(G7=""),IF($G$2="(nonblank)",--(G7<>""),--ISNUMBER(SEARCH($G$2,G7))))) | AS7: =IF($H$2="",1,IF($H$2="(blank)",--(H7=""),IF($H$2="(nonblank)",--(H7<>""),--ISNUMBER(SEARCH($H$2,H7))))) | AT7: =IF($I$2="",1,IF($I$2="(blank)",--(I7=""),IF($I$2="(nonblank)",--(I7<>""),--ISNUMBER(SEARCH($I$2,I7))))) | AU7: =IF($J$2="",1,IF($J$2="(blank)",--(J7=""),IF($J$2="(nonblank)",--(J7<>""),--ISNUMBER(SEARCH($J$2,J7))))) | AV7: =IF($K$2="",1,IF($K$2="(blank)",--(K7=""),IF($K$2="(nonblank)",--(K7<>""),--ISNUMBER(SEARCH($K$2,K7))))) | AW7: =IF($L$2="",1,IF($L$2="(blank)",--(L7=""),IF($L$2="(nonblank)",--(L7<>""),--ISNUMBER(SEARCH($L$2,L7))))) | AX7: =IF($M$2="",1,IF($M$2="(blank)",--(M7=""),IF($M$2="(nonblank)",--(M7<>""),--ISNUMBER(SEARCH($M$2,M7))))) | AY7: =IF($N$2="",1,IF($N$2="(blank)",--(N7=""),IF($N$2="(nonblank)",--(N7<>""),--ISNUMBER(SEARCH($N$2,N7))))) | AZ7: =IF($O$2="",1,IF($O$2="(blank)",--(O7=""),IF($O$2="(nonblank)",--(O7<>""),--ISNUMBER(SEARCH($O$2,O7))))) | BA7: =IF($P$2="",1,IF($P$2="(blank)",--(P7=""),IF($P$2="(nonblank)",--(P7<>""),--ISNUMBER(SEARCH($P$2,P7))))) | BB7: =IF($Q$2="",1,IF($Q$2="(blank)",--(Q7=""),IF($Q$2="(nonblank)",--(Q7<>""),--ISNUMBER(SEARCH($Q$2,Q7))))) | BC7: =IF($R$2="",1,IF($R$2="(blank)",--(R7=""),IF($R$2="(nonblank)",--(R7<>""),--ISNUMBER(SEARCH($R$2,R7))))) | BD7: =IF($S$2="",1,IF($S$2="(blank)",--(S7=""),IF($S$2="(nonblank)",--(S7<>""),--ISNUMBER(SEARCH($S$2,S7))))) | BE7: =IF($T$2="",1,IF($T$2="(blank)",--(T7=""),IF($T$2="(nonblank)",--(T7<>""),--ISNUMBER(SEARCH($T$2,T7))))) | BF7: =IF($U$2="",1,IF($U$2="(blank)",--(U7=""),IF($U$2="(nonblank)",--(U7<>""),--ISNUMBER(SEARCH($U$2,U7))))) | BG7: =IF($V$2="",1,IF($V$2="(blank)",--(V7=""),IF($V$2="(nonblank)",--(V7<>""),--ISNUMBER(SEARCH($V$2,V7))))) | BH7: =IF($W$2="",1,IF($W$2="(blank)",--(W7=""),IF($W$2="(nonblank)",--(W7<>""),--ISNUMBER(SEARCH($W$2,W7))))) | BI7: =IF($X$2="",1,IF($X$2="(blank)",--(X7=""),IF($X$2="(nonblank)",--(X7<>""),--ISNUMBER(SEARCH($X$2,X7))))) | BJ7: =IF($Y$2="",1,IF($Y$2="(blank)",--(Y7=""),IF($Y$2="(nonblank)",--(Y7<>""),--ISNUMBER(SEARCH($Y$2,Y7))))) | BK7: =IF($Z$2="",1,IF($Z$2="(blank)",--(Z7=""),IF($Z$2="(nonblank)",--(Z7<>""),--ISNUMBER(SEARCH($Z$2,Z7))))) | BL7: =IF($AA$2="",1,IF($AA$2="(blank)",--(AA7=""),IF($AA$2="(nonblank)",--(AA7<>""),--ISNUMBER(SEARCH($AA$2,AA7))))) | BM7: =IF($AB$2="",1,IF($AB$2="(blank)",--(AB7=""),IF($AB$2="(nonblank)",--(AB7<>""),--ISNUMBER(SEARCH($AB$2,AB7))))) | BN7: =IF($AC$2="",1,IF($AC$2="(blank)",--(AC7=""),IF($AC$2="(nonblank)",--(AC7<>""),--ISNUMBER(SEARCH($AC$2,AC7))))) | BO7: =IF($AD$2="",1,IF($AD$2="(blank)",--(AD7=""),IF($AD$2="(nonblank)",--(AD7<>""),--ISNUMBER(SEARCH($AD$2,AD7))))) | BP7: =IF($AE$2="",1,IF($AE$2="(blank)",--(AE7=""),IF($AE$2="(nonblank)",--(AE7<>""),--ISNUMBER(SEARCH($AE$2,AE7))))) | BQ7: =IF($AF$2="",1,IF($AF$2="(blank)",--(AF7=""),IF($AF$2="(nonblank)",--(AF7<>""),--ISNUMBER(SEARCH($AF$2,AF7))))) | BR7: =IF($AG$2="",1,IF($AG$2="(blank)",--(AG7=""),IF($AG$2="(nonblank)",--(AG7<>""),--ISNUMBER(SEARCH($AG$2,AG7))))) | BS7: =IF($AH$2="",1,IF($AH$2="(blank)",--(AH7=""),IF($AH$2="(nonblank)",--(AH7<>""),--ISNUMBER(SEARCH($AH$2,AH7))))) | BT7: =IF(COUNTIF($AL7:$BS7,0)>0,0,1)
A8: 7253 | B8: SCRAP ACSR CONDUCTORS (Conductor Pieces) | C8: 227 | D8: 21980 | E8: KG | F8: 1923 | G8: OMKAR STEELS | H8: 1646431 | I8: =ROUND(H8*18%,0) | J8: =+H8+I8 | K8: =ROUND((H8+I8)*2%,0) | L8: =H8*0.1% | M8: =H8*2.25%*118% | N8: =H8*2.25%*2% | O8: =M8-N8 | P8: =ROUND(O8+L8,0) | Q8: 0.02 | R8: =ROUND(H8*Q8,0) | S8: =ROUND(H8*117.65%-R8,0) | T8: =ROUND(H8*25%,0) | U8: =+T8 | V8: 14.08.2026 | W8: =ROUND(H8*92.65%-R8,0) | X8: 1492490 | Y8: 24.08.2026 | Z8: =IF(IF(OR(AB8="",AB8=0),TODAY(),DATE(VALUE(RIGHT(AB8,4)),VALUE(MID(AB8,4,2)),VALUE(LEFT(AB8,2))))<=DATE(2026,8,24),0,H8*0.0118*CEILING((IF(OR(AB8="",AB8=0),TODAY(),DATE(VALUE(RIGHT(AB8,4)),VALUE(MID(AB8,4,2)),VALUE(LEFT(AB8,2))))-DATE(2026,8,22))/7,1)) | AC8: =U8+X8+AA8 | AD8: =S8-AC8 | AE8: =IF(AD8="","",IF(AD8<=5,"SETTLED","OUTSTANDING")) | AF8: DR2640100045 | AG8: 1800003315 | AH8: 27.08.2026 | AL8: =IF($A$2="",1,IF($A$2="(blank)",--(A8=""),IF($A$2="(nonblank)",--(A8<>""),--ISNUMBER(SEARCH($A$2,A8))))) | AM8: =IF($B$2="",1,IF($B$2="(blank)",--(B8=""),IF($B$2="(nonblank)",--(B8<>""),--ISNUMBER(SEARCH($B$2,B8))))) | AN8: =IF($C$2="",1,IF($C$2="(blank)",--(C8=""),IF($C$2="(nonblank)",--(C8<>""),--ISNUMBER(SEARCH($C$2,C8))))) | AO8: =IF($D$2="",1,IF($D$2="(blank)",--(D8=""),IF($D$2="(nonblank)",--(D8<>""),--ISNUMBER(SEARCH($D$2,D8))))) | AP8: =IF($E$2="",1,IF($E$2="(blank)",--(E8=""),IF($E$2="(nonblank)",--(E8<>""),--ISNUMBER(SEARCH($E$2,E8))))) | AQ8: =IF($F$2="",1,IF($F$2="(blank)",--(F8=""),IF($F$2="(nonblank)",--(F8<>""),--ISNUMBER(SEARCH($F$2,F8))))) | AR8: =IF($G$2="",1,IF($G$2="(blank)",--(G8=""),IF($G$2="(nonblank)",--(G8<>""),--ISNUMBER(SEARCH($G$2,G8))))) | AS8: =IF($H$2="",1,IF($H$2="(blank)",--(H8=""),IF($H$2="(nonblank)",--(H8<>""),--ISNUMBER(SEARCH($H$2,H8))))) | AT8: =IF($I$2="",1,IF($I$2="(blank)",--(I8=""),IF($I$2="(nonblank)",--(I8<>""),--ISNUMBER(SEARCH($I$2,I8))))) | AU8: =IF($J$2="",1,IF($J$2="(blank)",--(J8=""),IF($J$2="(nonblank)",--(J8<>""),--ISNUMBER(SEARCH($J$2,J8))))) | AV8: =IF($K$2="",1,IF($K$2="(blank)",--(K8=""),IF($K$2="(nonblank)",--(K8<>""),--ISNUMBER(SEARCH($K$2,K8))))) | AW8: =IF($L$2="",1,IF($L$2="(blank)",--(L8=""),IF($L$2="(nonblank)",--(L8<>""),--ISNUMBER(SEARCH($L$2,L8))))) | AX8: =IF($M$2="",1,IF($M$2="(blank)",--(M8=""),IF($M$2="(nonblank)",--(M8<>""),--ISNUMBER(SEARCH($M$2,M8))))) | AY8: =IF($N$2="",1,IF($N$2="(blank)",--(N8=""),IF($N$2="(nonblank)",--(N8<>""),--ISNUMBER(SEARCH($N$2,N8))))) | AZ8: =IF($O$2="",1,IF($O$2="(blank)",--(O8=""),IF($O$2="(nonblank)",--(O8<>""),--ISNUMBER(SEARCH($O$2,O8))))) | BA8: =IF($P$2="",1,IF($P$2="(blank)",--(P8=""),IF($P$2="(nonblank)",--(P8<>""),--ISNUMBER(SEARCH($P$2,P8))))) | BB8: =IF($Q$2="",1,IF($Q$2="(blank)",--(Q8=""),IF($Q$2="(nonblank)",--(Q8<>""),--ISNUMBER(SEARCH($Q$2,Q8))))) | BC8: =IF($R$2="",1,IF($R$2="(blank)",--(R8=""),IF($R$2="(nonblank)",--(R8<>""),--ISNUMBER(SEARCH($R$2,R8))))) | BD8: =IF($S$2="",1,IF($S$2="(blank)",--(S8=""),IF($S$2="(nonblank)",--(S8<>""),--ISNUMBER(SEARCH($S$2,S8))))) | BE8: =IF($T$2="",1,IF($T$2="(blank)",--(T8=""),IF($T$2="(nonblank)",--(T8<>""),--ISNUMBER(SEARCH($T$2,T8))))) | BF8: =IF($U$2="",1,IF($U$2="(blank)",--(U8=""),IF($U$2="(nonblank)",--(U8<>""),--ISNUMBER(SEARCH($U$2,U8))))) | BG8: =IF($V$2="",1,IF($V$2="(blank)",--(V8=""),IF($V$2="(nonblank)",--(V8<>""),--ISNUMBER(SEARCH($V$2,V8))))) | BH8: =IF($W$2="",1,IF($W$2="(blank)",--(W8=""),IF($W$2="(nonblank)",--(W8<>""),--ISNUMBER(SEARCH($W$2,W8))))) | BI8: =IF($X$2="",1,IF($X$2="(blank)",--(X8=""),IF($X$2="(nonblank)",--(X8<>""),--ISNUMBER(SEARCH($X$2,X8))))) | BJ8: =IF($Y$2="",1,IF($Y$2="(blank)",--(Y8=""),IF($Y$2="(nonblank)",--(Y8<>""),--ISNUMBER(SEARCH($Y$2,Y8))))) | BK8: =IF($Z$2="",1,IF($Z$2="(blank)",--(Z8=""),IF($Z$2="(nonblank)",--(Z8<>""),--ISNUMBER(SEARCH($Z$2,Z8))))) | BL8: =IF($AA$2="",1,IF($AA$2="(blank)",--(AA8=""),IF($AA$2="(nonblank)",--(AA8<>""),--ISNUMBER(SEARCH($AA$2,AA8))))) | BM8: =IF($AB$2="",1,IF($AB$2="(blank)",--(AB8=""),IF($AB$2="(nonblank)",--(AB8<>""),--ISNUMBER(SEARCH($AB$2,AB8))))) | BN8: =IF($AC$2="",1,IF($AC$2="(blank)",--(AC8=""),IF($AC$2="(nonblank)",--(AC8<>""),--ISNUMBER(SEARCH($AC$2,AC8))))) | BO8: =IF($AD$2="",1,IF($AD$2="(blank)",--(AD8=""),IF($AD$2="(nonblank)",--(AD8<>""),--ISNUMBER(SEARCH($AD$2,AD8))))) | BP8: =IF($AE$2="",1,IF($AE$2="(blank)",--(AE8=""),IF($AE$2="(nonblank)",--(AE8<>""),--ISNUMBER(SEARCH($AE$2,AE8))))) | BQ8: =IF($AF$2="",1,IF($AF$2="(blank)",--(AF8=""),IF($AF$2="(nonblank)",--(AF8<>""),--ISNUMBER(SEARCH($AF$2,AF8))))) | BR8: =IF($AG$2="",1,IF($AG$2="(blank)",--(AG8=""),IF($AG$2="(nonblank)",--(AG8<>""),--ISNUMBER(SEARCH($AG$2,AG8))))) | BS8: =IF($AH$2="",1,IF($AH$2="(blank)",--(AH8=""),IF($AH$2="(nonblank)",--(AH8<>""),--ISNUMBER(SEARCH($AH$2,AH8))))) | BT8: =IF(COUNTIF($AL8:$BS8,0)>0,0,1)
A9: 1 | B9: Scrap Power Transformer | C9: 2787314 | D9: 21977 | E9: NO | F9: 1976 | G9: SHAR JAHAN TRADERS | H9: 2787314 | I9: =ROUND(H9*18%,0) | J9: =+H9+I9 | K9: =ROUND((H9+I9)*2%,0) | L9: =H9*0.1% | M9: =H9*2.25%*118% | N9: =H9*2.25%*2% | O9: =M9-N9 | P9: =ROUND(O9+L9,0) | Q9: 0 | R9: =ROUND(H9*Q9,0) | S9: =ROUND(H9*117.65%-R9,0) | T9: =ROUND(H9*25%,0) | U9: =+T9 | V9: 13.08.2026 | W9: =ROUND(H9*92.65%-R9,0) | X9: 2582447.1 | Y9: 13.08.2026 | Z9: =IF(IF(OR(AB9="",AB9=0),TODAY(),DATE(VALUE(RIGHT(AB9,4)),VALUE(MID(AB9,4,2)),VALUE(LEFT(AB9,2))))<=DATE(2026,8,24),0,H9*0.0118*CEILING((IF(OR(AB9="",AB9=0),TODAY(),DATE(VALUE(RIGHT(AB9,4)),VALUE(MID(AB9,4,2)),VALUE(LEFT(AB9,2))))-DATE(2026,8,22))/7,1)) | AC9: =U9+X9+AA9 | AD9: =S9-AC9 | AE9: =IF(AD9="","",IF(AD9<=5,"SETTLED","OUTSTANDING")) | AF9: DR2640100023 | AG9: 1800003194 | AH9: 17.08.2026 | AL9: =IF($A$2="",1,IF($A$2="(blank)",--(A9=""),IF($A$2="(nonblank)",--(A9<>""),--ISNUMBER(SEARCH($A$2,A9))))) | AM9: =IF($B$2="",1,IF($B$2="(blank)",--(B9=""),IF($B$2="(nonblank)",--(B9<>""),--ISNUMBER(SEARCH($B$2,B9))))) | AN9: =IF($C$2="",1,IF($C$2="(blank)",--(C9=""),IF($C$2="(nonblank)",--(C9<>""),--ISNUMBER(SEARCH($C$2,C9))))) | AO9: =IF($D$2="",1,IF($D$2="(blank)",--(D9=""),IF($D$2="(nonblank)",--(D9<>""),--ISNUMBER(SEARCH($D$2,D9))))) | AP9: =IF($E$2="",1,IF($E$2="(blank)",--(E9=""),IF($E$2="(nonblank)",--(E9<>""),--ISNUMBER(SEARCH($E$2,E9))))) | AQ9: =IF($F$2="",1,IF($F$2="(blank)",--(F9=""),IF($F$2="(nonblank)",--(F9<>""),--ISNUMBER(SEARCH($F$2,F9))))) | AR9: =IF($G$2="",1,IF($G$2="(blank)",--(G9=""),IF($G$2="(nonblank)",--(G9<>""),--ISNUMBER(SEARCH($G$2,G9))))) | AS9: =IF($H$2="",1,IF($H$2="(blank)",--(H9=""),IF($H$2="(nonblank)",--(H9<>""),--ISNUMBER(SEARCH($H$2,H9))))) | AT9: =IF($I$2="",1,IF($I$2="(blank)",--(I9=""),IF($I$2="(nonblank)",--(I9<>""),--ISNUMBER(SEARCH($I$2,I9))))) | AU9: =IF($J$2="",1,IF($J$2="(blank)",--(J9=""),IF($J$2="(nonblank)",--(J9<>""),--ISNUMBER(SEARCH($J$2,J9))))) | AV9: =IF($K$2="",1,IF($K$2="(blank)",--(K9=""),IF($K$2="(nonblank)",--(K9<>""),--ISNUMBER(SEARCH($K$2,K9))))) | AW9: =IF($L$2="",1,IF($L$2="(blank)",--(L9=""),IF($L$2="(nonblank)",--(L9<>""),--ISNUMBER(SEARCH($L$2,L9))))) | AX9: =IF($M$2="",1,IF($M$2="(blank)",--(M9=""),IF($M$2="(nonblank)",--(M9<>""),--ISNUMBER(SEARCH($M$2,M9))))) | AY9: =IF($N$2="",1,IF($N$2="(blank)",--(N9=""),IF($N$2="(nonblank)",--(N9<>""),--ISNUMBER(SEARCH($N$2,N9))))) | AZ9: =IF($O$2="",1,IF($O$2="(blank)",--(O9=""),IF($O$2="(nonblank)",--(O9<>""),--ISNUMBER(SEARCH($O$2,O9))))) | BA9: =IF($P$2="",1,IF($P$2="(blank)",--(P9=""),IF($P$2="(nonblank)",--(P9<>""),--ISNUMBER(SEARCH($P$2,P9))))) | BB9: =IF($Q$2="",1,IF($Q$2="(blank)",--(Q9=""),IF($Q$2="(nonblank)",--(Q9<>""),--ISNUMBER(SEARCH($Q$2,Q9))))) | BC9: =IF($R$2="",1,IF($R$2="(blank)",--(R9=""),IF($R$2="(nonblank)",--(R9<>""),--ISNUMBER(SEARCH($R$2,R9))))) | BD9: =IF($S$2="",1,IF($S$2="(blank)",--(S9=""),IF($S$2="(nonblank)",--(S9<>""),--ISNUMBER(SEARCH($S$2,S9))))) | BE9: =IF($T$2="",1,IF($T$2="(blank)",--(T9=""),IF($T$2="(nonblank)",--(T9<>""),--ISNUMBER(SEARCH($T$2,T9))))) | BF9: =IF($U$2="",1,IF($U$2="(blank)",--(U9=""),IF($U$2="(nonblank)",--(U9<>""),--ISNUMBER(SEARCH($U$2,U9))))) | BG9: =IF($V$2="",1,IF($V$2="(blank)",--(V9=""),IF($V$2="(nonblank)",--(V9<>""),--ISNUMBER(SEARCH($V$2,V9))))) | BH9: =IF($W$2="",1,IF($W$2="(blank)",--(W9=""),IF($W$2="(nonblank)",--(W9<>""),--ISNUMBER(SEARCH($W$2,W9))))) | BI9: =IF($X$2="",1,IF($X$2="(blank)",--(X9=""),IF($X$2="(nonblank)",--(X9<>""),--ISNUMBER(SEARCH($X$2,X9))))) | BJ9: =IF($Y$2="",1,IF($Y$2="(blank)",--(Y9=""),IF($Y$2="(nonblank)",--(Y9<>""),--ISNUMBER(SEARCH($Y$2,Y9))))) | BK9: =IF($Z$2="",1,IF($Z$2="(blank)",--(Z9=""),IF($Z$2="(nonblank)",--(Z9<>""),--ISNUMBER(SEARCH($Z$2,Z9))))) | BL9: =IF($AA$2="",1,IF($AA$2="(blank)",--(AA9=""),IF($AA$2="(nonblank)",--(AA9<>""),--ISNUMBER(SEARCH($AA$2,AA9))))) | BM9: =IF($AB$2="",1,IF($AB$2="(blank)",--(AB9=""),IF($AB$2="(nonblank)",--(AB9<>""),--ISNUMBER(SEARCH($AB$2,AB9))))) | BN9: =IF($AC$2="",1,IF($AC$2="(blank)",--(AC9=""),IF($AC$2="(nonblank)",--(AC9<>""),--ISNUMBER(SEARCH($AC$2,AC9))))) | BO9: =IF($AD$2="",1,IF($AD$2="(blank)",--(AD9=""),IF($AD$2="(nonblank)",--(AD9<>""),--ISNUMBER(SEARCH($AD$2,AD9))))) | BP9: =IF($AE$2="",1,IF($AE$2="(blank)",--(AE9=""),IF($AE$2="(nonblank)",--(AE9<>""),--ISNUMBER(SEARCH($AE$2,AE9))))) | BQ9: =IF($AF$2="",1,IF($AF$2="(blank)",--(AF9=""),IF($AF$2="(nonblank)",--(AF9<>""),--ISNUMBER(SEARCH($AF$2,AF9))))) | BR9: =IF($AG$2="",1,IF($AG$2="(blank)",--(AG9=""),IF($AG$2="(nonblank)",--(AG9<>""),--ISNUMBER(SEARCH($AG$2,AG9))))) | BS9: =IF($AH$2="",1,IF($AH$2="(blank)",--(AH9=""),IF($AH$2="(nonblank)",--(AH9<>""),--ISNUMBER(SEARCH($AH$2,AH9))))) | BT9: =IF(COUNTIF($AL9:$BS9,0)>0,0,1)
A10: 4 | B10: Scrap of 132 KV CT | C10: 51511 | D10: 21977 | E10: NO | F10: 2002 | G10: NATIONAL ENTERPRISES | H10: 206044 | I10: =ROUND(H10*18%,0) | J10: =+H10+I10 | K10: =ROUND((H10+I10)*2%,0) | L10: =H10*0.1% | M10: =H10*2.25%*118% | N10: =H10*2.25%*2% | O10: =M10-N10 | P10: =ROUND(O10+L10,0) | Q10: 0 | R10: =ROUND(H10*Q10,0) | S10: =ROUND(H10*117.65%-R10,0) | T10: =ROUND(H10*25%,0) | U10: =+T10 | V10: 13.08.2026 | W10: =ROUND(H10*92.65%-R10,0) | X10: 190900 | Y10: 24.08.2026 | Z10: =IF(IF(OR(AB10="",AB10=0),TODAY(),DATE(VALUE(RIGHT(AB10,4)),VALUE(MID(AB10,4,2)),VALUE(LEFT(AB10,2))))<=DATE(2026,8,24),0,H10*0.0118*CEILING((IF(OR(AB10="",AB10=0),TODAY(),DATE(VALUE(RIGHT(AB10,4)),VALUE(MID(AB10,4,2)),VALUE(LEFT(AB10,2))))-DATE(2026,8,22))/7,1)) | AC10: =U10+X10+AA10 | AD10: =S10-AC10 | AE10: =IF(AD10="","",IF(AD10<=5,"SETTLED","OUTSTANDING")) | AF10: DR2640100031 | AG10: 1800003303 | AH10: 27.08.2026 | AL10: =IF($A$2="",1,IF($A$2="(blank)",--(A10=""),IF($A$2="(nonblank)",--(A10<>""),--ISNUMBER(SEARCH($A$2,A10))))) | AM10: =IF($B$2="",1,IF($B$2="(blank)",--(B10=""),IF($B$2="(nonblank)",--(B10<>""),--ISNUMBER(SEARCH($B$2,B10))))) | AN10: =IF($C$2="",1,IF($C$2="(blank)",--(C10=""),IF($C$2="(nonblank)",--(C10<>""),--ISNUMBER(SEARCH($C$2,C10))))) | AO10: =IF($D$2="",1,IF($D$2="(blank)",--(D10=""),IF($D$2="(nonblank)",--(D10<>""),--ISNUMBER(SEARCH($D$2,D10))))) | AP10: =IF($E$2="",1,IF($E$2="(blank)",--(E10=""),IF($E$2="(nonblank)",--(E10<>""),--ISNUMBER(SEARCH($E$2,E10))))) | AQ10: =IF($F$2="",1,IF($F$2="(blank)",--(F10=""),IF($F$2="(nonblank)",--(F10<>""),--ISNUMBER(SEARCH($F$2,F10))))) | AR10: =IF($G$2="",1,IF($G$2="(blank)",--(G10=""),IF($G$2="(nonblank)",--(G10<>""),--ISNUMBER(SEARCH($G$2,G10))))) | AS10: =IF($H$2="",1,IF($H$2="(blank)",--(H10=""),IF($H$2="(nonblank)",--(H10<>""),--ISNUMBER(SEARCH($H$2,H10))))) | AT10: =IF($I$2="",1,IF($I$2="(blank)",--(I10=""),IF($I$2="(nonblank)",--(I10<>""),--ISNUMBER(SEARCH($I$2,I10))))) | AU10: =IF($J$2="",1,IF($J$2="(blank)",--(J10=""),IF($J$2="(nonblank)",--(J10<>""),--ISNUMBER(SEARCH($J$2,J10))))) | AV10: =IF($K$2="",1,IF($K$2="(blank)",--(K10=""),IF($K$2="(nonblank)",--(K10<>""),--ISNUMBER(SEARCH($K$2,K10))))) | AW10: =IF($L$2="",1,IF($L$2="(blank)",--(L10=""),IF($L$2="(nonblank)",--(L10<>""),--ISNUMBER(SEARCH($L$2,L10))))) | AX10: =IF($M$2="",1,IF($M$2="(blank)",--(M10=""),IF($M$2="(nonblank)",--(M10<>""),--ISNUMBER(SEARCH($M$2,M10))))) | AY10: =IF($N$2="",1,IF($N$2="(blank)",--(N10=""),IF($N$2="(nonblank)",--(N10<>""),--ISNUMBER(SEARCH($N$2,N10))))) | AZ10: =IF($O$2="",1,IF($O$2="(blank)",--(O10=""),IF($O$2="(nonblank)",--(O10<>""),--ISNUMBER(SEARCH($O$2,O10))))) | BA10: =IF($P$2="",1,IF($P$2="(blank)",--(P10=""),IF($P$2="(nonblank)",--(P10<>""),--ISNUMBER(SEARCH($P$2,P10))))) | BB10: =IF($Q$2="",1,IF($Q$2="(blank)",--(Q10=""),IF($Q$2="(nonblank)",--(Q10<>""),--ISNUMBER(SEARCH($Q$2,Q10))))) | BC10: =IF($R$2="",1,IF($R$2="(blank)",--(R10=""),IF($R$2="(nonblank)",--(R10<>""),--ISNUMBER(SEARCH($R$2,R10))))) | BD10: =IF($S$2="",1,IF($S$2="(blank)",--(S10=""),IF($S$2="(nonblank)",--(S10<>""),--ISNUMBER(SEARCH($S$2,S10))))) | BE10: =IF($T$2="",1,IF($T$2="(blank)",--(T10=""),IF($T$2="(nonblank)",--(T10<>""),--ISNUMBER(SEARCH($T$2,T10))))) | BF10: =IF($U$2="",1,IF($U$2="(blank)",--(U10=""),IF($U$2="(nonblank)",--(U10<>""),--ISNUMBER(SEARCH($U$2,U10))))) | BG10: =IF($V$2="",1,IF($V$2="(blank)",--(V10=""),IF($V$2="(nonblank)",--(V10<>""),--ISNUMBER(SEARCH($V$2,V10))))) | BH10: =IF($W$2="",1,IF($W$2="(blank)",--(W10=""),IF($W$2="(nonblank)",--(W10<>""),--ISNUMBER(SEARCH($W$2,W10))))) | BI10: =IF($X$2="",1,IF($X$2="(blank)",--(X10=""),IF($X$2="(nonblank)",--(X10<>""),--ISNUMBER(SEARCH($X$2,X10))))) | BJ10: =IF($Y$2="",1,IF($Y$2="(blank)",--(Y10=""),IF($Y$2="(nonblank)",--(Y10<>""),--ISNUMBER(SEARCH($Y$2,Y10))))) | BK10: =IF($Z$2="",1,IF($Z$2="(blank)",--(Z10=""),IF($Z$2="(nonblank)",--(Z10<>""),--ISNUMBER(SEARCH($Z$2,Z10))))) | BL10: =IF($AA$2="",1,IF($AA$2="(blank)",--(AA10=""),IF($AA$2="(nonblank)",--(AA10<>""),--ISNUMBER(SEARCH($AA$2,AA10))))) | BM10: =IF($AB$2="",1,IF($AB$2="(blank)",--(AB10=""),IF($AB$2="(nonblank)",--(AB10<>""),--ISNUMBER(SEARCH($AB$2,AB10))))) | BN10: =IF($AC$2="",1,IF($AC$2="(blank)",--(AC10=""),IF($AC$2="(nonblank)",--(AC10<>""),--ISNUMBER(SEARCH($AC$2,AC10))))) | BO10: =IF($AD$2="",1,IF($AD$2="(blank)",--(AD10=""),IF($AD$2="(nonblank)",--(AD10<>""),--ISNUMBER(SEARCH($AD$2,AD10))))) | BP10: =IF($AE$2="",1,IF($AE$2="(blank)",--(AE10=""),IF($AE$2="(nonblank)",--(AE10<>""),--ISNUMBER(SEARCH($AE$2,AE10))))) | BQ10: =IF($AF$2="",1,IF($AF$2="(blank)",--(AF10=""),IF($AF$2="(nonblank)",--(AF10<>""),--ISNUMBER(SEARCH($AF$2,AF10))))) | BR10: =IF($AG$2="",1,IF($AG$2="(blank)",--(AG10=""),IF($AG$2="(nonblank)",--(AG10<>""),--ISNUMBER(SEARCH($AG$2,AG10))))) | BS10: =IF($AH$2="",1,IF($AH$2="(blank)",--(AH10=""),IF($AH$2="(nonblank)",--(AH10<>""),--ISNUMBER(SEARCH($AH$2,AH10))))) | BT10: =IF(COUNTIF($AL10:$BS10,0)>0,0,1)
A11: 1 | B11: Scrap of 145 KV CB | C11: 65007 | D11: 21977 | E11: NO | F11: 2003 | G11: NATIONAL ENTERPRISES | H11: 65007 | I11: =ROUND(H11*18%,0) | J11: =+H11+I11 | K11: =ROUND((H11+I11)*2%,0) | L11: =H11*0.1% | M11: =H11*2.25%*118% | N11: =H11*2.25%*2% | O11: =M11-N11 | P11: =ROUND(O11+L11,0) | Q11: 0 | R11: =ROUND(H11*Q11,0) | S11: =ROUND(H11*117.65%-R11,0) | T11: =ROUND(H11*25%,0) | U11: =+T11 | V11: 13.08.2026 | W11: =ROUND(H11*92.65%-R11,0) | X11: 60229 | Y11: 24.08.2026 | Z11: =IF(IF(OR(AB11="",AB11=0),TODAY(),DATE(VALUE(RIGHT(AB11,4)),VALUE(MID(AB11,4,2)),VALUE(LEFT(AB11,2))))<=DATE(2026,8,24),0,H11*0.0118*CEILING((IF(OR(AB11="",AB11=0),TODAY(),DATE(VALUE(RIGHT(AB11,4)),VALUE(MID(AB11,4,2)),VALUE(LEFT(AB11,2))))-DATE(2026,8,22))/7,1)) | AC11: =U11+X11+AA11 | AD11: =S11-AC11 | AE11: =IF(AD11="","",IF(AD11<=5,"SETTLED","OUTSTANDING")) | AF11: DR2640100032 | AG11: 1800003304 | AH11: 27.08.2026 | AL11: =IF($A$2="",1,IF($A$2="(blank)",--(A11=""),IF($A$2="(nonblank)",--(A11<>""),--ISNUMBER(SEARCH($A$2,A11))))) | AM11: =IF($B$2="",1,IF($B$2="(blank)",--(B11=""),IF($B$2="(nonblank)",--(B11<>""),--ISNUMBER(SEARCH($B$2,B11))))) | AN11: =IF($C$2="",1,IF($C$2="(blank)",--(C11=""),IF($C$2="(nonblank)",--(C11<>""),--ISNUMBER(SEARCH($C$2,C11))))) | AO11: =IF($D$2="",1,IF($D$2="(blank)",--(D11=""),IF($D$2="(nonblank)",--(D11<>""),--ISNUMBER(SEARCH($D$2,D11))))) | AP11: =IF($E$2="",1,IF($E$2="(blank)",--(E11=""),IF($E$2="(nonblank)",--(E11<>""),--ISNUMBER(SEARCH($E$2,E11))))) | AQ11: =IF($F$2="",1,IF($F$2="(blank)",--(F11=""),IF($F$2="(nonblank)",--(F11<>""),--ISNUMBER(SEARCH($F$2,F11))))) | AR11: =IF($G$2="",1,IF($G$2="(blank)",--(G11=""),IF($G$2="(nonblank)",--(G11<>""),--ISNUMBER(SEARCH($G$2,G11))))) | AS11: =IF($H$2="",1,IF($H$2="(blank)",--(H11=""),IF($H$2="(nonblank)",--(H11<>""),--ISNUMBER(SEARCH($H$2,H11))))) | AT11: =IF($I$2="",1,IF($I$2="(blank)",--(I11=""),IF($I$2="(nonblank)",--(I11<>""),--ISNUMBER(SEARCH($I$2,I11))))) | AU11: =IF($J$2="",1,IF($J$2="(blank)",--(J11=""),IF($J$2="(nonblank)",--(J11<>""),--ISNUMBER(SEARCH($J$2,J11))))) | AV11: =IF($K$2="",1,IF($K$2="(blank)",--(K11=""),IF($K$2="(nonblank)",--(K11<>""),--ISNUMBER(SEARCH($K$2,K11))))) | AW11: =IF($L$2="",1,IF($L$2="(blank)",--(L11=""),IF($L$2="(nonblank)",--(L11<>""),--ISNUMBER(SEARCH($L$2,L11))))) | AX11: =IF($M$2="",1,IF($M$2="(blank)",--(M11=""),IF($M$2="(nonblank)",--(M11<>""),--ISNUMBER(SEARCH($M$2,M11))))) | AY11: =IF($N$2="",1,IF($N$2="(blank)",--(N11=""),IF($N$2="(nonblank)",--(N11<>""),--ISNUMBER(SEARCH($N$2,N11))))) | AZ11: =IF($O$2="",1,IF($O$2="(blank)",--(O11=""),IF($O$2="(nonblank)",--(O11<>""),--ISNUMBER(SEARCH($O$2,O11))))) | BA11: =IF($P$2="",1,IF($P$2="(blank)",--(P11=""),IF($P$2="(nonblank)",--(P11<>""),--ISNUMBER(SEARCH($P$2,P11))))) | BB11: =IF($Q$2="",1,IF($Q$2="(blank)",--(Q11=""),IF($Q$2="(nonblank)",--(Q11<>""),--ISNUMBER(SEARCH($Q$2,Q11))))) | BC11: =IF($R$2="",1,IF($R$2="(blank)",--(R11=""),IF($R$2="(nonblank)",--(R11<>""),--ISNUMBER(SEARCH($R$2,R11))))) | BD11: =IF($S$2="",1,IF($S$2="(blank)",--(S11=""),IF($S$2="(nonblank)",--(S11<>""),--ISNUMBER(SEARCH($S$2,S11))))) | BE11: =IF($T$2="",1,IF($T$2="(blank)",--(T11=""),IF($T$2="(nonblank)",--(T11<>""),--ISNUMBER(SEARCH($T$2,T11))))) | BF11: =IF($U$2="",1,IF($U$2="(blank)",--(U11=""),IF($U$2="(nonblank)",--(U11<>""),--ISNUMBER(SEARCH($U$2,U11))))) | BG11: =IF($V$2="",1,IF($V$2="(blank)",--(V11=""),IF($V$2="(nonblank)",--(V11<>""),--ISNUMBER(SEARCH($V$2,V11))))) | BH11: =IF($W$2="",1,IF($W$2="(blank)",--(W11=""),IF($W$2="(nonblank)",--(W11<>""),--ISNUMBER(SEARCH($W$2,W11))))) | BI11: =IF($X$2="",1,IF($X$2="(blank)",--(X11=""),IF($X$2="(nonblank)",--(X11<>""),--ISNUMBER(SEARCH($X$2,X11))))) | BJ11: =IF($Y$2="",1,IF($Y$2="(blank)",--(Y11=""),IF($Y$2="(nonblank)",--(Y11<>""),--ISNUMBER(SEARCH($Y$2,Y11))))) | BK11: =IF($Z$2="",1,IF($Z$2="(blank)",--(Z11=""),IF($Z$2="(nonblank)",--(Z11<>""),--ISNUMBER(SEARCH($Z$2,Z11))))) | BL11: =IF($AA$2="",1,IF($AA$2="(blank)",--(AA11=""),IF($AA$2="(nonblank)",--(AA11<>""),--ISNUMBER(SEARCH($AA$2,AA11))))) | BM11: =IF($AB$2="",1,IF($AB$2="(blank)",--(AB11=""),IF($AB$2="(nonblank)",--(AB11<>""),--ISNUMBER(SEARCH($AB$2,AB11))))) | BN11: =IF($AC$2="",1,IF($AC$2="(blank)",--(AC11=""),IF($AC$2="(nonblank)",--(AC11<>""),--ISNUMBER(SEARCH($AC$2,AC11))))) | BO11: =IF($AD$2="",1,IF($AD$2="(blank)",--(AD11=""),IF($AD$2="(nonblank)",--(AD11<>""),--ISNUMBER(SEARCH($AD$2,AD11))))) | BP11: =IF($AE$2="",1,IF($AE$2="(blank)",--(AE11=""),IF($AE$2="(nonblank)",--(AE11<>""),--ISNUMBER(SEARCH($AE$2,AE11))))) | BQ11: =IF($AF$2="",1,IF($AF$2="(blank)",--(AF11=""),IF($AF$2="(nonblank)",--(AF11<>""),--ISNUMBER(SEARCH($AF$2,AF11))))) | BR11: =IF($AG$2="",1,IF($AG$2="(blank)",--(AG11=""),IF($AG$2="(nonblank)",--(AG11<>""),--ISNUMBER(SEARCH($AG$2,AG11))))) | BS11: =IF($AH$2="",1,IF($AH$2="(blank)",--(AH11=""),IF($AH$2="(nonblank)",--(AH11<>""),--ISNUMBER(SEARCH($AH$2,AH11))))) | BT11: =IF(COUNTIF($AL11:$BS11,0)>0,0,1)
A12: 1 | B12: Scrap of 220KV CT | C12: 70006 | D12: 21977 | E12: NO | F12: 2005 | G12: NATIONAL ENTERPRISES | H12: 70006 | I12: =ROUND(H12*18%,0) | J12: =+H12+I12 | K12: =ROUND((H12+I12)*2%,0) | L12: =H12*0.1% | M12: =H12*2.25%*118% | N12: =H12*2.25%*2% | O12: =M12-N12 | P12: =ROUND(O12+L12,0) | Q12: 0 | R12: =ROUND(H12*Q12,0) | S12: =ROUND(H12*117.65%-R12,0) | T12: =ROUND(H12*25%,0) | U12: =+T12 | V12: 13.08.2026 | W12: =ROUND(H12*92.65%-R12,0) | X12: 64859 | Y12: 24.08.2026 | Z12: =IF(IF(OR(AB12="",AB12=0),TODAY(),DATE(VALUE(RIGHT(AB12,4)),VALUE(MID(AB12,4,2)),VALUE(LEFT(AB12,2))))<=DATE(2026,8,24),0,H12*0.0118*CEILING((IF(OR(AB12="",AB12=0),TODAY(),DATE(VALUE(RIGHT(AB12,4)),VALUE(MID(AB12,4,2)),VALUE(LEFT(AB12,2))))-DATE(2026,8,22))/7,1)) | AC12: =U12+X12+AA12 | AD12: =S12-AC12 | AE12: =IF(AD12="","",IF(AD12<=5,"SETTLED","OUTSTANDING")) | AF12: DR2640100033 | AG12: 1800003305 | AH12: 27.08.2026 | AL12: =IF($A$2="",1,IF($A$2="(blank)",--(A12=""),IF($A$2="(nonblank)",--(A12<>""),--ISNUMBER(SEARCH($A$2,A12))))) | AM12: =IF($B$2="",1,IF($B$2="(blank)",--(B12=""),IF($B$2="(nonblank)",--(B12<>""),--ISNUMBER(SEARCH($B$2,B12))))) | AN12: =IF($C$2="",1,IF($C$2="(blank)",--(C12=""),IF($C$2="(nonblank)",--(C12<>""),--ISNUMBER(SEARCH($C$2,C12))))) | AO12: =IF($D$2="",1,IF($D$2="(blank)",--(D12=""),IF($D$2="(nonblank)",--(D12<>""),--ISNUMBER(SEARCH($D$2,D12))))) | AP12: =IF($E$2="",1,IF($E$2="(blank)",--(E12=""),IF($E$2="(nonblank)",--(E12<>""),--ISNUMBER(SEARCH($E$2,E12))))) | AQ12: =IF($F$2="",1,IF($F$2="(blank)",--(F12=""),IF($F$2="(nonblank)",--(F12<>""),--ISNUMBER(SEARCH($F$2,F12))))) | AR12: =IF($G$2="",1,IF($G$2="(blank)",--(G12=""),IF($G$2="(nonblank)",--(G12<>""),--ISNUMBER(SEARCH($G$2,G12))))) | AS12: =IF($H$2="",1,IF($H$2="(blank)",--(H12=""),IF($H$2="(nonblank)",--(H12<>""),--ISNUMBER(SEARCH($H$2,H12))))) | AT12: =IF($I$2="",1,IF($I$2="(blank)",--(I12=""),IF($I$2="(nonblank)",--(I12<>""),--ISNUMBER(SEARCH($I$2,I12))))) | AU12: =IF($J$2="",1,IF($J$2="(blank)",--(J12=""),IF($J$2="(nonblank)",--(J12<>""),--ISNUMBER(SEARCH($J$2,J12))))) | AV12: =IF($K$2="",1,IF($K$2="(blank)",--(K12=""),IF($K$2="(nonblank)",--(K12<>""),--ISNUMBER(SEARCH($K$2,K12))))) | AW12: =IF($L$2="",1,IF($L$2="(blank)",--(L12=""),IF($L$2="(nonblank)",--(L12<>""),--ISNUMBER(SEARCH($L$2,L12))))) | AX12: =IF($M$2="",1,IF($M$2="(blank)",--(M12=""),IF($M$2="(nonblank)",--(M12<>""),--ISNUMBER(SEARCH($M$2,M12))))) | AY12: =IF($N$2="",1,IF($N$2="(blank)",--(N12=""),IF($N$2="(nonblank)",--(N12<>""),--ISNUMBER(SEARCH($N$2,N12))))) | AZ12: =IF($O$2="",1,IF($O$2="(blank)",--(O12=""),IF($O$2="(nonblank)",--(O12<>""),--ISNUMBER(SEARCH($O$2,O12))))) | BA12: =IF($P$2="",1,IF($P$2="(blank)",--(P12=""),IF($P$2="(nonblank)",--(P12<>""),--ISNUMBER(SEARCH($P$2,P12))))) | BB12: =IF($Q$2="",1,IF($Q$2="(blank)",--(Q12=""),IF($Q$2="(nonblank)",--(Q12<>""),--ISNUMBER(SEARCH($Q$2,Q12))))) | BC12: =IF($R$2="",1,IF($R$2="(blank)",--(R12=""),IF($R$2="(nonblank)",--(R12<>""),--ISNUMBER(SEARCH($R$2,R12))))) | BD12: =IF($S$2="",1,IF($S$2="(blank)",--(S12=""),IF($S$2="(nonblank)",--(S12<>""),--ISNUMBER(SEARCH($S$2,S12))))) | BE12: =IF($T$2="",1,IF($T$2="(blank)",--(T12=""),IF($T$2="(nonblank)",--(T12<>""),--ISNUMBER(SEARCH($T$2,T12))))) | BF12: =IF($U$2="",1,IF($U$2="(blank)",--(U12=""),IF($U$2="(nonblank)",--(U12<>""),--ISNUMBER(SEARCH($U$2,U12))))) | BG12: =IF($V$2="",1,IF($V$2="(blank)",--(V12=""),IF($V$2="(nonblank)",--(V12<>""),--ISNUMBER(SEARCH($V$2,V12))))) | BH12: =IF($W$2="",1,IF($W$2="(blank)",--(W12=""),IF($W$2="(nonblank)",--(W12<>""),--ISNUMBER(SEARCH($W$2,W12))))) | BI12: =IF($X$2="",1,IF($X$2="(blank)",--(X12=""),IF($X$2="(nonblank)",--(X12<>""),--ISNUMBER(SEARCH($X$2,X12))))) | BJ12: =IF($Y$2="",1,IF($Y$2="(blank)",--(Y12=""),IF($Y$2="(nonblank)",--(Y12<>""),--ISNUMBER(SEARCH($Y$2,Y12))))) | BK12: =IF($Z$2="",1,IF($Z$2="(blank)",--(Z12=""),IF($Z$2="(nonblank)",--(Z12<>""),--ISNUMBER(SEARCH($Z$2,Z12))))) | BL12: =IF($AA$2="",1,IF($AA$2="(blank)",--(AA12=""),IF($AA$2="(nonblank)",--(AA12<>""),--ISNUMBER(SEARCH($AA$2,AA12))))) | BM12: =IF($AB$2="",1,IF($AB$2="(blank)",--(AB12=""),IF($AB$2="(nonblank)",--(AB12<>""),--ISNUMBER(SEARCH($AB$2,AB12))))) | BN12: =IF($AC$2="",1,IF($AC$2="(blank)",--(AC12=""),IF($AC$2="(nonblank)",--(AC12<>""),--ISNUMBER(SEARCH($AC$2,AC12))))) | BO12: =IF($AD$2="",1,IF($AD$2="(blank)",--(AD12=""),IF($AD$2="(nonblank)",--(AD12<>""),--ISNUMBER(SEARCH($AD$2,AD12))))) | BP12: =IF($AE$2="",1,IF($AE$2="(blank)",--(AE12=""),IF($AE$2="(nonblank)",--(AE12<>""),--ISNUMBER(SEARCH($AE$2,AE12))))) | BQ12: =IF($AF$2="",1,IF($AF$2="(blank)",--(AF12=""),IF($AF$2="(nonblank)",--(AF12<>""),--ISNUMBER(SEARCH($AF$2,AF12))))) | BR12: =IF($AG$2="",1,IF($AG$2="(blank)",--(AG12=""),IF($AG$2="(nonblank)",--(AG12<>""),--ISNUMBER(SEARCH($AG$2,AG12))))) | BS12: =IF($AH$2="",1,IF($AH$2="(blank)",--(AH12=""),IF($AH$2="(nonblank)",--(AH12<>""),--ISNUMBER(SEARCH($AH$2,AH12))))) | BT12: =IF(COUNTIF($AL12:$BS12,0)>0,0,1)
A13: 25 | B13: Scrap of empty oil drums | C13: 700 | D13: 21977 | E13: NO | F13: 2006 | G13: STERLING ENTERPRISES | H13: 17500 | I13: =ROUND(H13*18%,0) | J13: =+H13+I13 | K13: =ROUND((H13+I13)*2%,0) | L13: =H13*0.1% | M13: =H13*2.25%*118% | N13: =H13*2.25%*2% | O13: =M13-N13 | P13: =ROUND(O13+L13,0) | Q13: 0 | R13: =ROUND(H13*Q13,0) | S13: =ROUND(H13*117.65%-R13,0) | T13: =ROUND(H13*25%,0) | U13: 4375 | V13: 11.08.2026 | W13: =ROUND(H13*92.65%-R13,0) | X13: 16214 | Y13: 11.08.2026 | Z13: =IF(IF(OR(AB13="",AB13=0),TODAY(),DATE(VALUE(RIGHT(AB13,4)),VALUE(MID(AB13,4,2)),VALUE(LEFT(AB13,2))))<=DATE(2026,8,24),0,H13*0.0118*CEILING((IF(OR(AB13="",AB13=0),TODAY(),DATE(VALUE(RIGHT(AB13,4)),VALUE(MID(AB13,4,2)),VALUE(LEFT(AB13,2))))-DATE(2026,8,22))/7,1)) | AC13: =U13+X13+AA13 | AD13: =S13-AC13 | AE13: =IF(AD13="","",IF(AD13<=5,"SETTLED","OUTSTANDING")) | AF13: DR2640100018 | AG13: 1800003156 | AH13: 14.08.2026 | AL13: =IF($A$2="",1,IF($A$2="(blank)",--(A13=""),IF($A$2="(nonblank)",--(A13<>""),--ISNUMBER(SEARCH($A$2,A13))))) | AM13: =IF($B$2="",1,IF($B$2="(blank)",--(B13=""),IF($B$2="(nonblank)",--(B13<>""),--ISNUMBER(SEARCH($B$2,B13))))) | AN13: =IF($C$2="",1,IF($C$2="(blank)",--(C13=""),IF($C$2="(nonblank)",--(C13<>""),--ISNUMBER(SEARCH($C$2,C13))))) | AO13: =IF($D$2="",1,IF($D$2="(blank)",--(D13=""),IF($D$2="(nonblank)",--(D13<>""),--ISNUMBER(SEARCH($D$2,D13))))) | AP13: =IF($E$2="",1,IF($E$2="(blank)",--(E13=""),IF($E$2="(nonblank)",--(E13<>""),--ISNUMBER(SEARCH($E$2,E13))))) | AQ13: =IF($F$2="",1,IF($F$2="(blank)",--(F13=""),IF($F$2="(nonblank)",--(F13<>""),--ISNUMBER(SEARCH($F$2,F13))))) | AR13: =IF($G$2="",1,IF($G$2="(blank)",--(G13=""),IF($G$2="(nonblank)",--(G13<>""),--ISNUMBER(SEARCH($G$2,G13))))) | AS13: =IF($H$2="",1,IF($H$2="(blank)",--(H13=""),IF($H$2="(nonblank)",--(H13<>""),--ISNUMBER(SEARCH($H$2,H13))))) | AT13: =IF($I$2="",1,IF($I$2="(blank)",--(I13=""),IF($I$2="(nonblank)",--(I13<>""),--ISNUMBER(SEARCH($I$2,I13))))) | AU13: =IF($J$2="",1,IF($J$2="(blank)",--(J13=""),IF($J$2="(nonblank)",--(J13<>""),--ISNUMBER(SEARCH($J$2,J13))))) | AV13: =IF($K$2="",1,IF($K$2="(blank)",--(K13=""),IF($K$2="(nonblank)",--(K13<>""),--ISNUMBER(SEARCH($K$2,K13))))) | AW13: =IF($L$2="",1,IF($L$2="(blank)",--(L13=""),IF($L$2="(nonblank)",--(L13<>""),--ISNUMBER(SEARCH($L$2,L13))))) | AX13: =IF($M$2="",1,IF($M$2="(blank)",--(M13=""),IF($M$2="(nonblank)",--(M13<>""),--ISNUMBER(SEARCH($M$2,M13))))) | AY13: =IF($N$2="",1,IF($N$2="(blank)",--(N13=""),IF($N$2="(nonblank)",--(N13<>""),--ISNUMBER(SEARCH($N$2,N13))))) | AZ13: =IF($O$2="",1,IF($O$2="(blank)",--(O13=""),IF($O$2="(nonblank)",--(O13<>""),--ISNUMBER(SEARCH($O$2,O13))))) | BA13: =IF($P$2="",1,IF($P$2="(blank)",--(P13=""),IF($P$2="(nonblank)",--(P13<>""),--ISNUMBER(SEARCH($P$2,P13))))) | BB13: =IF($Q$2="",1,IF($Q$2="(blank)",--(Q13=""),IF($Q$2="(nonblank)",--(Q13<>""),--ISNUMBER(SEARCH($Q$2,Q13))))) | BC13: =IF($R$2="",1,IF($R$2="(blank)",--(R13=""),IF($R$2="(nonblank)",--(R13<>""),--ISNUMBER(SEARCH($R$2,R13))))) | BD13: =IF($S$2="",1,IF($S$2="(blank)",--(S13=""),IF($S$2="(nonblank)",--(S13<>""),--ISNUMBER(SEARCH($S$2,S13))))) | BE13: =IF($T$2="",1,IF($T$2="(blank)",--(T13=""),IF($T$2="(nonblank)",--(T13<>""),--ISNUMBER(SEARCH($T$2,T13))))) | BF13: =IF($U$2="",1,IF($U$2="(blank)",--(U13=""),IF($U$2="(nonblank)",--(U13<>""),--ISNUMBER(SEARCH($U$2,U13))))) | BG13: =IF($V$2="",1,IF($V$2="(blank)",--(V13=""),IF($V$2="(nonblank)",--(V13<>""),--ISNUMBER(SEARCH($V$2,V13))))) | BH13: =IF($W$2="",1,IF($W$2="(blank)",--(W13=""),IF($W$2="(nonblank)",--(W13<>""),--ISNUMBER(SEARCH($W$2,W13))))) | BI13: =IF($X$2="",1,IF($X$2="(blank)",--(X13=""),IF($X$2="(nonblank)",--(X13<>""),--ISNUMBER(SEARCH($X$2,X13))))) | BJ13: =IF($Y$2="",1,IF($Y$2="(blank)",--(Y13=""),IF($Y$2="(nonblank)",--(Y13<>""),--ISNUMBER(SEARCH($Y$2,Y13))))) | BK13: =IF($Z$2="",1,IF($Z$2="(blank)",--(Z13=""),IF($Z$2="(nonblank)",--(Z13<>""),--ISNUMBER(SEARCH($Z$2,Z13))))) | BL13: =IF($AA$2="",1,IF($AA$2="(blank)",--(AA13=""),IF($AA$2="(nonblank)",--(AA13<>""),--ISNUMBER(SEARCH($AA$2,AA13))))) | BM13: =IF($AB$2="",1,IF($AB$2="(blank)",--(AB13=""),IF($AB$2="(nonblank)",--(AB13<>""),--ISNUMBER(SEARCH($AB$2,AB13))))) | BN13: =IF($AC$2="",1,IF($AC$2="(blank)",--(AC13=""),IF($AC$2="(nonblank)",--(AC13<>""),--ISNUMBER(SEARCH($AC$2,AC13))))) | BO13: =IF($AD$2="",1,IF($AD$2="(blank)",--(AD13=""),IF($AD$2="(nonblank)",--(AD13<>""),--ISNUMBER(SEARCH($AD$2,AD13))))) | BP13: =IF($AE$2="",1,IF($AE$2="(blank)",--(AE13=""),IF($AE$2="(nonblank)",--(AE13<>""),--ISNUMBER(SEARCH($AE$2,AE13))))) | BQ13: =IF($AF$2="",1,IF($AF$2="(blank)",--(AF13=""),IF($AF$2="(nonblank)",--(AF13<>""),--ISNUMBER(SEARCH($AF$2,AF13))))) | BR13: =IF($AG$2="",1,IF($AG$2="(blank)",--(AG13=""),IF($AG$2="(nonblank)",--(AG13<>""),--ISNUMBER(SEARCH($AG$2,AG13))))) | BS13: =IF($AH$2="",1,IF($AH$2="(blank)",--(AH13=""),IF($AH$2="(nonblank)",--(AH13<>""),--ISNUMBER(SEARCH($AH$2,AH13))))) | BT13: =IF(COUNTIF($AL13:$BS13,0)>0,0,1)
A14: 1 | B14: SCRAP POWER TRANSFORMER | C14: 3857116 | D14: 21977 | E14: NO | F14: 2007 | G14: SHAR JAHAN TRADERS | H14: 3857116 | I14: =ROUND(H14*18%,0) | J14: =+H14+I14 | K14: =ROUND((H14+I14)*2%,0) | L14: =H14*0.1% | M14: =H14*2.25%*118% | N14: =H14*2.25%*2% | O14: =M14-N14 | P14: =ROUND(O14+L14,0) | Q14: 0 | R14: =ROUND(H14*Q14,0) | S14: =ROUND(H14*117.65%-R14,0) | T14: =ROUND(H14*25%,0) | U14: =+T14 | V14: 13.08.2026 | W14: =ROUND(H14*92.65%-R14,0) | X14: 3573618.9 | Y14: 13.08.2026 | Z14: =IF(IF(OR(AB14="",AB14=0),TODAY(),DATE(VALUE(RIGHT(AB14,4)),VALUE(MID(AB14,4,2)),VALUE(LEFT(AB14,2))))<=DATE(2026,8,24),0,H14*0.0118*CEILING((IF(OR(AB14="",AB14=0),TODAY(),DATE(VALUE(RIGHT(AB14,4)),VALUE(MID(AB14,4,2)),VALUE(LEFT(AB14,2))))-DATE(2026,8,22))/7,1)) | AC14: =U14+X14+AA14 | AD14: =S14-AC14 | AE14: =IF(AD14="","",IF(AD14<=5,"SETTLED","OUTSTANDING")) | AF14: DR2640100024 | AG14: 1800003196 | AH14: 17.08.2026 | AL14: =IF($A$2="",1,IF($A$2="(blank)",--(A14=""),IF($A$2="(nonblank)",--(A14<>""),--ISNUMBER(SEARCH($A$2,A14))))) | AM14: =IF($B$2="",1,IF($B$2="(blank)",--(B14=""),IF($B$2="(nonblank)",--(B14<>""),--ISNUMBER(SEARCH($B$2,B14))))) | AN14: =IF($C$2="",1,IF($C$2="(blank)",--(C14=""),IF($C$2="(nonblank)",--(C14<>""),--ISNUMBER(SEARCH($C$2,C14))))) | AO14: =IF($D$2="",1,IF($D$2="(blank)",--(D14=""),IF($D$2="(nonblank)",--(D14<>""),--ISNUMBER(SEARCH($D$2,D14))))) | AP14: =IF($E$2="",1,IF($E$2="(blank)",--(E14=""),IF($E$2="(nonblank)",--(E14<>""),--ISNUMBER(SEARCH($E$2,E14))))) | AQ14: =IF($F$2="",1,IF($F$2="(blank)",--(F14=""),IF($F$2="(nonblank)",--(F14<>""),--ISNUMBER(SEARCH($F$2,F14))))) | AR14: =IF($G$2="",1,IF($G$2="(blank)",--(G14=""),IF($G$2="(nonblank)",--(G14<>""),--ISNUMBER(SEARCH($G$2,G14))))) | AS14: =IF($H$2="",1,IF($H$2="(blank)",--(H14=""),IF($H$2="(nonblank)",--(H14<>""),--ISNUMBER(SEARCH($H$2,H14))))) | AT14: =IF($I$2="",1,IF($I$2="(blank)",--(I14=""),IF($I$2="(nonblank)",--(I14<>""),--ISNUMBER(SEARCH($I$2,I14))))) | AU14: =IF($J$2="",1,IF($J$2="(blank)",--(J14=""),IF($J$2="(nonblank)",--(J14<>""),--ISNUMBER(SEARCH($J$2,J14))))) | AV14: =IF($K$2="",1,IF($K$2="(blank)",--(K14=""),IF($K$2="(nonblank)",--(K14<>""),--ISNUMBER(SEARCH($K$2,K14))))) | AW14: =IF($L$2="",1,IF($L$2="(blank)",--(L14=""),IF($L$2="(nonblank)",--(L14<>""),--ISNUMBER(SEARCH($L$2,L14))))) | AX14: =IF($M$2="",1,IF($M$2="(blank)",--(M14=""),IF($M$2="(nonblank)",--(M14<>""),--ISNUMBER(SEARCH($M$2,M14))))) | AY14: =IF($N$2="",1,IF($N$2="(blank)",--(N14=""),IF($N$2="(nonblank)",--(N14<>""),--ISNUMBER(SEARCH($N$2,N14))))) | AZ14: =IF($O$2="",1,IF($O$2="(blank)",--(O14=""),IF($O$2="(nonblank)",--(O14<>""),--ISNUMBER(SEARCH($O$2,O14))))) | BA14: =IF($P$2="",1,IF($P$2="(blank)",--(P14=""),IF($P$2="(nonblank)",--(P14<>""),--ISNUMBER(SEARCH($P$2,P14))))) | BB14: =IF($Q$2="",1,IF($Q$2="(blank)",--(Q14=""),IF($Q$2="(nonblank)",--(Q14<>""),--ISNUMBER(SEARCH($Q$2,Q14))))) | BC14: =IF($R$2="",1,IF($R$2="(blank)",--(R14=""),IF($R$2="(nonblank)",--(R14<>""),--ISNUMBER(SEARCH($R$2,R14))))) | BD14: =IF($S$2="",1,IF($S$2="(blank)",--(S14=""),IF($S$2="(nonblank)",--(S14<>""),--ISNUMBER(SEARCH($S$2,S14))))) | BE14: =IF($T$2="",1,IF($T$2="(blank)",--(T14=""),IF($T$2="(nonblank)",--(T14<>""),--ISNUMBER(SEARCH($T$2,T14))))) | BF14: =IF($U$2="",1,IF($U$2="(blank)",--(U14=""),IF($U$2="(nonblank)",--(U14<>""),--ISNUMBER(SEARCH($U$2,U14))))) | BG14: =IF($V$2="",1,IF($V$2="(blank)",--(V14=""),IF($V$2="(nonblank)",--(V14<>""),--ISNUMBER(SEARCH($V$2,V14))))) | BH14: =IF($W$2="",1,IF($W$2="(blank)",--(W14=""),IF($W$2="(nonblank)",--(W14<>""),--ISNUMBER(SEARCH($W$2,W14))))) | BI14: =IF($X$2="",1,IF($X$2="(blank)",--(X14=""),IF($X$2="(nonblank)",--(X14<>""),--ISNUMBER(SEARCH($X$2,X14))))) | BJ14: =IF($Y$2="",1,IF($Y$2="(blank)",--(Y14=""),IF($Y$2="(nonblank)",--(Y14<>""),--ISNUMBER(SEARCH($Y$2,Y14))))) | BK14: =IF($Z$2="",1,IF($Z$2="(blank)",--(Z14=""),IF($Z$2="(nonblank)",--(Z14<>""),--ISNUMBER(SEARCH($Z$2,Z14))))) | BL14: =IF($AA$2="",1,IF($AA$2="(blank)",--(AA14=""),IF($AA$2="(nonblank)",--(AA14<>""),--ISNUMBER(SEARCH($AA$2,AA14))))) | BM14: =IF($AB$2="",1,IF($AB$2="(blank)",--(AB14=""),IF($AB$2="(nonblank)",--(AB14<>""),--ISNUMBER(SEARCH($AB$2,AB14))))) | BN14: =IF($AC$2="",1,IF($AC$2="(blank)",--(AC14=""),IF($AC$2="(nonblank)",--(AC14<>""),--ISNUMBER(SEARCH($AC$2,AC14))))) | BO14: =IF($AD$2="",1,IF($AD$2="(blank)",--(AD14=""),IF($AD$2="(nonblank)",--(AD14<>""),--ISNUMBER(SEARCH($AD$2,AD14))))) | BP14: =IF($AE$2="",1,IF($AE$2="(blank)",--(AE14=""),IF($AE$2="(nonblank)",--(AE14<>""),--ISNUMBER(SEARCH($AE$2,AE14))))) | BQ14: =IF($AF$2="",1,IF($AF$2="(blank)",--(AF14=""),IF($AF$2="(nonblank)",--(AF14<>""),--ISNUMBER(SEARCH($AF$2,AF14))))) | BR14: =IF($AG$2="",1,IF($AG$2="(blank)",--(AG14=""),IF($AG$2="(nonblank)",--(AG14<>""),--ISNUMBER(SEARCH($AG$2,AG14))))) | BS14: =IF($AH$2="",1,IF($AH$2="(blank)",--(AH14=""),IF($AH$2="(nonblank)",--(AH14<>""),--ISNUMBER(SEARCH($AH$2,AH14))))) | BT14: =IF(COUNTIF($AL14:$BS14,0)>0,0,1)
A15: 250 | B15: Scrap of empty oil Druam | C15: 543 | D15: 21977 | E15: NO | F15: 2008 | G15: HIND TRADERS | H15: 135750 | I15: =ROUND(H15*18%,0) | J15: =+H15+I15 | K15: =ROUND((H15+I15)*2%,0) | L15: =H15*0.1% | M15: =H15*2.25%*118% | N15: =H15*2.25%*2% | O15: =M15-N15 | P15: =ROUND(O15+L15,0) | Q15: 0 | R15: =ROUND(H15*Q15,0) | S15: =ROUND(H15*117.65%-R15,0) | T15: =ROUND(H15*25%,0) | U15: 33938 | V15: 14.08.2026 | W15: =ROUND(H15*92.65%-R15,0) | X15: 125772 | Y15: 18.08.2026 | Z15: =IF(IF(OR(AB15="",AB15=0),TODAY(),DATE(VALUE(RIGHT(AB15,4)),VALUE(MID(AB15,4,2)),VALUE(LEFT(AB15,2))))<=DATE(2026,8,24),0,H15*0.0118*CEILING((IF(OR(AB15="",AB15=0),TODAY(),DATE(VALUE(RIGHT(AB15,4)),VALUE(MID(AB15,4,2)),VALUE(LEFT(AB15,2))))-DATE(2026,8,22))/7,1)) | AC15: =U15+X15+AA15 | AD15: =S15-AC15 | AE15: =IF(AD15="","",IF(AD15<=5,"SETTLED","OUTSTANDING")) | AF15: DR2640100026 | AG15: 1800003247 | AH15: 20.08.2026 | AL15: =IF($A$2="",1,IF($A$2="(blank)",--(A15=""),IF($A$2="(nonblank)",--(A15<>""),--ISNUMBER(SEARCH($A$2,A15))))) | AM15: =IF($B$2="",1,IF($B$2="(blank)",--(B15=""),IF($B$2="(nonblank)",--(B15<>""),--ISNUMBER(SEARCH($B$2,B15))))) | AN15: =IF($C$2="",1,IF($C$2="(blank)",--(C15=""),IF($C$2="(nonblank)",--(C15<>""),--ISNUMBER(SEARCH($C$2,C15))))) | AO15: =IF($D$2="",1,IF($D$2="(blank)",--(D15=""),IF($D$2="(nonblank)",--(D15<>""),--ISNUMBER(SEARCH($D$2,D15))))) | AP15: =IF($E$2="",1,IF($E$2="(blank)",--(E15=""),IF($E$2="(nonblank)",--(E15<>""),--ISNUMBER(SEARCH($E$2,E15))))) | AQ15: =IF($F$2="",1,IF($F$2="(blank)",--(F15=""),IF($F$2="(nonblank)",--(F15<>""),--ISNUMBER(SEARCH($F$2,F15))))) | AR15: =IF($G$2="",1,IF($G$2="(blank)",--(G15=""),IF($G$2="(nonblank)",--(G15<>""),--ISNUMBER(SEARCH($G$2,G15))))) | AS15: =IF($H$2="",1,IF($H$2="(blank)",--(H15=""),IF($H$2="(nonblank)",--(H15<>""),--ISNUMBER(SEARCH($H$2,H15))))) | AT15: =IF($I$2="",1,IF($I$2="(blank)",--(I15=""),IF($I$2="(nonblank)",--(I15<>""),--ISNUMBER(SEARCH($I$2,I15))))) | AU15: =IF($J$2="",1,IF($J$2="(blank)",--(J15=""),IF($J$2="(nonblank)",--(J15<>""),--ISNUMBER(SEARCH($J$2,J15))))) | AV15: =IF($K$2="",1,IF($K$2="(blank)",--(K15=""),IF($K$2="(nonblank)",--(K15<>""),--ISNUMBER(SEARCH($K$2,K15))))) | AW15: =IF($L$2="",1,IF($L$2="(blank)",--(L15=""),IF($L$2="(nonblank)",--(L15<>""),--ISNUMBER(SEARCH($L$2,L15))))) | AX15: =IF($M$2="",1,IF($M$2="(blank)",--(M15=""),IF($M$2="(nonblank)",--(M15<>""),--ISNUMBER(SEARCH($M$2,M15))))) | AY15: =IF($N$2="",1,IF($N$2="(blank)",--(N15=""),IF($N$2="(nonblank)",--(N15<>""),--ISNUMBER(SEARCH($N$2,N15))))) | AZ15: =IF($O$2="",1,IF($O$2="(blank)",--(O15=""),IF($O$2="(nonblank)",--(O15<>""),--ISNUMBER(SEARCH($O$2,O15))))) | BA15: =IF($P$2="",1,IF($P$2="(blank)",--(P15=""),IF($P$2="(nonblank)",--(P15<>""),--ISNUMBER(SEARCH($P$2,P15))))) | BB15: =IF($Q$2="",1,IF($Q$2="(blank)",--(Q15=""),IF($Q$2="(nonblank)",--(Q15<>""),--ISNUMBER(SEARCH($Q$2,Q15))))) | BC15: =IF($R$2="",1,IF($R$2="(blank)",--(R15=""),IF($R$2="(nonblank)",--(R15<>""),--ISNUMBER(SEARCH($R$2,R15))))) | BD15: =IF($S$2="",1,IF($S$2="(blank)",--(S15=""),IF($S$2="(nonblank)",--(S15<>""),--ISNUMBER(SEARCH($S$2,S15))))) | BE15: =IF($T$2="",1,IF($T$2="(blank)",--(T15=""),IF($T$2="(nonblank)",--(T15<>""),--ISNUMBER(SEARCH($T$2,T15))))) | BF15: =IF($U$2="",1,IF($U$2="(blank)",--(U15=""),IF($U$2="(nonblank)",--(U15<>""),--ISNUMBER(SEARCH($U$2,U15))))) | BG15: =IF($V$2="",1,IF($V$2="(blank)",--(V15=""),IF($V$2="(nonblank)",--(V15<>""),--ISNUMBER(SEARCH($V$2,V15))))) | BH15: =IF($W$2="",1,IF($W$2="(blank)",--(W15=""),IF($W$2="(nonblank)",--(W15<>""),--ISNUMBER(SEARCH($W$2,W15))))) | BI15: =IF($X$2="",1,IF($X$2="(blank)",--(X15=""),IF($X$2="(nonblank)",--(X15<>""),--ISNUMBER(SEARCH($X$2,X15))))) | BJ15: =IF($Y$2="",1,IF($Y$2="(blank)",--(Y15=""),IF($Y$2="(nonblank)",--(Y15<>""),--ISNUMBER(SEARCH($Y$2,Y15))))) | BK15: =IF($Z$2="",1,IF($Z$2="(blank)",--(Z15=""),IF($Z$2="(nonblank)",--(Z15<>""),--ISNUMBER(SEARCH($Z$2,Z15))))) | BL15: =IF($AA$2="",1,IF($AA$2="(blank)",--(AA15=""),IF($AA$2="(nonblank)",--(AA15<>""),--ISNUMBER(SEARCH($AA$2,AA15))))) | BM15: =IF($AB$2="",1,IF($AB$2="(blank)",--(AB15=""),IF($AB$2="(nonblank)",--(AB15<>""),--ISNUMBER(SEARCH($AB$2,AB15))))) | BN15: =IF($AC$2="",1,IF($AC$2="(blank)",--(AC15=""),IF($AC$2="(nonblank)",--(AC15<>""),--ISNUMBER(SEARCH($AC$2,AC15))))) | BO15: =IF($AD$2="",1,IF($AD$2="(blank)",--(AD15=""),IF($AD$2="(nonblank)",--(AD15<>""),--ISNUMBER(SEARCH($AD$2,AD15))))) | BP15: =IF($AE$2="",1,IF($AE$2="(blank)",--(AE15=""),IF($AE$2="(nonblank)",--(AE15<>""),--ISNUMBER(SEARCH($AE$2,AE15))))) | BQ15: =IF($AF$2="",1,IF($AF$2="(blank)",--(AF15=""),IF($AF$2="(nonblank)",--(AF15<>""),--ISNUMBER(SEARCH($AF$2,AF15))))) | BR15: =IF($AG$2="",1,IF($AG$2="(blank)",--(AG15=""),IF($AG$2="(nonblank)",--(AG15<>""),--ISNUMBER(SEARCH($AG$2,AG15))))) | BS15: =IF($AH$2="",1,IF($AH$2="(blank)",--(AH15=""),IF($AH$2="(nonblank)",--(AH15<>""),--ISNUMBER(SEARCH($AH$2,AH15))))) | BT15: =IF(COUNTIF($AL15:$BS15,0)>0,0,1)
A16: 22 | B16: Scrap of empty oil Barrel | C16: 700 | D16: 21977 | E16: NO | F16: 2011 | G16: STERLING ENTERPRISES | H16: 15400 | I16: =ROUND(H16*18%,0) | J16: =+H16+I16 | K16: =ROUND((H16+I16)*2%,0) | L16: =H16*0.1% | M16: =H16*2.25%*118% | N16: =H16*2.25%*2% | O16: =M16-N16 | P16: =ROUND(O16+L16,0) | Q16: 0 | R16: =ROUND(H16*Q16,0) | S16: =ROUND(H16*117.65%-R16,0) | T16: =ROUND(H16*25%,0) | U16: 3850 | V16: 11.08.2026 | W16: =ROUND(H16*92.65%-R16,0) | X16: 14267 | Y16: 11.08.2026 | Z16: =IF(IF(OR(AB16="",AB16=0),TODAY(),DATE(VALUE(RIGHT(AB16,4)),VALUE(MID(AB16,4,2)),VALUE(LEFT(AB16,2))))<=DATE(2026,8,24),0,H16*0.0118*CEILING((IF(OR(AB16="",AB16=0),TODAY(),DATE(VALUE(RIGHT(AB16,4)),VALUE(MID(AB16,4,2)),VALUE(LEFT(AB16,2))))-DATE(2026,8,22))/7,1)) | AC16: =U16+X16+AA16 | AD16: =S16-AC16 | AE16: =IF(AD16="","",IF(AD16<=5,"SETTLED","OUTSTANDING")) | AF16: DR2640100019 | AG16: 1800003157 | AH16: 14.08.2026 | AL16: =IF($A$2="",1,IF($A$2="(blank)",--(A16=""),IF($A$2="(nonblank)",--(A16<>""),--ISNUMBER(SEARCH($A$2,A16))))) | AM16: =IF($B$2="",1,IF($B$2="(blank)",--(B16=""),IF($B$2="(nonblank)",--(B16<>""),--ISNUMBER(SEARCH($B$2,B16))))) | AN16: =IF($C$2="",1,IF($C$2="(blank)",--(C16=""),IF($C$2="(nonblank)",--(C16<>""),--ISNUMBER(SEARCH($C$2,C16))))) | AO16: =IF($D$2="",1,IF($D$2="(blank)",--(D16=""),IF($D$2="(nonblank)",--(D16<>""),--ISNUMBER(SEARCH($D$2,D16))))) | AP16: =IF($E$2="",1,IF($E$2="(blank)",--(E16=""),IF($E$2="(nonblank)",--(E16<>""),--ISNUMBER(SEARCH($E$2,E16))))) | AQ16: =IF($F$2="",1,IF($F$2="(blank)",--(F16=""),IF($F$2="(nonblank)",--(F16<>""),--ISNUMBER(SEARCH($F$2,F16))))) | AR16: =IF($G$2="",1,IF($G$2="(blank)",--(G16=""),IF($G$2="(nonblank)",--(G16<>""),--ISNUMBER(SEARCH($G$2,G16))))) | AS16: =IF($H$2="",1,IF($H$2="(blank)",--(H16=""),IF($H$2="(nonblank)",--(H16<>""),--ISNUMBER(SEARCH($H$2,H16))))) | AT16: =IF($I$2="",1,IF($I$2="(blank)",--(I16=""),IF($I$2="(nonblank)",--(I16<>""),--ISNUMBER(SEARCH($I$2,I16))))) | AU16: =IF($J$2="",1,IF($J$2="(blank)",--(J16=""),IF($J$2="(nonblank)",--(J16<>""),--ISNUMBER(SEARCH($J$2,J16))))) | AV16: =IF($K$2="",1,IF($K$2="(blank)",--(K16=""),IF($K$2="(nonblank)",--(K16<>""),--ISNUMBER(SEARCH($K$2,K16))))) | AW16: =IF($L$2="",1,IF($L$2="(blank)",--(L16=""),IF($L$2="(nonblank)",--(L16<>""),--ISNUMBER(SEARCH($L$2,L16))))) | AX16: =IF($M$2="",1,IF($M$2="(blank)",--(M16=""),IF($M$2="(nonblank)",--(M16<>""),--ISNUMBER(SEARCH($M$2,M16))))) | AY16: =IF($N$2="",1,IF($N$2="(blank)",--(N16=""),IF($N$2="(nonblank)",--(N16<>""),--ISNUMBER(SEARCH($N$2,N16))))) | AZ16: =IF($O$2="",1,IF($O$2="(blank)",--(O16=""),IF($O$2="(nonblank)",--(O16<>""),--ISNUMBER(SEARCH($O$2,O16))))) | BA16: =IF($P$2="",1,IF($P$2="(blank)",--(P16=""),IF($P$2="(nonblank)",--(P16<>""),--ISNUMBER(SEARCH($P$2,P16))))) | BB16: =IF($Q$2="",1,IF($Q$2="(blank)",--(Q16=""),IF($Q$2="(nonblank)",--(Q16<>""),--ISNUMBER(SEARCH($Q$2,Q16))))) | BC16: =IF($R$2="",1,IF($R$2="(blank)",--(R16=""),IF($R$2="(nonblank)",--(R16<>""),--ISNUMBER(SEARCH($R$2,R16))))) | BD16: =IF($S$2="",1,IF($S$2="(blank)",--(S16=""),IF($S$2="(nonblank)",--(S16<>""),--ISNUMBER(SEARCH($S$2,S16))))) | BE16: =IF($T$2="",1,IF($T$2="(blank)",--(T16=""),IF($T$2="(nonblank)",--(T16<>""),--ISNUMBER(SEARCH($T$2,T16))))) | BF16: =IF($U$2="",1,IF($U$2="(blank)",--(U16=""),IF($U$2="(nonblank)",--(U16<>""),--ISNUMBER(SEARCH($U$2,U16))))) | BG16: =IF($V$2="",1,IF($V$2="(blank)",--(V16=""),IF($V$2="(nonblank)",--(V16<>""),--ISNUMBER(SEARCH($V$2,V16))))) | BH16: =IF($W$2="",1,IF($W$2="(blank)",--(W16=""),IF($W$2="(nonblank)",--(W16<>""),--ISNUMBER(SEARCH($W$2,W16))))) | BI16: =IF($X$2="",1,IF($X$2="(blank)",--(X16=""),IF($X$2="(nonblank)",--(X16<>""),--ISNUMBER(SEARCH($X$2,X16))))) | BJ16: =IF($Y$2="",1,IF($Y$2="(blank)",--(Y16=""),IF($Y$2="(nonblank)",--(Y16<>""),--ISNUMBER(SEARCH($Y$2,Y16))))) | BK16: =IF($Z$2="",1,IF($Z$2="(blank)",--(Z16=""),IF($Z$2="(nonblank)",--(Z16<>""),--ISNUMBER(SEARCH($Z$2,Z16))))) | BL16: =IF($AA$2="",1,IF($AA$2="(blank)",--(AA16=""),IF($AA$2="(nonblank)",--(AA16<>""),--ISNUMBER(SEARCH($AA$2,AA16))))) | BM16: =IF($AB$2="",1,IF($AB$2="(blank)",--(AB16=""),IF($AB$2="(nonblank)",--(AB16<>""),--ISNUMBER(SEARCH($AB$2,AB16))))) | BN16: =IF($AC$2="",1,IF($AC$2="(blank)",--(AC16=""),IF($AC$2="(nonblank)",--(AC16<>""),--ISNUMBER(SEARCH($AC$2,AC16))))) | BO16: =IF($AD$2="",1,IF($AD$2="(blank)",--(AD16=""),IF($AD$2="(nonblank)",--(AD16<>""),--ISNUMBER(SEARCH($AD$2,AD16))))) | BP16: =IF($AE$2="",1,IF($AE$2="(blank)",--(AE16=""),IF($AE$2="(nonblank)",--(AE16<>""),--ISNUMBER(SEARCH($AE$2,AE16))))) | BQ16: =IF($AF$2="",1,IF($AF$2="(blank)",--(AF16=""),IF($AF$2="(nonblank)",--(AF16<>""),--ISNUMBER(SEARCH($AF$2,AF16))))) | BR16: =IF($AG$2="",1,IF($AG$2="(blank)",--(AG16=""),IF($AG$2="(nonblank)",--(AG16<>""),--ISNUMBER(SEARCH($AG$2,AG16))))) | BS16: =IF($AH$2="",1,IF($AH$2="(blank)",--(AH16=""),IF($AH$2="(nonblank)",--(AH16<>""),--ISNUMBER(SEARCH($AH$2,AH16))))) | BT16: =IF(COUNTIF($AL16:$BS16,0)>0,0,1)
A17: 100 | B17: Scrap of empty oil Barrels | C17: 710 | D17: 21978 | E17: NO | F17: 2015 | G17: STERLING ENTERPRISES | H17: 71000 | I17: =ROUND(H17*18%,0) | J17: =+H17+I17 | K17: =ROUND((H17+I17)*2%,0) | L17: =H17*0.1% | M17: =H17*2.25%*118% | N17: =H17*2.25%*2% | O17: =M17-N17 | P17: =ROUND(O17+L17,0) | Q17: 0 | R17: =ROUND(H17*Q17,0) | S17: =ROUND(H17*117.65%-R17,0) | T17: =ROUND(H17*25%,0) | U17: 17750 | V17: 11.08.2026 | W17: =ROUND(H17*92.65%-R17,0) | X17: =+W17 | Y17: 11.08.2026 | Z17: =IF(IF(OR(AB17="",AB17=0),TODAY(),DATE(VALUE(RIGHT(AB17,4)),VALUE(MID(AB17,4,2)),VALUE(LEFT(AB17,2))))<=DATE(2026,8,24),0,H17*0.0118*CEILING((IF(OR(AB17="",AB17=0),TODAY(),DATE(VALUE(RIGHT(AB17,4)),VALUE(MID(AB17,4,2)),VALUE(LEFT(AB17,2))))-DATE(2026,8,22))/7,1)) | AC17: =U17+X17+AA17 | AD17: =S17-AC17 | AE17: =IF(AD17="","",IF(AD17<=5,"SETTLED","OUTSTANDING")) | AF17: DR2640100020 | AG17: 1800003158 | AH17: 14.08.2026 | AL17: =IF($A$2="",1,IF($A$2="(blank)",--(A17=""),IF($A$2="(nonblank)",--(A17<>""),--ISNUMBER(SEARCH($A$2,A17))))) | AM17: =IF($B$2="",1,IF($B$2="(blank)",--(B17=""),IF($B$2="(nonblank)",--(B17<>""),--ISNUMBER(SEARCH($B$2,B17))))) | AN17: =IF($C$2="",1,IF($C$2="(blank)",--(C17=""),IF($C$2="(nonblank)",--(C17<>""),--ISNUMBER(SEARCH($C$2,C17))))) | AO17: =IF($D$2="",1,IF($D$2="(blank)",--(D17=""),IF($D$2="(nonblank)",--(D17<>""),--ISNUMBER(SEARCH($D$2,D17))))) | AP17: =IF($E$2="",1,IF($E$2="(blank)",--(E17=""),IF($E$2="(nonblank)",--(E17<>""),--ISNUMBER(SEARCH($E$2,E17))))) | AQ17: =IF($F$2="",1,IF($F$2="(blank)",--(F17=""),IF($F$2="(nonblank)",--(F17<>""),--ISNUMBER(SEARCH($F$2,F17))))) | AR17: =IF($G$2="",1,IF($G$2="(blank)",--(G17=""),IF($G$2="(nonblank)",--(G17<>""),--ISNUMBER(SEARCH($G$2,G17))))) | AS17: =IF($H$2="",1,IF($H$2="(blank)",--(H17=""),IF($H$2="(nonblank)",--(H17<>""),--ISNUMBER(SEARCH($H$2,H17))))) | AT17: =IF($I$2="",1,IF($I$2="(blank)",--(I17=""),IF($I$2="(nonblank)",--(I17<>""),--ISNUMBER(SEARCH($I$2,I17))))) | AU17: =IF($J$2="",1,IF($J$2="(blank)",--(J17=""),IF($J$2="(nonblank)",--(J17<>""),--ISNUMBER(SEARCH($J$2,J17))))) | AV17: =IF($K$2="",1,IF($K$2="(blank)",--(K17=""),IF($K$2="(nonblank)",--(K17<>""),--ISNUMBER(SEARCH($K$2,K17))))) | AW17: =IF($L$2="",1,IF($L$2="(blank)",--(L17=""),IF($L$2="(nonblank)",--(L17<>""),--ISNUMBER(SEARCH($L$2,L17))))) | AX17: =IF($M$2="",1,IF($M$2="(blank)",--(M17=""),IF($M$2="(nonblank)",--(M17<>""),--ISNUMBER(SEARCH($M$2,M17))))) | AY17: =IF($N$2="",1,IF($N$2="(blank)",--(N17=""),IF($N$2="(nonblank)",--(N17<>""),--ISNUMBER(SEARCH($N$2,N17))))) | AZ17: =IF($O$2="",1,IF($O$2="(blank)",--(O17=""),IF($O$2="(nonblank)",--(O17<>""),--ISNUMBER(SEARCH($O$2,O17))))) | BA17: =IF($P$2="",1,IF($P$2="(blank)",--(P17=""),IF($P$2="(nonblank)",--(P17<>""),--ISNUMBER(SEARCH($P$2,P17))))) | BB17: =IF($Q$2="",1,IF($Q$2="(blank)",--(Q17=""),IF($Q$2="(nonblank)",--(Q17<>""),--ISNUMBER(SEARCH($Q$2,Q17))))) | BC17: =IF($R$2="",1,IF($R$2="(blank)",--(R17=""),IF($R$2="(nonblank)",--(R17<>""),--ISNUMBER(SEARCH($R$2,R17))))) | BD17: =IF($S$2="",1,IF($S$2="(blank)",--(S17=""),IF($S$2="(nonblank)",--(S17<>""),--ISNUMBER(SEARCH($S$2,S17))))) | BE17: =IF($T$2="",1,IF($T$2="(blank)",--(T17=""),IF($T$2="(nonblank)",--(T17<>""),--ISNUMBER(SEARCH($T$2,T17))))) | BF17: =IF($U$2="",1,IF($U$2="(blank)",--(U17=""),IF($U$2="(nonblank)",--(U17<>""),--ISNUMBER(SEARCH($U$2,U17))))) | BG17: =IF($V$2="",1,IF($V$2="(blank)",--(V17=""),IF($V$2="(nonblank)",--(V17<>""),--ISNUMBER(SEARCH($V$2,V17))))) | BH17: =IF($W$2="",1,IF($W$2="(blank)",--(W17=""),IF($W$2="(nonblank)",--(W17<>""),--ISNUMBER(SEARCH($W$2,W17))))) | BI17: =IF($X$2="",1,IF($X$2="(blank)",--(X17=""),IF($X$2="(nonblank)",--(X17<>""),--ISNUMBER(SEARCH($X$2,X17))))) | BJ17: =IF($Y$2="",1,IF($Y$2="(blank)",--(Y17=""),IF($Y$2="(nonblank)",--(Y17<>""),--ISNUMBER(SEARCH($Y$2,Y17))))) | BK17: =IF($Z$2="",1,IF($Z$2="(blank)",--(Z17=""),IF($Z$2="(nonblank)",--(Z17<>""),--ISNUMBER(SEARCH($Z$2,Z17))))) | BL17: =IF($AA$2="",1,IF($AA$2="(blank)",--(AA17=""),IF($AA$2="(nonblank)",--(AA17<>""),--ISNUMBER(SEARCH($AA$2,AA17))))) | BM17: =IF($AB$2="",1,IF($AB$2="(blank)",--(AB17=""),IF($AB$2="(nonblank)",--(AB17<>""),--ISNUMBER(SEARCH($AB$2,AB17))))) | BN17: =IF($AC$2="",1,IF($AC$2="(blank)",--(AC17=""),IF($AC$2="(nonblank)",--(AC17<>""),--ISNUMBER(SEARCH($AC$2,AC17))))) | BO17: =IF($AD$2="",1,IF($AD$2="(blank)",--(AD17=""),IF($AD$2="(nonblank)",--(AD17<>""),--ISNUMBER(SEARCH($AD$2,AD17))))) | BP17: =IF($AE$2="",1,IF($AE$2="(blank)",--(AE17=""),IF($AE$2="(nonblank)",--(AE17<>""),--ISNUMBER(SEARCH($AE$2,AE17))))) | BQ17: =IF($AF$2="",1,IF($AF$2="(blank)",--(AF17=""),IF($AF$2="(nonblank)",--(AF17<>""),--ISNUMBER(SEARCH($AF$2,AF17))))) | BR17: =IF($AG$2="",1,IF($AG$2="(blank)",--(AG17=""),IF($AG$2="(nonblank)",--(AG17<>""),--ISNUMBER(SEARCH($AG$2,AG17))))) | BS17: =IF($AH$2="",1,IF($AH$2="(blank)",--(AH17=""),IF($AH$2="(nonblank)",--(AH17<>""),--ISNUMBER(SEARCH($AH$2,AH17))))) | BT17: =IF(COUNTIF($AL17:$BS17,0)>0,0,1)
A18: 1 | B18: Scrap of 220 KV Circuit Breaker | C18: 220001 | D18: 21978 | E18: NO | F18: 2018 | G18: NATIONAL ENTERPRISES | H18: 220001 | I18: =ROUND(H18*18%,0) | J18: =+H18+I18 | K18: =ROUND((H18+I18)*2%,0) | L18: =H18*0.1% | M18: =H18*2.25%*118% | N18: =H18*2.25%*2% | O18: =M18-N18 | P18: =ROUND(O18+L18,0) | Q18: 0 | R18: =ROUND(H18*Q18,0) | S18: =ROUND(H18*117.65%-R18,0) | T18: =ROUND(H18*25%,0) | U18: =+T18 | V18: 13.08.2026 | W18: =ROUND(H18*92.65%-R18,0) | X18: 203831 | Y18: 24.08.2026 | Z18: =IF(IF(OR(AB18="",AB18=0),TODAY(),DATE(VALUE(RIGHT(AB18,4)),VALUE(MID(AB18,4,2)),VALUE(LEFT(AB18,2))))<=DATE(2026,8,24),0,H18*0.0118*CEILING((IF(OR(AB18="",AB18=0),TODAY(),DATE(VALUE(RIGHT(AB18,4)),VALUE(MID(AB18,4,2)),VALUE(LEFT(AB18,2))))-DATE(2026,8,22))/7,1)) | AC18: =U18+X18+AA18 | AD18: =S18-AC18 | AE18: =IF(AD18="","",IF(AD18<=5,"SETTLED","OUTSTANDING")) | AF18: DR2640100034 | AG18: 1800003306 | AH18: 27.08.2026 | AL18: =IF($A$2="",1,IF($A$2="(blank)",--(A18=""),IF($A$2="(nonblank)",--(A18<>""),--ISNUMBER(SEARCH($A$2,A18))))) | AM18: =IF($B$2="",1,IF($B$2="(blank)",--(B18=""),IF($B$2="(nonblank)",--(B18<>""),--ISNUMBER(SEARCH($B$2,B18))))) | AN18: =IF($C$2="",1,IF($C$2="(blank)",--(C18=""),IF($C$2="(nonblank)",--(C18<>""),--ISNUMBER(SEARCH($C$2,C18))))) | AO18: =IF($D$2="",1,IF($D$2="(blank)",--(D18=""),IF($D$2="(nonblank)",--(D18<>""),--ISNUMBER(SEARCH($D$2,D18))))) | AP18: =IF($E$2="",1,IF($E$2="(blank)",--(E18=""),IF($E$2="(nonblank)",--(E18<>""),--ISNUMBER(SEARCH($E$2,E18))))) | AQ18: =IF($F$2="",1,IF($F$2="(blank)",--(F18=""),IF($F$2="(nonblank)",--(F18<>""),--ISNUMBER(SEARCH($F$2,F18))))) | AR18: =IF($G$2="",1,IF($G$2="(blank)",--(G18=""),IF($G$2="(nonblank)",--(G18<>""),--ISNUMBER(SEARCH($G$2,G18))))) | AS18: =IF($H$2="",1,IF($H$2="(blank)",--(H18=""),IF($H$2="(nonblank)",--(H18<>""),--ISNUMBER(SEARCH($H$2,H18))))) | AT18: =IF($I$2="",1,IF($I$2="(blank)",--(I18=""),IF($I$2="(nonblank)",--(I18<>""),--ISNUMBER(SEARCH($I$2,I18))))) | AU18: =IF($J$2="",1,IF($J$2="(blank)",--(J18=""),IF($J$2="(nonblank)",--(J18<>""),--ISNUMBER(SEARCH($J$2,J18))))) | AV18: =IF($K$2="",1,IF($K$2="(blank)",--(K18=""),IF($K$2="(nonblank)",--(K18<>""),--ISNUMBER(SEARCH($K$2,K18))))) | AW18: =IF($L$2="",1,IF($L$2="(blank)",--(L18=""),IF($L$2="(nonblank)",--(L18<>""),--ISNUMBER(SEARCH($L$2,L18))))) | AX18: =IF($M$2="",1,IF($M$2="(blank)",--(M18=""),IF($M$2="(nonblank)",--(M18<>""),--ISNUMBER(SEARCH($M$2,M18))))) | AY18: =IF($N$2="",1,IF($N$2="(blank)",--(N18=""),IF($N$2="(nonblank)",--(N18<>""),--ISNUMBER(SEARCH($N$2,N18))))) | AZ18: =IF($O$2="",1,IF($O$2="(blank)",--(O18=""),IF($O$2="(nonblank)",--(O18<>""),--ISNUMBER(SEARCH($O$2,O18))))) | BA18: =IF($P$2="",1,IF($P$2="(blank)",--(P18=""),IF($P$2="(nonblank)",--(P18<>""),--ISNUMBER(SEARCH($P$2,P18))))) | BB18: =IF($Q$2="",1,IF($Q$2="(blank)",--(Q18=""),IF($Q$2="(nonblank)",--(Q18<>""),--ISNUMBER(SEARCH($Q$2,Q18))))) | BC18: =IF($R$2="",1,IF($R$2="(blank)",--(R18=""),IF($R$2="(nonblank)",--(R18<>""),--ISNUMBER(SEARCH($R$2,R18))))) | BD18: =IF($S$2="",1,IF($S$2="(blank)",--(S18=""),IF($S$2="(nonblank)",--(S18<>""),--ISNUMBER(SEARCH($S$2,S18))))) | BE18: =IF($T$2="",1,IF($T$2="(blank)",--(T18=""),IF($T$2="(nonblank)",--(T18<>""),--ISNUMBER(SEARCH($T$2,T18))))) | BF18: =IF($U$2="",1,IF($U$2="(blank)",--(U18=""),IF($U$2="(nonblank)",--(U18<>""),--ISNUMBER(SEARCH($U$2,U18))))) | BG18: =IF($V$2="",1,IF($V$2="(blank)",--(V18=""),IF($V$2="(nonblank)",--(V18<>""),--ISNUMBER(SEARCH($V$2,V18))))) | BH18: =IF($W$2="",1,IF($W$2="(blank)",--(W18=""),IF($W$2="(nonblank)",--(W18<>""),--ISNUMBER(SEARCH($W$2,W18))))) | BI18: =IF($X$2="",1,IF($X$2="(blank)",--(X18=""),IF($X$2="(nonblank)",--(X18<>""),--ISNUMBER(SEARCH($X$2,X18))))) | BJ18: =IF($Y$2="",1,IF($Y$2="(blank)",--(Y18=""),IF($Y$2="(nonblank)",--(Y18<>""),--ISNUMBER(SEARCH($Y$2,Y18))))) | BK18: =IF($Z$2="",1,IF($Z$2="(blank)",--(Z18=""),IF($Z$2="(nonblank)",--(Z18<>""),--ISNUMBER(SEARCH($Z$2,Z18))))) | BL18: =IF($AA$2="",1,IF($AA$2="(blank)",--(AA18=""),IF($AA$2="(nonblank)",--(AA18<>""),--ISNUMBER(SEARCH($AA$2,AA18))))) | BM18: =IF($AB$2="",1,IF($AB$2="(blank)",--(AB18=""),IF($AB$2="(nonblank)",--(AB18<>""),--ISNUMBER(SEARCH($AB$2,AB18))))) | BN18: =IF($AC$2="",1,IF($AC$2="(blank)",--(AC18=""),IF($AC$2="(nonblank)",--(AC18<>""),--ISNUMBER(SEARCH($AC$2,AC18))))) | BO18: =IF($AD$2="",1,IF($AD$2="(blank)",--(AD18=""),IF($AD$2="(nonblank)",--(AD18<>""),--ISNUMBER(SEARCH($AD$2,AD18))))) | BP18: =IF($AE$2="",1,IF($AE$2="(blank)",--(AE18=""),IF($AE$2="(nonblank)",--(AE18<>""),--ISNUMBER(SEARCH($AE$2,AE18))))) | BQ18: =IF($AF$2="",1,IF($AF$2="(blank)",--(AF18=""),IF($AF$2="(nonblank)",--(AF18<>""),--ISNUMBER(SEARCH($AF$2,AF18))))) | BR18: =IF($AG$2="",1,IF($AG$2="(blank)",--(AG18=""),IF($AG$2="(nonblank)",--(AG18<>""),--ISNUMBER(SEARCH($AG$2,AG18))))) | BS18: =IF($AH$2="",1,IF($AH$2="(blank)",--(AH18=""),IF($AH$2="(nonblank)",--(AH18<>""),--ISNUMBER(SEARCH($AH$2,AH18))))) | BT18: =IF(COUNTIF($AL18:$BS18,0)>0,0,1)
A19: 1 | B19: Scrap of 220 KV Circuit Breaker | C19: 210001 | D19: 21978 | E19: NO | F19: 2019 | G19: NATIONAL ENTERPRISES | H19: 210001 | I19: =ROUND(H19*18%,0) | J19: =+H19+I19 | K19: =ROUND((H19+I19)*2%,0) | L19: =H19*0.1% | M19: =H19*2.25%*118% | N19: =H19*2.25%*2% | O19: =M19-N19 | P19: =ROUND(O19+L19,0) | Q19: 0 | R19: =ROUND(H19*Q19,0) | S19: =ROUND(H19*117.65%-R19,0) | T19: =ROUND(H19*25%,0) | U19: =+T19 | V19: 13.08.2026 | W19: =ROUND(H19*92.65%-R19,0) | X19: 194566 | Y19: 24.08.2026 | Z19: =IF(IF(OR(AB19="",AB19=0),TODAY(),DATE(VALUE(RIGHT(AB19,4)),VALUE(MID(AB19,4,2)),VALUE(LEFT(AB19,2))))<=DATE(2026,8,24),0,H19*0.0118*CEILING((IF(OR(AB19="",AB19=0),TODAY(),DATE(VALUE(RIGHT(AB19,4)),VALUE(MID(AB19,4,2)),VALUE(LEFT(AB19,2))))-DATE(2026,8,22))/7,1)) | AC19: =U19+X19+AA19 | AD19: =S19-AC19 | AE19: =IF(AD19="","",IF(AD19<=5,"SETTLED","OUTSTANDING")) | AF19: DR2640100035 | AG19: 1800003307 | AH19: 27.08.2026 | AL19: =IF($A$2="",1,IF($A$2="(blank)",--(A19=""),IF($A$2="(nonblank)",--(A19<>""),--ISNUMBER(SEARCH($A$2,A19))))) | AM19: =IF($B$2="",1,IF($B$2="(blank)",--(B19=""),IF($B$2="(nonblank)",--(B19<>""),--ISNUMBER(SEARCH($B$2,B19))))) | AN19: =IF($C$2="",1,IF($C$2="(blank)",--(C19=""),IF($C$2="(nonblank)",--(C19<>""),--ISNUMBER(SEARCH($C$2,C19))))) | AO19: =IF($D$2="",1,IF($D$2="(blank)",--(D19=""),IF($D$2="(nonblank)",--(D19<>""),--ISNUMBER(SEARCH($D$2,D19))))) | AP19: =IF($E$2="",1,IF($E$2="(blank)",--(E19=""),IF($E$2="(nonblank)",--(E19<>""),--ISNUMBER(SEARCH($E$2,E19))))) | AQ19: =IF($F$2="",1,IF($F$2="(blank)",--(F19=""),IF($F$2="(nonblank)",--(F19<>""),--ISNUMBER(SEARCH($F$2,F19))))) | AR19: =IF($G$2="",1,IF($G$2="(blank)",--(G19=""),IF($G$2="(nonblank)",--(G19<>""),--ISNUMBER(SEARCH($G$2,G19))))) | AS19: =IF($H$2="",1,IF($H$2="(blank)",--(H19=""),IF($H$2="(nonblank)",--(H19<>""),--ISNUMBER(SEARCH($H$2,H19))))) | AT19: =IF($I$2="",1,IF($I$2="(blank)",--(I19=""),IF($I$2="(nonblank)",--(I19<>""),--ISNUMBER(SEARCH($I$2,I19))))) | AU19: =IF($J$2="",1,IF($J$2="(blank)",--(J19=""),IF($J$2="(nonblank)",--(J19<>""),--ISNUMBER(SEARCH($J$2,J19))))) | AV19: =IF($K$2="",1,IF($K$2="(blank)",--(K19=""),IF($K$2="(nonblank)",--(K19<>""),--ISNUMBER(SEARCH($K$2,K19))))) | AW19: =IF($L$2="",1,IF($L$2="(blank)",--(L19=""),IF($L$2="(nonblank)",--(L19<>""),--ISNUMBER(SEARCH($L$2,L19))))) | AX19: =IF($M$2="",1,IF($M$2="(blank)",--(M19=""),IF($M$2="(nonblank)",--(M19<>""),--ISNUMBER(SEARCH($M$2,M19))))) | AY19: =IF($N$2="",1,IF($N$2="(blank)",--(N19=""),IF($N$2="(nonblank)",--(N19<>""),--ISNUMBER(SEARCH($N$2,N19))))) | AZ19: =IF($O$2="",1,IF($O$2="(blank)",--(O19=""),IF($O$2="(nonblank)",--(O19<>""),--ISNUMBER(SEARCH($O$2,O19))))) | BA19: =IF($P$2="",1,IF($P$2="(blank)",--(P19=""),IF($P$2="(nonblank)",--(P19<>""),--ISNUMBER(SEARCH($P$2,P19))))) | BB19: =IF($Q$2="",1,IF($Q$2="(blank)",--(Q19=""),IF($Q$2="(nonblank)",--(Q19<>""),--ISNUMBER(SEARCH($Q$2,Q19))))) | BC19: =IF($R$2="",1,IF($R$2="(blank)",--(R19=""),IF($R$2="(nonblank)",--(R19<>""),--ISNUMBER(SEARCH($R$2,R19))))) | BD19: =IF($S$2="",1,IF($S$2="(blank)",--(S19=""),IF($S$2="(nonblank)",--(S19<>""),--ISNUMBER(SEARCH($S$2,S19))))) | BE19: =IF($T$2="",1,IF($T$2="(blank)",--(T19=""),IF($T$2="(nonblank)",--(T19<>""),--ISNUMBER(SEARCH($T$2,T19))))) | BF19: =IF($U$2="",1,IF($U$2="(blank)",--(U19=""),IF($U$2="(nonblank)",--(U19<>""),--ISNUMBER(SEARCH($U$2,U19))))) | BG19: =IF($V$2="",1,IF($V$2="(blank)",--(V19=""),IF($V$2="(nonblank)",--(V19<>""),--ISNUMBER(SEARCH($V$2,V19))))) | BH19: =IF($W$2="",1,IF($W$2="(blank)",--(W19=""),IF($W$2="(nonblank)",--(W19<>""),--ISNUMBER(SEARCH($W$2,W19))))) | BI19: =IF($X$2="",1,IF($X$2="(blank)",--(X19=""),IF($X$2="(nonblank)",--(X19<>""),--ISNUMBER(SEARCH($X$2,X19))))) | BJ19: =IF($Y$2="",1,IF($Y$2="(blank)",--(Y19=""),IF($Y$2="(nonblank)",--(Y19<>""),--ISNUMBER(SEARCH($Y$2,Y19))))) | BK19: =IF($Z$2="",1,IF($Z$2="(blank)",--(Z19=""),IF($Z$2="(nonblank)",--(Z19<>""),--ISNUMBER(SEARCH($Z$2,Z19))))) | BL19: =IF($AA$2="",1,IF($AA$2="(blank)",--(AA19=""),IF($AA$2="(nonblank)",--(AA19<>""),--ISNUMBER(SEARCH($AA$2,AA19))))) | BM19: =IF($AB$2="",1,IF($AB$2="(blank)",--(AB19=""),IF($AB$2="(nonblank)",--(AB19<>""),--ISNUMBER(SEARCH($AB$2,AB19))))) | BN19: =IF($AC$2="",1,IF($AC$2="(blank)",--(AC19=""),IF($AC$2="(nonblank)",--(AC19<>""),--ISNUMBER(SEARCH($AC$2,AC19))))) | BO19: =IF($AD$2="",1,IF($AD$2="(blank)",--(AD19=""),IF($AD$2="(nonblank)",--(AD19<>""),--ISNUMBER(SEARCH($AD$2,AD19))))) | BP19: =IF($AE$2="",1,IF($AE$2="(blank)",--(AE19=""),IF($AE$2="(nonblank)",--(AE19<>""),--ISNUMBER(SEARCH($AE$2,AE19))))) | BQ19: =IF($AF$2="",1,IF($AF$2="(blank)",--(AF19=""),IF($AF$2="(nonblank)",--(AF19<>""),--ISNUMBER(SEARCH($AF$2,AF19))))) | BR19: =IF($AG$2="",1,IF($AG$2="(blank)",--(AG19=""),IF($AG$2="(nonblank)",--(AG19<>""),--ISNUMBER(SEARCH($AG$2,AG19))))) | BS19: =IF($AH$2="",1,IF($AH$2="(blank)",--(AH19=""),IF($AH$2="(nonblank)",--(AH19<>""),--ISNUMBER(SEARCH($AH$2,AH19))))) | BT19: =IF(COUNTIF($AL19:$BS19,0)>0,0,1)
A20: 3500 | B20: SCRAP 80MM² AAAC EARTHWIRE | C20: 333 | D20: 21978 | E20: KG | F20: 2020 | G20: OMKAR STEELS | H20: 1165500 | I20: =ROUND(H20*18%,0) | J20: =+H20+I20 | K20: =ROUND((H20+I20)*2%,0) | L20: =H20*0.1% | M20: =H20*2.25%*118% | N20: =H20*2.25%*2% | O20: =M20-N20 | P20: =ROUND(O20+L20,0) | Q20: 0.02 | R20: =ROUND(H20*Q20,0) | S20: =ROUND(H20*117.65%-R20,0) | T20: =ROUND(H20*25%,0) | U20: 291375 | V20: 10.08.2026 | W20: =ROUND(H20*92.65%-R20,0) | X20: 1056525 | Y20: 10.08.2026 | Z20: =IF(IF(OR(AB20="",AB20=0),TODAY(),DATE(VALUE(RIGHT(AB20,4)),VALUE(MID(AB20,4,2)),VALUE(LEFT(AB20,2))))<=DATE(2026,8,24),0,H20*0.0118*CEILING((IF(OR(AB20="",AB20=0),TODAY(),DATE(VALUE(RIGHT(AB20,4)),VALUE(MID(AB20,4,2)),VALUE(LEFT(AB20,2))))-DATE(2026,8,22))/7,1)) | AC20: =U20+X20+AA20 | AD20: =S20-AC20 | AE20: =IF(AD20="","",IF(AD20<=5,"SETTLED","OUTSTANDING")) | AF20: DR2640100017 | AG20: 1800003065 | AH20: 12.08.2026 | AL20: =IF($A$2="",1,IF($A$2="(blank)",--(A20=""),IF($A$2="(nonblank)",--(A20<>""),--ISNUMBER(SEARCH($A$2,A20))))) | AM20: =IF($B$2="",1,IF($B$2="(blank)",--(B20=""),IF($B$2="(nonblank)",--(B20<>""),--ISNUMBER(SEARCH($B$2,B20))))) | AN20: =IF($C$2="",1,IF($C$2="(blank)",--(C20=""),IF($C$2="(nonblank)",--(C20<>""),--ISNUMBER(SEARCH($C$2,C20))))) | AO20: =IF($D$2="",1,IF($D$2="(blank)",--(D20=""),IF($D$2="(nonblank)",--(D20<>""),--ISNUMBER(SEARCH($D$2,D20))))) | AP20: =IF($E$2="",1,IF($E$2="(blank)",--(E20=""),IF($E$2="(nonblank)",--(E20<>""),--ISNUMBER(SEARCH($E$2,E20))))) | AQ20: =IF($F$2="",1,IF($F$2="(blank)",--(F20=""),IF($F$2="(nonblank)",--(F20<>""),--ISNUMBER(SEARCH($F$2,F20))))) | AR20: =IF($G$2="",1,IF($G$2="(blank)",--(G20=""),IF($G$2="(nonblank)",--(G20<>""),--ISNUMBER(SEARCH($G$2,G20))))) | AS20: =IF($H$2="",1,IF($H$2="(blank)",--(H20=""),IF($H$2="(nonblank)",--(H20<>""),--ISNUMBER(SEARCH($H$2,H20))))) | AT20: =IF($I$2="",1,IF($I$2="(blank)",--(I20=""),IF($I$2="(nonblank)",--(I20<>""),--ISNUMBER(SEARCH($I$2,I20))))) | AU20: =IF($J$2="",1,IF($J$2="(blank)",--(J20=""),IF($J$2="(nonblank)",--(J20<>""),--ISNUMBER(SEARCH($J$2,J20))))) | AV20: =IF($K$2="",1,IF($K$2="(blank)",--(K20=""),IF($K$2="(nonblank)",--(K20<>""),--ISNUMBER(SEARCH($K$2,K20))))) | AW20: =IF($L$2="",1,IF($L$2="(blank)",--(L20=""),IF($L$2="(nonblank)",--(L20<>""),--ISNUMBER(SEARCH($L$2,L20))))) | AX20: =IF($M$2="",1,IF($M$2="(blank)",--(M20=""),IF($M$2="(nonblank)",--(M20<>""),--ISNUMBER(SEARCH($M$2,M20))))) | AY20: =IF($N$2="",1,IF($N$2="(blank)",--(N20=""),IF($N$2="(nonblank)",--(N20<>""),--ISNUMBER(SEARCH($N$2,N20))))) | AZ20: =IF($O$2="",1,IF($O$2="(blank)",--(O20=""),IF($O$2="(nonblank)",--(O20<>""),--ISNUMBER(SEARCH($O$2,O20))))) | BA20: =IF($P$2="",1,IF($P$2="(blank)",--(P20=""),IF($P$2="(nonblank)",--(P20<>""),--ISNUMBER(SEARCH($P$2,P20))))) | BB20: =IF($Q$2="",1,IF($Q$2="(blank)",--(Q20=""),IF($Q$2="(nonblank)",--(Q20<>""),--ISNUMBER(SEARCH($Q$2,Q20))))) | BC20: =IF($R$2="",1,IF($R$2="(blank)",--(R20=""),IF($R$2="(nonblank)",--(R20<>""),--ISNUMBER(SEARCH($R$2,R20))))) | BD20: =IF($S$2="",1,IF($S$2="(blank)",--(S20=""),IF($S$2="(nonblank)",--(S20<>""),--ISNUMBER(SEARCH($S$2,S20))))) | BE20: =IF($T$2="",1,IF($T$2="(blank)",--(T20=""),IF($T$2="(nonblank)",--(T20<>""),--ISNUMBER(SEARCH($T$2,T20))))) | BF20: =IF($U$2="",1,IF($U$2="(blank)",--(U20=""),IF($U$2="(nonblank)",--(U20<>""),--ISNUMBER(SEARCH($U$2,U20))))) | BG20: =IF($V$2="",1,IF($V$2="(blank)",--(V20=""),IF($V$2="(nonblank)",--(V20<>""),--ISNUMBER(SEARCH($V$2,V20))))) | BH20: =IF($W$2="",1,IF($W$2="(blank)",--(W20=""),IF($W$2="(nonblank)",--(W20<>""),--ISNUMBER(SEARCH($W$2,W20))))) | BI20: =IF($X$2="",1,IF($X$2="(blank)",--(X20=""),IF($X$2="(nonblank)",--(X20<>""),--ISNUMBER(SEARCH($X$2,X20))))) | BJ20: =IF($Y$2="",1,IF($Y$2="(blank)",--(Y20=""),IF($Y$2="(nonblank)",--(Y20<>""),--ISNUMBER(SEARCH($Y$2,Y20))))) | BK20: =IF($Z$2="",1,IF($Z$2="(blank)",--(Z20=""),IF($Z$2="(nonblank)",--(Z20<>""),--ISNUMBER(SEARCH($Z$2,Z20))))) | BL20: =IF($AA$2="",1,IF($AA$2="(blank)",--(AA20=""),IF($AA$2="(nonblank)",--(AA20<>""),--ISNUMBER(SEARCH($AA$2,AA20))))) | BM20: =IF($AB$2="",1,IF($AB$2="(blank)",--(AB20=""),IF($AB$2="(nonblank)",--(AB20<>""),--ISNUMBER(SEARCH($AB$2,AB20))))) | BN20: =IF($AC$2="",1,IF($AC$2="(blank)",--(AC20=""),IF($AC$2="(nonblank)",--(AC20<>""),--ISNUMBER(SEARCH($AC$2,AC20))))) | BO20: =IF($AD$2="",1,IF($AD$2="(blank)",--(AD20=""),IF($AD$2="(nonblank)",--(AD20<>""),--ISNUMBER(SEARCH($AD$2,AD20))))) | BP20: =IF($AE$2="",1,IF($AE$2="(blank)",--(AE20=""),IF($AE$2="(nonblank)",--(AE20<>""),--ISNUMBER(SEARCH($AE$2,AE20))))) | BQ20: =IF($AF$2="",1,IF($AF$2="(blank)",--(AF20=""),IF($AF$2="(nonblank)",--(AF20<>""),--ISNUMBER(SEARCH($AF$2,AF20))))) | BR20: =IF($AG$2="",1,IF($AG$2="(blank)",--(AG20=""),IF($AG$2="(nonblank)",--(AG20<>""),--ISNUMBER(SEARCH($AG$2,AG20))))) | BS20: =IF($AH$2="",1,IF($AH$2="(blank)",--(AH20=""),IF($AH$2="(nonblank)",--(AH20<>""),--ISNUMBER(SEARCH($AH$2,AH20))))) | BT20: =IF(COUNTIF($AL20:$BS20,0)>0,0,1)
A21: 3 | B21: Scrap of 132 KV CT | C21: 110200 | D21: 21978 | E21: NO | F21: 2022 | G21: NATIONAL SCRAP AND BUILDING MATERIAL SUPPLIER | H21: 330600 | I21: =ROUND(H21*18%,0) | J21: =+H21+I21 | K21: =ROUND((H21+I21)*2%,0) | L21: =H21*0.1% | M21: =H21*2.25%*118% | N21: =H21*2.25%*2% | O21: =M21-N21 | P21: =ROUND(O21+L21,0) | Q21: 0 | R21: =ROUND(H21*Q21,0) | S21: =ROUND(H21*117.65%-R21,0) | T21: =ROUND(H21*25%,0) | U21: =+T21 | V21: 14.08.2026 | W21: =ROUND(H21*92.65%-R21,0) | X21: 306301 | Y21: 21.08.2026 | Z21: =IF(IF(OR(AB21="",AB21=0),TODAY(),DATE(VALUE(RIGHT(AB21,4)),VALUE(MID(AB21,4,2)),VALUE(LEFT(AB21,2))))<=DATE(2026,8,24),0,H21*0.0118*CEILING((IF(OR(AB21="",AB21=0),TODAY(),DATE(VALUE(RIGHT(AB21,4)),VALUE(MID(AB21,4,2)),VALUE(LEFT(AB21,2))))-DATE(2026,8,22))/7,1)) | AC21: =U21+X21+AA21 | AD21: =S21-AC21 | AE21: =IF(AD21="","",IF(AD21<=5,"SETTLED","OUTSTANDING")) | AF21: DR2640100028 | AG21: 1800003269 | AH21: 24.08.2026 | AL21: =IF($A$2="",1,IF($A$2="(blank)",--(A21=""),IF($A$2="(nonblank)",--(A21<>""),--ISNUMBER(SEARCH($A$2,A21))))) | AM21: =IF($B$2="",1,IF($B$2="(blank)",--(B21=""),IF($B$2="(nonblank)",--(B21<>""),--ISNUMBER(SEARCH($B$2,B21))))) | AN21: =IF($C$2="",1,IF($C$2="(blank)",--(C21=""),IF($C$2="(nonblank)",--(C21<>""),--ISNUMBER(SEARCH($C$2,C21))))) | AO21: =IF($D$2="",1,IF($D$2="(blank)",--(D21=""),IF($D$2="(nonblank)",--(D21<>""),--ISNUMBER(SEARCH($D$2,D21))))) | AP21: =IF($E$2="",1,IF($E$2="(blank)",--(E21=""),IF($E$2="(nonblank)",--(E21<>""),--ISNUMBER(SEARCH($E$2,E21))))) | AQ21: =IF($F$2="",1,IF($F$2="(blank)",--(F21=""),IF($F$2="(nonblank)",--(F21<>""),--ISNUMBER(SEARCH($F$2,F21))))) | AR21: =IF($G$2="",1,IF($G$2="(blank)",--(G21=""),IF($G$2="(nonblank)",--(G21<>""),--ISNUMBER(SEARCH($G$2,G21))))) | AS21: =IF($H$2="",1,IF($H$2="(blank)",--(H21=""),IF($H$2="(nonblank)",--(H21<>""),--ISNUMBER(SEARCH($H$2,H21))))) | AT21: =IF($I$2="",1,IF($I$2="(blank)",--(I21=""),IF($I$2="(nonblank)",--(I21<>""),--ISNUMBER(SEARCH($I$2,I21))))) | AU21: =IF($J$2="",1,IF($J$2="(blank)",--(J21=""),IF($J$2="(nonblank)",--(J21<>""),--ISNUMBER(SEARCH($J$2,J21))))) | AV21: =IF($K$2="",1,IF($K$2="(blank)",--(K21=""),IF($K$2="(nonblank)",--(K21<>""),--ISNUMBER(SEARCH($K$2,K21))))) | AW21: =IF($L$2="",1,IF($L$2="(blank)",--(L21=""),IF($L$2="(nonblank)",--(L21<>""),--ISNUMBER(SEARCH($L$2,L21))))) | AX21: =IF($M$2="",1,IF($M$2="(blank)",--(M21=""),IF($M$2="(nonblank)",--(M21<>""),--ISNUMBER(SEARCH($M$2,M21))))) | AY21: =IF($N$2="",1,IF($N$2="(blank)",--(N21=""),IF($N$2="(nonblank)",--(N21<>""),--ISNUMBER(SEARCH($N$2,N21))))) | AZ21: =IF($O$2="",1,IF($O$2="(blank)",--(O21=""),IF($O$2="(nonblank)",--(O21<>""),--ISNUMBER(SEARCH($O$2,O21))))) | BA21: =IF($P$2="",1,IF($P$2="(blank)",--(P21=""),IF($P$2="(nonblank)",--(P21<>""),--ISNUMBER(SEARCH($P$2,P21))))) | BB21: =IF($Q$2="",1,IF($Q$2="(blank)",--(Q21=""),IF($Q$2="(nonblank)",--(Q21<>""),--ISNUMBER(SEARCH($Q$2,Q21))))) | BC21: =IF($R$2="",1,IF($R$2="(blank)",--(R21=""),IF($R$2="(nonblank)",--(R21<>""),--ISNUMBER(SEARCH($R$2,R21))))) | BD21: =IF($S$2="",1,IF($S$2="(blank)",--(S21=""),IF($S$2="(nonblank)",--(S21<>""),--ISNUMBER(SEARCH($S$2,S21))))) | BE21: =IF($T$2="",1,IF($T$2="(blank)",--(T21=""),IF($T$2="(nonblank)",--(T21<>""),--ISNUMBER(SEARCH($T$2,T21))))) | BF21: =IF($U$2="",1,IF($U$2="(blank)",--(U21=""),IF($U$2="(nonblank)",--(U21<>""),--ISNUMBER(SEARCH($U$2,U21))))) | BG21: =IF($V$2="",1,IF($V$2="(blank)",--(V21=""),IF($V$2="(nonblank)",--(V21<>""),--ISNUMBER(SEARCH($V$2,V21))))) | BH21: =IF($W$2="",1,IF($W$2="(blank)",--(W21=""),IF($W$2="(nonblank)",--(W21<>""),--ISNUMBER(SEARCH($W$2,W21))))) | BI21: =IF($X$2="",1,IF($X$2="(blank)",--(X21=""),IF($X$2="(nonblank)",--(X21<>""),--ISNUMBER(SEARCH($X$2,X21))))) | BJ21: =IF($Y$2="",1,IF($Y$2="(blank)",--(Y21=""),IF($Y$2="(nonblank)",--(Y21<>""),--ISNUMBER(SEARCH($Y$2,Y21))))) | BK21: =IF($Z$2="",1,IF($Z$2="(blank)",--(Z21=""),IF($Z$2="(nonblank)",--(Z21<>""),--ISNUMBER(SEARCH($Z$2,Z21))))) | BL21: =IF($AA$2="",1,IF($AA$2="(blank)",--(AA21=""),IF($AA$2="(nonblank)",--(AA21<>""),--ISNUMBER(SEARCH($AA$2,AA21))))) | BM21: =IF($AB$2="",1,IF($AB$2="(blank)",--(AB21=""),IF($AB$2="(nonblank)",--(AB21<>""),--ISNUMBER(SEARCH($AB$2,AB21))))) | BN21: =IF($AC$2="",1,IF($AC$2="(blank)",--(AC21=""),IF($AC$2="(nonblank)",--(AC21<>""),--ISNUMBER(SEARCH($AC$2,AC21))))) | BO21: =IF($AD$2="",1,IF($AD$2="(blank)",--(AD21=""),IF($AD$2="(nonblank)",--(AD21<>""),--ISNUMBER(SEARCH($AD$2,AD21))))) | BP21: =IF($AE$2="",1,IF($AE$2="(blank)",--(AE21=""),IF($AE$2="(nonblank)",--(AE21<>""),--ISNUMBER(SEARCH($AE$2,AE21))))) | BQ21: =IF($AF$2="",1,IF($AF$2="(blank)",--(AF21=""),IF($AF$2="(nonblank)",--(AF21<>""),--ISNUMBER(SEARCH($AF$2,AF21))))) | BR21: =IF($AG$2="",1,IF($AG$2="(blank)",--(AG21=""),IF($AG$2="(nonblank)",--(AG21<>""),--ISNUMBER(SEARCH($AG$2,AG21))))) | BS21: =IF($AH$2="",1,IF($AH$2="(blank)",--(AH21=""),IF($AH$2="(nonblank)",--(AH21<>""),--ISNUMBER(SEARCH($AH$2,AH21))))) | BT21: =IF(COUNTIF($AL21:$BS21,0)>0,0,1)
A22: 3 | B22: Scrap of 132 KV CT | C22: 83743 | D22: 21978 | E22: NO | F22: 2023 | G22: NATIONAL ENTERPRISES | H22: 251229 | I22: =ROUND(H22*18%,0) | J22: =+H22+I22 | K22: =ROUND((H22+I22)*2%,0) | L22: =H22*0.1% | M22: =H22*2.25%*118% | N22: =H22*2.25%*2% | O22: =M22-N22 | P22: =ROUND(O22+L22,0) | Q22: 0 | R22: =ROUND(H22*Q22,0) | S22: =ROUND(H22*117.65%-R22,0) | T22: =ROUND(H22*25%,0) | U22: =+T22 | V22: 13.08.2026 | W22: =ROUND(H22*92.65%-R22,0) | X22: 232764 | Y22: 24.08.2026 | Z22: =IF(IF(OR(AB22="",AB22=0),TODAY(),DATE(VALUE(RIGHT(AB22,4)),VALUE(MID(AB22,4,2)),VALUE(LEFT(AB22,2))))<=DATE(2026,8,24),0,H22*0.0118*CEILING((IF(OR(AB22="",AB22=0),TODAY(),DATE(VALUE(RIGHT(AB22,4)),VALUE(MID(AB22,4,2)),VALUE(LEFT(AB22,2))))-DATE(2026,8,22))/7,1)) | AC22: =U22+X22+AA22 | AD22: =S22-AC22 | AE22: =IF(AD22="","",IF(AD22<=5,"SETTLED","OUTSTANDING")) | AF22: DR2640100044 | AG22: 1800003308 | AH22: 27.08.2026 | AL22: =IF($A$2="",1,IF($A$2="(blank)",--(A22=""),IF($A$2="(nonblank)",--(A22<>""),--ISNUMBER(SEARCH($A$2,A22))))) | AM22: =IF($B$2="",1,IF($B$2="(blank)",--(B22=""),IF($B$2="(nonblank)",--(B22<>""),--ISNUMBER(SEARCH($B$2,B22))))) | AN22: =IF($C$2="",1,IF($C$2="(blank)",--(C22=""),IF($C$2="(nonblank)",--(C22<>""),--ISNUMBER(SEARCH($C$2,C22))))) | AO22: =IF($D$2="",1,IF($D$2="(blank)",--(D22=""),IF($D$2="(nonblank)",--(D22<>""),--ISNUMBER(SEARCH($D$2,D22))))) | AP22: =IF($E$2="",1,IF($E$2="(blank)",--(E22=""),IF($E$2="(nonblank)",--(E22<>""),--ISNUMBER(SEARCH($E$2,E22))))) | AQ22: =IF($F$2="",1,IF($F$2="(blank)",--(F22=""),IF($F$2="(nonblank)",--(F22<>""),--ISNUMBER(SEARCH($F$2,F22))))) | AR22: =IF($G$2="",1,IF($G$2="(blank)",--(G22=""),IF($G$2="(nonblank)",--(G22<>""),--ISNUMBER(SEARCH($G$2,G22))))) | AS22: =IF($H$2="",1,IF($H$2="(blank)",--(H22=""),IF($H$2="(nonblank)",--(H22<>""),--ISNUMBER(SEARCH($H$2,H22))))) | AT22: =IF($I$2="",1,IF($I$2="(blank)",--(I22=""),IF($I$2="(nonblank)",--(I22<>""),--ISNUMBER(SEARCH($I$2,I22))))) | AU22: =IF($J$2="",1,IF($J$2="(blank)",--(J22=""),IF($J$2="(nonblank)",--(J22<>""),--ISNUMBER(SEARCH($J$2,J22))))) | AV22: =IF($K$2="",1,IF($K$2="(blank)",--(K22=""),IF($K$2="(nonblank)",--(K22<>""),--ISNUMBER(SEARCH($K$2,K22))))) | AW22: =IF($L$2="",1,IF($L$2="(blank)",--(L22=""),IF($L$2="(nonblank)",--(L22<>""),--ISNUMBER(SEARCH($L$2,L22))))) | AX22: =IF($M$2="",1,IF($M$2="(blank)",--(M22=""),IF($M$2="(nonblank)",--(M22<>""),--ISNUMBER(SEARCH($M$2,M22))))) | AY22: =IF($N$2="",1,IF($N$2="(blank)",--(N22=""),IF($N$2="(nonblank)",--(N22<>""),--ISNUMBER(SEARCH($N$2,N22))))) | AZ22: =IF($O$2="",1,IF($O$2="(blank)",--(O22=""),IF($O$2="(nonblank)",--(O22<>""),--ISNUMBER(SEARCH($O$2,O22))))) | BA22: =IF($P$2="",1,IF($P$2="(blank)",--(P22=""),IF($P$2="(nonblank)",--(P22<>""),--ISNUMBER(SEARCH($P$2,P22))))) | BB22: =IF($Q$2="",1,IF($Q$2="(blank)",--(Q22=""),IF($Q$2="(nonblank)",--(Q22<>""),--ISNUMBER(SEARCH($Q$2,Q22))))) | BC22: =IF($R$2="",1,IF($R$2="(blank)",--(R22=""),IF($R$2="(nonblank)",--(R22<>""),--ISNUMBER(SEARCH($R$2,R22))))) | BD22: =IF($S$2="",1,IF($S$2="(blank)",--(S22=""),IF($S$2="(nonblank)",--(S22<>""),--ISNUMBER(SEARCH($S$2,S22))))) | BE22: =IF($T$2="",1,IF($T$2="(blank)",--(T22=""),IF($T$2="(nonblank)",--(T22<>""),--ISNUMBER(SEARCH($T$2,T22))))) | BF22: =IF($U$2="",1,IF($U$2="(blank)",--(U22=""),IF($U$2="(nonblank)",--(U22<>""),--ISNUMBER(SEARCH($U$2,U22))))) | BG22: =IF($V$2="",1,IF($V$2="(blank)",--(V22=""),IF($V$2="(nonblank)",--(V22<>""),--ISNUMBER(SEARCH($V$2,V22))))) | BH22: =IF($W$2="",1,IF($W$2="(blank)",--(W22=""),IF($W$2="(nonblank)",--(W22<>""),--ISNUMBER(SEARCH($W$2,W22))))) | BI22: =IF($X$2="",1,IF($X$2="(blank)",--(X22=""),IF($X$2="(nonblank)",--(X22<>""),--ISNUMBER(SEARCH($X$2,X22))))) | BJ22: =IF($Y$2="",1,IF($Y$2="(blank)",--(Y22=""),IF($Y$2="(nonblank)",--(Y22<>""),--ISNUMBER(SEARCH($Y$2,Y22))))) | BK22: =IF($Z$2="",1,IF($Z$2="(blank)",--(Z22=""),IF($Z$2="(nonblank)",--(Z22<>""),--ISNUMBER(SEARCH($Z$2,Z22))))) | BL22: =IF($AA$2="",1,IF($AA$2="(blank)",--(AA22=""),IF($AA$2="(nonblank)",--(AA22<>""),--ISNUMBER(SEARCH($AA$2,AA22))))) | BM22: =IF($AB$2="",1,IF($AB$2="(blank)",--(AB22=""),IF($AB$2="(nonblank)",--(AB22<>""),--ISNUMBER(SEARCH($AB$2,AB22))))) | BN22: =IF($AC$2="",1,IF($AC$2="(blank)",--(AC22=""),IF($AC$2="(nonblank)",--(AC22<>""),--ISNUMBER(SEARCH($AC$2,AC22))))) | BO22: =IF($AD$2="",1,IF($AD$2="(blank)",--(AD22=""),IF($AD$2="(nonblank)",--(AD22<>""),--ISNUMBER(SEARCH($AD$2,AD22))))) | BP22: =IF($AE$2="",1,IF($AE$2="(blank)",--(AE22=""),IF($AE$2="(nonblank)",--(AE22<>""),--ISNUMBER(SEARCH($AE$2,AE22))))) | BQ22: =IF($AF$2="",1,IF($AF$2="(blank)",--(AF22=""),IF($AF$2="(nonblank)",--(AF22<>""),--ISNUMBER(SEARCH($AF$2,AF22))))) | BR22: =IF($AG$2="",1,IF($AG$2="(blank)",--(AG22=""),IF($AG$2="(nonblank)",--(AG22<>""),--ISNUMBER(SEARCH($AG$2,AG22))))) | BS22: =IF($AH$2="",1,IF($AH$2="(blank)",--(AH22=""),IF($AH$2="(nonblank)",--(AH22<>""),--ISNUMBER(SEARCH($AH$2,AH22))))) | BT22: =IF(COUNTIF($AL22:$BS22,0)>0,0,1)
A23: 90 | B23: Scrap of empty oil Barrels | C23: 700 | D23: 21978 | E23: NO | F23: 2025 | G23: STERLING ENTERPRISES | H23: 63000 | I23: =ROUND(H23*18%,0) | J23: =+H23+I23 | K23: =ROUND((H23+I23)*2%,0) | L23: =H23*0.1% | M23: =H23*2.25%*118% | N23: =H23*2.25%*2% | O23: =M23-N23 | P23: =ROUND(O23+L23,0) | Q23: 0 | R23: =ROUND(H23*Q23,0) | S23: =ROUND(H23*117.65%-R23,0) | T23: =ROUND(H23*25%,0) | U23: 15750 | V23: 11.08.2026 | W23: =ROUND(H23*92.65%-R23,0) | X23: 58418 | Y23: 11.08.2026 | Z23: =IF(IF(OR(AB23="",AB23=0),TODAY(),DATE(VALUE(RIGHT(AB23,4)),VALUE(MID(AB23,4,2)),VALUE(LEFT(AB23,2))))<=DATE(2026,8,24),0,H23*0.0118*CEILING((IF(OR(AB23="",AB23=0),TODAY(),DATE(VALUE(RIGHT(AB23,4)),VALUE(MID(AB23,4,2)),VALUE(LEFT(AB23,2))))-DATE(2026,8,22))/7,1)) | AC23: =U23+X23+AA23 | AD23: =S23-AC23 | AE23: =IF(AD23="","",IF(AD23<=5,"SETTLED","OUTSTANDING")) | AF23: DR2640100021 | AG23: 1800003160 | AH23: 14.08.2026 | AL23: =IF($A$2="",1,IF($A$2="(blank)",--(A23=""),IF($A$2="(nonblank)",--(A23<>""),--ISNUMBER(SEARCH($A$2,A23))))) | AM23: =IF($B$2="",1,IF($B$2="(blank)",--(B23=""),IF($B$2="(nonblank)",--(B23<>""),--ISNUMBER(SEARCH($B$2,B23))))) | AN23: =IF($C$2="",1,IF($C$2="(blank)",--(C23=""),IF($C$2="(nonblank)",--(C23<>""),--ISNUMBER(SEARCH($C$2,C23))))) | AO23: =IF($D$2="",1,IF($D$2="(blank)",--(D23=""),IF($D$2="(nonblank)",--(D23<>""),--ISNUMBER(SEARCH($D$2,D23))))) | AP23: =IF($E$2="",1,IF($E$2="(blank)",--(E23=""),IF($E$2="(nonblank)",--(E23<>""),--ISNUMBER(SEARCH($E$2,E23))))) | AQ23: =IF($F$2="",1,IF($F$2="(blank)",--(F23=""),IF($F$2="(nonblank)",--(F23<>""),--ISNUMBER(SEARCH($F$2,F23))))) | AR23: =IF($G$2="",1,IF($G$2="(blank)",--(G23=""),IF($G$2="(nonblank)",--(G23<>""),--ISNUMBER(SEARCH($G$2,G23))))) | AS23: =IF($H$2="",1,IF($H$2="(blank)",--(H23=""),IF($H$2="(nonblank)",--(H23<>""),--ISNUMBER(SEARCH($H$2,H23))))) | AT23: =IF($I$2="",1,IF($I$2="(blank)",--(I23=""),IF($I$2="(nonblank)",--(I23<>""),--ISNUMBER(SEARCH($I$2,I23))))) | AU23: =IF($J$2="",1,IF($J$2="(blank)",--(J23=""),IF($J$2="(nonblank)",--(J23<>""),--ISNUMBER(SEARCH($J$2,J23))))) | AV23: =IF($K$2="",1,IF($K$2="(blank)",--(K23=""),IF($K$2="(nonblank)",--(K23<>""),--ISNUMBER(SEARCH($K$2,K23))))) | AW23: =IF($L$2="",1,IF($L$2="(blank)",--(L23=""),IF($L$2="(nonblank)",--(L23<>""),--ISNUMBER(SEARCH($L$2,L23))))) | AX23: =IF($M$2="",1,IF($M$2="(blank)",--(M23=""),IF($M$2="(nonblank)",--(M23<>""),--ISNUMBER(SEARCH($M$2,M23))))) | AY23: =IF($N$2="",1,IF($N$2="(blank)",--(N23=""),IF($N$2="(nonblank)",--(N23<>""),--ISNUMBER(SEARCH($N$2,N23))))) | AZ23: =IF($O$2="",1,IF($O$2="(blank)",--(O23=""),IF($O$2="(nonblank)",--(O23<>""),--ISNUMBER(SEARCH($O$2,O23))))) | BA23: =IF($P$2="",1,IF($P$2="(blank)",--(P23=""),IF($P$2="(nonblank)",--(P23<>""),--ISNUMBER(SEARCH($P$2,P23))))) | BB23: =IF($Q$2="",1,IF($Q$2="(blank)",--(Q23=""),IF($Q$2="(nonblank)",--(Q23<>""),--ISNUMBER(SEARCH($Q$2,Q23))))) | BC23: =IF($R$2="",1,IF($R$2="(blank)",--(R23=""),IF($R$2="(nonblank)",--(R23<>""),--ISNUMBER(SEARCH($R$2,R23))))) | BD23: =IF($S$2="",1,IF($S$2="(blank)",--(S23=""),IF($S$2="(nonblank)",--(S23<>""),--ISNUMBER(SEARCH($S$2,S23))))) | BE23: =IF($T$2="",1,IF($T$2="(blank)",--(T23=""),IF($T$2="(nonblank)",--(T23<>""),--ISNUMBER(SEARCH($T$2,T23))))) | BF23: =IF($U$2="",1,IF($U$2="(blank)",--(U23=""),IF($U$2="(nonblank)",--(U23<>""),--ISNUMBER(SEARCH($U$2,U23))))) | BG23: =IF($V$2="",1,IF($V$2="(blank)",--(V23=""),IF($V$2="(nonblank)",--(V23<>""),--ISNUMBER(SEARCH($V$2,V23))))) | BH23: =IF($W$2="",1,IF($W$2="(blank)",--(W23=""),IF($W$2="(nonblank)",--(W23<>""),--ISNUMBER(SEARCH($W$2,W23))))) | BI23: =IF($X$2="",1,IF($X$2="(blank)",--(X23=""),IF($X$2="(nonblank)",--(X23<>""),--ISNUMBER(SEARCH($X$2,X23))))) | BJ23: =IF($Y$2="",1,IF($Y$2="(blank)",--(Y23=""),IF($Y$2="(nonblank)",--(Y23<>""),--ISNUMBER(SEARCH($Y$2,Y23))))) | BK23: =IF($Z$2="",1,IF($Z$2="(blank)",--(Z23=""),IF($Z$2="(nonblank)",--(Z23<>""),--ISNUMBER(SEARCH($Z$2,Z23))))) | BL23: =IF($AA$2="",1,IF($AA$2="(blank)",--(AA23=""),IF($AA$2="(nonblank)",--(AA23<>""),--ISNUMBER(SEARCH($AA$2,AA23))))) | BM23: =IF($AB$2="",1,IF($AB$2="(blank)",--(AB23=""),IF($AB$2="(nonblank)",--(AB23<>""),--ISNUMBER(SEARCH($AB$2,AB23))))) | BN23: =IF($AC$2="",1,IF($AC$2="(blank)",--(AC23=""),IF($AC$2="(nonblank)",--(AC23<>""),--ISNUMBER(SEARCH($AC$2,AC23))))) | BO23: =IF($AD$2="",1,IF($AD$2="(blank)",--(AD23=""),IF($AD$2="(nonblank)",--(AD23<>""),--ISNUMBER(SEARCH($AD$2,AD23))))) | BP23: =IF($AE$2="",1,IF($AE$2="(blank)",--(AE23=""),IF($AE$2="(nonblank)",--(AE23<>""),--ISNUMBER(SEARCH($AE$2,AE23))))) | BQ23: =IF($AF$2="",1,IF($AF$2="(blank)",--(AF23=""),IF($AF$2="(nonblank)",--(AF23<>""),--ISNUMBER(SEARCH($AF$2,AF23))))) | BR23: =IF($AG$2="",1,IF($AG$2="(blank)",--(AG23=""),IF($AG$2="(nonblank)",--(AG23<>""),--ISNUMBER(SEARCH($AG$2,AG23))))) | BS23: =IF($AH$2="",1,IF($AH$2="(blank)",--(AH23=""),IF($AH$2="(nonblank)",--(AH23<>""),--ISNUMBER(SEARCH($AH$2,AH23))))) | BT23: =IF(COUNTIF($AL23:$BS23,0)>0,0,1)
A24: 1 | B24: Scrap of 132 KV CT | C24: 50003 | D24: 21978 | E24: NO | F24: 2027 | G24: NATIONAL ENTERPRISES | H24: 50003 | I24: =ROUND(H24*18%,0) | J24: =+H24+I24 | K24: =ROUND((H24+I24)*2%,0) | L24: =H24*0.1% | M24: =H24*2.25%*118% | N24: =H24*2.25%*2% | O24: =M24-N24 | P24: =ROUND(O24+L24,0) | Q24: 0 | R24: =ROUND(H24*Q24,0) | S24: =ROUND(H24*117.65%-R24,0) | T24: =ROUND(H24*25%,0) | U24: =+T24 | V24: 13.08.2026 | W24: =ROUND(H24*92.65%-R24,0) | X24: 46328 | Y24: 24.08.2026 | Z24: =IF(IF(OR(AB24="",AB24=0),TODAY(),DATE(VALUE(RIGHT(AB24,4)),VALUE(MID(AB24,4,2)),VALUE(LEFT(AB24,2))))<=DATE(2026,8,24),0,H24*0.0118*CEILING((IF(OR(AB24="",AB24=0),TODAY(),DATE(VALUE(RIGHT(AB24,4)),VALUE(MID(AB24,4,2)),VALUE(LEFT(AB24,2))))-DATE(2026,8,22))/7,1)) | AC24: =U24+X24+AA24 | AD24: =S24-AC24 | AE24: =IF(AD24="","",IF(AD24<=5,"SETTLED","OUTSTANDING")) | AF24: DR2640100036 | AG24: 1800003309 | AH24: 27.08.2026 | AL24: =IF($A$2="",1,IF($A$2="(blank)",--(A24=""),IF($A$2="(nonblank)",--(A24<>""),--ISNUMBER(SEARCH($A$2,A24))))) | AM24: =IF($B$2="",1,IF($B$2="(blank)",--(B24=""),IF($B$2="(nonblank)",--(B24<>""),--ISNUMBER(SEARCH($B$2,B24))))) | AN24: =IF($C$2="",1,IF($C$2="(blank)",--(C24=""),IF($C$2="(nonblank)",--(C24<>""),--ISNUMBER(SEARCH($C$2,C24))))) | AO24: =IF($D$2="",1,IF($D$2="(blank)",--(D24=""),IF($D$2="(nonblank)",--(D24<>""),--ISNUMBER(SEARCH($D$2,D24))))) | AP24: =IF($E$2="",1,IF($E$2="(blank)",--(E24=""),IF($E$2="(nonblank)",--(E24<>""),--ISNUMBER(SEARCH($E$2,E24))))) | AQ24: =IF($F$2="",1,IF($F$2="(blank)",--(F24=""),IF($F$2="(nonblank)",--(F24<>""),--ISNUMBER(SEARCH($F$2,F24))))) | AR24: =IF($G$2="",1,IF($G$2="(blank)",--(G24=""),IF($G$2="(nonblank)",--(G24<>""),--ISNUMBER(SEARCH($G$2,G24))))) | AS24: =IF($H$2="",1,IF($H$2="(blank)",--(H24=""),IF($H$2="(nonblank)",--(H24<>""),--ISNUMBER(SEARCH($H$2,H24))))) | AT24: =IF($I$2="",1,IF($I$2="(blank)",--(I24=""),IF($I$2="(nonblank)",--(I24<>""),--ISNUMBER(SEARCH($I$2,I24))))) | AU24: =IF($J$2="",1,IF($J$2="(blank)",--(J24=""),IF($J$2="(nonblank)",--(J24<>""),--ISNUMBER(SEARCH($J$2,J24))))) | AV24: =IF($K$2="",1,IF($K$2="(blank)",--(K24=""),IF($K$2="(nonblank)",--(K24<>""),--ISNUMBER(SEARCH($K$2,K24))))) | AW24: =IF($L$2="",1,IF($L$2="(blank)",--(L24=""),IF($L$2="(nonblank)",--(L24<>""),--ISNUMBER(SEARCH($L$2,L24))))) | AX24: =IF($M$2="",1,IF($M$2="(blank)",--(M24=""),IF($M$2="(nonblank)",--(M24<>""),--ISNUMBER(SEARCH($M$2,M24))))) | AY24: =IF($N$2="",1,IF($N$2="(blank)",--(N24=""),IF($N$2="(nonblank)",--(N24<>""),--ISNUMBER(SEARCH($N$2,N24))))) | AZ24: =IF($O$2="",1,IF($O$2="(blank)",--(O24=""),IF($O$2="(nonblank)",--(O24<>""),--ISNUMBER(SEARCH($O$2,O24))))) | BA24: =IF($P$2="",1,IF($P$2="(blank)",--(P24=""),IF($P$2="(nonblank)",--(P24<>""),--ISNUMBER(SEARCH($P$2,P24))))) | BB24: =IF($Q$2="",1,IF($Q$2="(blank)",--(Q24=""),IF($Q$2="(nonblank)",--(Q24<>""),--ISNUMBER(SEARCH($Q$2,Q24))))) | BC24: =IF($R$2="",1,IF($R$2="(blank)",--(R24=""),IF($R$2="(nonblank)",--(R24<>""),--ISNUMBER(SEARCH($R$2,R24))))) | BD24: =IF($S$2="",1,IF($S$2="(blank)",--(S24=""),IF($S$2="(nonblank)",--(S24<>""),--ISNUMBER(SEARCH($S$2,S24))))) | BE24: =IF($T$2="",1,IF($T$2="(blank)",--(T24=""),IF($T$2="(nonblank)",--(T24<>""),--ISNUMBER(SEARCH($T$2,T24))))) | BF24: =IF($U$2="",1,IF($U$2="(blank)",--(U24=""),IF($U$2="(nonblank)",--(U24<>""),--ISNUMBER(SEARCH($U$2,U24))))) | BG24: =IF($V$2="",1,IF($V$2="(blank)",--(V24=""),IF($V$2="(nonblank)",--(V24<>""),--ISNUMBER(SEARCH($V$2,V24))))) | BH24: =IF($W$2="",1,IF($W$2="(blank)",--(W24=""),IF($W$2="(nonblank)",--(W24<>""),--ISNUMBER(SEARCH($W$2,W24))))) | BI24: =IF($X$2="",1,IF($X$2="(blank)",--(X24=""),IF($X$2="(nonblank)",--(X24<>""),--ISNUMBER(SEARCH($X$2,X24))))) | BJ24: =IF($Y$2="",1,IF($Y$2="(blank)",--(Y24=""),IF($Y$2="(nonblank)",--(Y24<>""),--ISNUMBER(SEARCH($Y$2,Y24))))) | BK24: =IF($Z$2="",1,IF($Z$2="(blank)",--(Z24=""),IF($Z$2="(nonblank)",--(Z24<>""),--ISNUMBER(SEARCH($Z$2,Z24))))) | BL24: =IF($AA$2="",1,IF($AA$2="(blank)",--(AA24=""),IF($AA$2="(nonblank)",--(AA24<>""),--ISNUMBER(SEARCH($AA$2,AA24))))) | BM24: =IF($AB$2="",1,IF($AB$2="(blank)",--(AB24=""),IF($AB$2="(nonblank)",--(AB24<>""),--ISNUMBER(SEARCH($AB$2,AB24))))) | BN24: =IF($AC$2="",1,IF($AC$2="(blank)",--(AC24=""),IF($AC$2="(nonblank)",--(AC24<>""),--ISNUMBER(SEARCH($AC$2,AC24))))) | BO24: =IF($AD$2="",1,IF($AD$2="(blank)",--(AD24=""),IF($AD$2="(nonblank)",--(AD24<>""),--ISNUMBER(SEARCH($AD$2,AD24))))) | BP24: =IF($AE$2="",1,IF($AE$2="(blank)",--(AE24=""),IF($AE$2="(nonblank)",--(AE24<>""),--ISNUMBER(SEARCH($AE$2,AE24))))) | BQ24: =IF($AF$2="",1,IF($AF$2="(blank)",--(AF24=""),IF($AF$2="(nonblank)",--(AF24<>""),--ISNUMBER(SEARCH($AF$2,AF24))))) | BR24: =IF($AG$2="",1,IF($AG$2="(blank)",--(AG24=""),IF($AG$2="(nonblank)",--(AG24<>""),--ISNUMBER(SEARCH($AG$2,AG24))))) | BS24: =IF($AH$2="",1,IF($AH$2="(blank)",--(AH24=""),IF($AH$2="(nonblank)",--(AH24<>""),--ISNUMBER(SEARCH($AH$2,AH24))))) | BT24: =IF(COUNTIF($AL24:$BS24,0)>0,0,1)
A25: 1000 | B25: Scrap Empty Oil Drum/ Barrel | C25: 517 | D25: 21978 | E25: NO | F25: 2033 | G25: WATAN SCRAP TRADERS | H25: 517000 | I25: =ROUND(H25*18%,0) | J25: =+H25+I25 | K25: =ROUND((H25+I25)*2%,0) | L25: =H25*0.1% | M25: =H25*2.25%*118% | N25: =H25*2.25%*2% | O25: =M25-N25 | P25: =ROUND(O25+L25,0) | Q25: 0 | R25: =ROUND(H25*Q25,0) | S25: =ROUND(H25*117.65%-R25,0) | T25: =ROUND(H25*25%,0) | U25: 129250 | V25: 14.08.2026 | W25: =ROUND(H25*92.65%-R25,0) | X25: 479001 | Y25: 21.08.2026 | Z25: =IF(IF(OR(AB25="",AB25=0),TODAY(),DATE(VALUE(RIGHT(AB25,4)),VALUE(MID(AB25,4,2)),VALUE(LEFT(AB25,2))))<=DATE(2026,8,24),0,H25*0.0118*CEILING((IF(OR(AB25="",AB25=0),TODAY(),DATE(VALUE(RIGHT(AB25,4)),VALUE(MID(AB25,4,2)),VALUE(LEFT(AB25,2))))-DATE(2026,8,22))/7,1)) | AC25: =U25+X25+AA25 | AD25: =S25-AC25 | AE25: =IF(AD25="","",IF(AD25<=5,"SETTLED","OUTSTANDING")) | AF25: DR2640100042 | AG25: 1800003317 | AH25: 27.08.2026 | AL25: =IF($A$2="",1,IF($A$2="(blank)",--(A25=""),IF($A$2="(nonblank)",--(A25<>""),--ISNUMBER(SEARCH($A$2,A25))))) | AM25: =IF($B$2="",1,IF($B$2="(blank)",--(B25=""),IF($B$2="(nonblank)",--(B25<>""),--ISNUMBER(SEARCH($B$2,B25))))) | AN25: =IF($C$2="",1,IF($C$2="(blank)",--(C25=""),IF($C$2="(nonblank)",--(C25<>""),--ISNUMBER(SEARCH($C$2,C25))))) | AO25: =IF($D$2="",1,IF($D$2="(blank)",--(D25=""),IF($D$2="(nonblank)",--(D25<>""),--ISNUMBER(SEARCH($D$2,D25))))) | AP25: =IF($E$2="",1,IF($E$2="(blank)",--(E25=""),IF($E$2="(nonblank)",--(E25<>""),--ISNUMBER(SEARCH($E$2,E25))))) | AQ25: =IF($F$2="",1,IF($F$2="(blank)",--(F25=""),IF($F$2="(nonblank)",--(F25<>""),--ISNUMBER(SEARCH($F$2,F25))))) | AR25: =IF($G$2="",1,IF($G$2="(blank)",--(G25=""),IF($G$2="(nonblank)",--(G25<>""),--ISNUMBER(SEARCH($G$2,G25))))) | AS25: =IF($H$2="",1,IF($H$2="(blank)",--(H25=""),IF($H$2="(nonblank)",--(H25<>""),--ISNUMBER(SEARCH($H$2,H25))))) | AT25: =IF($I$2="",1,IF($I$2="(blank)",--(I25=""),IF($I$2="(nonblank)",--(I25<>""),--ISNUMBER(SEARCH($I$2,I25))))) | AU25: =IF($J$2="",1,IF($J$2="(blank)",--(J25=""),IF($J$2="(nonblank)",--(J25<>""),--ISNUMBER(SEARCH($J$2,J25))))) | AV25: =IF($K$2="",1,IF($K$2="(blank)",--(K25=""),IF($K$2="(nonblank)",--(K25<>""),--ISNUMBER(SEARCH($K$2,K25))))) | AW25: =IF($L$2="",1,IF($L$2="(blank)",--(L25=""),IF($L$2="(nonblank)",--(L25<>""),--ISNUMBER(SEARCH($L$2,L25))))) | AX25: =IF($M$2="",1,IF($M$2="(blank)",--(M25=""),IF($M$2="(nonblank)",--(M25<>""),--ISNUMBER(SEARCH($M$2,M25))))) | AY25: =IF($N$2="",1,IF($N$2="(blank)",--(N25=""),IF($N$2="(nonblank)",--(N25<>""),--ISNUMBER(SEARCH($N$2,N25))))) | AZ25: =IF($O$2="",1,IF($O$2="(blank)",--(O25=""),IF($O$2="(nonblank)",--(O25<>""),--ISNUMBER(SEARCH($O$2,O25))))) | BA25: =IF($P$2="",1,IF($P$2="(blank)",--(P25=""),IF($P$2="(nonblank)",--(P25<>""),--ISNUMBER(SEARCH($P$2,P25))))) | BB25: =IF($Q$2="",1,IF($Q$2="(blank)",--(Q25=""),IF($Q$2="(nonblank)",--(Q25<>""),--ISNUMBER(SEARCH($Q$2,Q25))))) | BC25: =IF($R$2="",1,IF($R$2="(blank)",--(R25=""),IF($R$2="(nonblank)",--(R25<>""),--ISNUMBER(SEARCH($R$2,R25))))) | BD25: =IF($S$2="",1,IF($S$2="(blank)",--(S25=""),IF($S$2="(nonblank)",--(S25<>""),--ISNUMBER(SEARCH($S$2,S25))))) | BE25: =IF($T$2="",1,IF($T$2="(blank)",--(T25=""),IF($T$2="(nonblank)",--(T25<>""),--ISNUMBER(SEARCH($T$2,T25))))) | BF25: =IF($U$2="",1,IF($U$2="(blank)",--(U25=""),IF($U$2="(nonblank)",--(U25<>""),--ISNUMBER(SEARCH($U$2,U25))))) | BG25: =IF($V$2="",1,IF($V$2="(blank)",--(V25=""),IF($V$2="(nonblank)",--(V25<>""),--ISNUMBER(SEARCH($V$2,V25))))) | BH25: =IF($W$2="",1,IF($W$2="(blank)",--(W25=""),IF($W$2="(nonblank)",--(W25<>""),--ISNUMBER(SEARCH($W$2,W25))))) | BI25: =IF($X$2="",1,IF($X$2="(blank)",--(X25=""),IF($X$2="(nonblank)",--(X25<>""),--ISNUMBER(SEARCH($X$2,X25))))) | BJ25: =IF($Y$2="",1,IF($Y$2="(blank)",--(Y25=""),IF($Y$2="(nonblank)",--(Y25<>""),--ISNUMBER(SEARCH($Y$2,Y25))))) | BK25: =IF($Z$2="",1,IF($Z$2="(blank)",--(Z25=""),IF($Z$2="(nonblank)",--(Z25<>""),--ISNUMBER(SEARCH($Z$2,Z25))))) | BL25: =IF($AA$2="",1,IF($AA$2="(blank)",--(AA25=""),IF($AA$2="(nonblank)",--(AA25<>""),--ISNUMBER(SEARCH($AA$2,AA25))))) | BM25: =IF($AB$2="",1,IF($AB$2="(blank)",--(AB25=""),IF($AB$2="(nonblank)",--(AB25<>""),--ISNUMBER(SEARCH($AB$2,AB25))))) | BN25: =IF($AC$2="",1,IF($AC$2="(blank)",--(AC25=""),IF($AC$2="(nonblank)",--(AC25<>""),--ISNUMBER(SEARCH($AC$2,AC25))))) | BO25: =IF($AD$2="",1,IF($AD$2="(blank)",--(AD25=""),IF($AD$2="(nonblank)",--(AD25<>""),--ISNUMBER(SEARCH($AD$2,AD25))))) | BP25: =IF($AE$2="",1,IF($AE$2="(blank)",--(AE25=""),IF($AE$2="(nonblank)",--(AE25<>""),--ISNUMBER(SEARCH($AE$2,AE25))))) | BQ25: =IF($AF$2="",1,IF($AF$2="(blank)",--(AF25=""),IF($AF$2="(nonblank)",--(AF25<>""),--ISNUMBER(SEARCH($AF$2,AF25))))) | BR25: =IF($AG$2="",1,IF($AG$2="(blank)",--(AG25=""),IF($AG$2="(nonblank)",--(AG25<>""),--ISNUMBER(SEARCH($AG$2,AG25))))) | BS25: =IF($AH$2="",1,IF($AH$2="(blank)",--(AH25=""),IF($AH$2="(nonblank)",--(AH25<>""),--ISNUMBER(SEARCH($AH$2,AH25))))) | BT25: =IF(COUNTIF($AL25:$BS25,0)>0,0,1)
A26: 2 | B26: Scrap of 132 KV Wave Trap | C26: 14001 | D26: 21978 | E26: NO | F26: 2035 | G26: NATIONAL ENTERPRISES | H26: 28002 | I26: =ROUND(H26*18%,0) | J26: =+H26+I26 | K26: =ROUND((H26+I26)*2%,0) | L26: =H26*0.1% | M26: =H26*2.25%*118% | N26: =H26*2.25%*2% | O26: =M26-N26 | P26: =ROUND(O26+L26,0) | Q26: 0 | R26: =ROUND(H26*Q26,0) | S26: =ROUND(H26*117.65%-R26,0) | T26: =ROUND(H26*25%,0) | U26: =+T26 | V26: 13.08.2026 | W26: =ROUND(H26*92.65%-R26,0) | X26: 25943 | Y26: 24.08.2026 | Z26: =IF(IF(OR(AB26="",AB26=0),TODAY(),DATE(VALUE(RIGHT(AB26,4)),VALUE(MID(AB26,4,2)),VALUE(LEFT(AB26,2))))<=DATE(2026,8,24),0,H26*0.0118*CEILING((IF(OR(AB26="",AB26=0),TODAY(),DATE(VALUE(RIGHT(AB26,4)),VALUE(MID(AB26,4,2)),VALUE(LEFT(AB26,2))))-DATE(2026,8,22))/7,1)) | AC26: =U26+X26+AA26 | AD26: =S26-AC26 | AE26: =IF(AD26="","",IF(AD26<=5,"SETTLED","OUTSTANDING")) | AF26: DR2640100037 | AG26: 1800003310 | AH26: 27.08.2026 | AL26: =IF($A$2="",1,IF($A$2="(blank)",--(A26=""),IF($A$2="(nonblank)",--(A26<>""),--ISNUMBER(SEARCH($A$2,A26))))) | AM26: =IF($B$2="",1,IF($B$2="(blank)",--(B26=""),IF($B$2="(nonblank)",--(B26<>""),--ISNUMBER(SEARCH($B$2,B26))))) | AN26: =IF($C$2="",1,IF($C$2="(blank)",--(C26=""),IF($C$2="(nonblank)",--(C26<>""),--ISNUMBER(SEARCH($C$2,C26))))) | AO26: =IF($D$2="",1,IF($D$2="(blank)",--(D26=""),IF($D$2="(nonblank)",--(D26<>""),--ISNUMBER(SEARCH($D$2,D26))))) | AP26: =IF($E$2="",1,IF($E$2="(blank)",--(E26=""),IF($E$2="(nonblank)",--(E26<>""),--ISNUMBER(SEARCH($E$2,E26))))) | AQ26: =IF($F$2="",1,IF($F$2="(blank)",--(F26=""),IF($F$2="(nonblank)",--(F26<>""),--ISNUMBER(SEARCH($F$2,F26))))) | AR26: =IF($G$2="",1,IF($G$2="(blank)",--(G26=""),IF($G$2="(nonblank)",--(G26<>""),--ISNUMBER(SEARCH($G$2,G26))))) | AS26: =IF($H$2="",1,IF($H$2="(blank)",--(H26=""),IF($H$2="(nonblank)",--(H26<>""),--ISNUMBER(SEARCH($H$2,H26))))) | AT26: =IF($I$2="",1,IF($I$2="(blank)",--(I26=""),IF($I$2="(nonblank)",--(I26<>""),--ISNUMBER(SEARCH($I$2,I26))))) | AU26: =IF($J$2="",1,IF($J$2="(blank)",--(J26=""),IF($J$2="(nonblank)",--(J26<>""),--ISNUMBER(SEARCH($J$2,J26))))) | AV26: =IF($K$2="",1,IF($K$2="(blank)",--(K26=""),IF($K$2="(nonblank)",--(K26<>""),--ISNUMBER(SEARCH($K$2,K26))))) | AW26: =IF($L$2="",1,IF($L$2="(blank)",--(L26=""),IF($L$2="(nonblank)",--(L26<>""),--ISNUMBER(SEARCH($L$2,L26))))) | AX26: =IF($M$2="",1,IF($M$2="(blank)",--(M26=""),IF($M$2="(nonblank)",--(M26<>""),--ISNUMBER(SEARCH($M$2,M26))))) | AY26: =IF($N$2="",1,IF($N$2="(blank)",--(N26=""),IF($N$2="(nonblank)",--(N26<>""),--ISNUMBER(SEARCH($N$2,N26))))) | AZ26: =IF($O$2="",1,IF($O$2="(blank)",--(O26=""),IF($O$2="(nonblank)",--(O26<>""),--ISNUMBER(SEARCH($O$2,O26))))) | BA26: =IF($P$2="",1,IF($P$2="(blank)",--(P26=""),IF($P$2="(nonblank)",--(P26<>""),--ISNUMBER(SEARCH($P$2,P26))))) | BB26: =IF($Q$2="",1,IF($Q$2="(blank)",--(Q26=""),IF($Q$2="(nonblank)",--(Q26<>""),--ISNUMBER(SEARCH($Q$2,Q26))))) | BC26: =IF($R$2="",1,IF($R$2="(blank)",--(R26=""),IF($R$2="(nonblank)",--(R26<>""),--ISNUMBER(SEARCH($R$2,R26))))) | BD26: =IF($S$2="",1,IF($S$2="(blank)",--(S26=""),IF($S$2="(nonblank)",--(S26<>""),--ISNUMBER(SEARCH($S$2,S26))))) | BE26: =IF($T$2="",1,IF($T$2="(blank)",--(T26=""),IF($T$2="(nonblank)",--(T26<>""),--ISNUMBER(SEARCH($T$2,T26))))) | BF26: =IF($U$2="",1,IF($U$2="(blank)",--(U26=""),IF($U$2="(nonblank)",--(U26<>""),--ISNUMBER(SEARCH($U$2,U26))))) | BG26: =IF($V$2="",1,IF($V$2="(blank)",--(V26=""),IF($V$2="(nonblank)",--(V26<>""),--ISNUMBER(SEARCH($V$2,V26))))) | BH26: =IF($W$2="",1,IF($W$2="(blank)",--(W26=""),IF($W$2="(nonblank)",--(W26<>""),--ISNUMBER(SEARCH($W$2,W26))))) | BI26: =IF($X$2="",1,IF($X$2="(blank)",--(X26=""),IF($X$2="(nonblank)",--(X26<>""),--ISNUMBER(SEARCH($X$2,X26))))) | BJ26: =IF($Y$2="",1,IF($Y$2="(blank)",--(Y26=""),IF($Y$2="(nonblank)",--(Y26<>""),--ISNUMBER(SEARCH($Y$2,Y26))))) | BK26: =IF($Z$2="",1,IF($Z$2="(blank)",--(Z26=""),IF($Z$2="(nonblank)",--(Z26<>""),--ISNUMBER(SEARCH($Z$2,Z26))))) | BL26: =IF($AA$2="",1,IF($AA$2="(blank)",--(AA26=""),IF($AA$2="(nonblank)",--(AA26<>""),--ISNUMBER(SEARCH($AA$2,AA26))))) | BM26: =IF($AB$2="",1,IF($AB$2="(blank)",--(AB26=""),IF($AB$2="(nonblank)",--(AB26<>""),--ISNUMBER(SEARCH($AB$2,AB26))))) | BN26: =IF($AC$2="",1,IF($AC$2="(blank)",--(AC26=""),IF($AC$2="(nonblank)",--(AC26<>""),--ISNUMBER(SEARCH($AC$2,AC26))))) | BO26: =IF($AD$2="",1,IF($AD$2="(blank)",--(AD26=""),IF($AD$2="(nonblank)",--(AD26<>""),--ISNUMBER(SEARCH($AD$2,AD26))))) | BP26: =IF($AE$2="",1,IF($AE$2="(blank)",--(AE26=""),IF($AE$2="(nonblank)",--(AE26<>""),--ISNUMBER(SEARCH($AE$2,AE26))))) | BQ26: =IF($AF$2="",1,IF($AF$2="(blank)",--(AF26=""),IF($AF$2="(nonblank)",--(AF26<>""),--ISNUMBER(SEARCH($AF$2,AF26))))) | BR26: =IF($AG$2="",1,IF($AG$2="(blank)",--(AG26=""),IF($AG$2="(nonblank)",--(AG26<>""),--ISNUMBER(SEARCH($AG$2,AG26))))) | BS26: =IF($AH$2="",1,IF($AH$2="(blank)",--(AH26=""),IF($AH$2="(nonblank)",--(AH26<>""),--ISNUMBER(SEARCH($AH$2,AH26))))) | BT26: =IF(COUNTIF($AL26:$BS26,0)>0,0,1)
A27: 8.2 | B27: Mix Scrap (Tower angles & 0.2 ACSR Condutor pieces) | C27: 67000 | D27: 21978 | E27: MT | F27: 2036 | G27: M I SCRAP TRADERS | H27: 549400 | I27: =ROUND(H27*18%,0) | J27: =+H27+I27 | K27: =ROUND((H27+I27)*2%,0) | L27: =H27*0.1% | M27: =H27*2.25%*118% | N27: =H27*2.25%*2% | O27: =M27-N27 | P27: =ROUND(O27+L27,0) | Q27: 0.02 | R27: =ROUND(H27*Q27,0) | S27: =ROUND(H27*117.65%-R27,0) | T27: =ROUND(H27*25%,0) | U27: 137350 | V27: 14.08.2026 | W27: =ROUND(H27*92.65%-R27,0) | Y27: 0 | Z27: =IF(IF(OR(AB27="",AB27=0),TODAY(),DATE(VALUE(RIGHT(AB27,4)),VALUE(MID(AB27,4,2)),VALUE(LEFT(AB27,2))))<=DATE(2026,8,24),0,H27*0.0118*CEILING((IF(OR(AB27="",AB27=0),TODAY(),DATE(VALUE(RIGHT(AB27,4)),VALUE(MID(AB27,4,2)),VALUE(LEFT(AB27,2))))-DATE(2026,8,22))/7,1)) | AC27: =U27+X27+AA27 | AD27: =S27-AC27 | AE27: =IF(AD27="","",IF(AD27<=5,"SETTLED","OUTSTANDING")) | AL27: =IF($A$2="",1,IF($A$2="(blank)",--(A27=""),IF($A$2="(nonblank)",--(A27<>""),--ISNUMBER(SEARCH($A$2,A27))))) | AM27: =IF($B$2="",1,IF($B$2="(blank)",--(B27=""),IF($B$2="(nonblank)",--(B27<>""),--ISNUMBER(SEARCH($B$2,B27))))) | AN27: =IF($C$2="",1,IF($C$2="(blank)",--(C27=""),IF($C$2="(nonblank)",--(C27<>""),--ISNUMBER(SEARCH($C$2,C27))))) | AO27: =IF($D$2="",1,IF($D$2="(blank)",--(D27=""),IF($D$2="(nonblank)",--(D27<>""),--ISNUMBER(SEARCH($D$2,D27))))) | AP27: =IF($E$2="",1,IF($E$2="(blank)",--(E27=""),IF($E$2="(nonblank)",--(E27<>""),--ISNUMBER(SEARCH($E$2,E27))))) | AQ27: =IF($F$2="",1,IF($F$2="(blank)",--(F27=""),IF($F$2="(nonblank)",--(F27<>""),--ISNUMBER(SEARCH($F$2,F27))))) | AR27: =IF($G$2="",1,IF($G$2="(blank)",--(G27=""),IF($G$2="(nonblank)",--(G27<>""),--ISNUMBER(SEARCH($G$2,G27))))) | AS27: =IF($H$2="",1,IF($H$2="(blank)",--(H27=""),IF($H$2="(nonblank)",--(H27<>""),--ISNUMBER(SEARCH($H$2,H27))))) | AT27: =IF($I$2="",1,IF($I$2="(blank)",--(I27=""),IF($I$2="(nonblank)",--(I27<>""),--ISNUMBER(SEARCH($I$2,I27))))) | AU27: =IF($J$2="",1,IF($J$2="(blank)",--(J27=""),IF($J$2="(nonblank)",--(J27<>""),--ISNUMBER(SEARCH($J$2,J27))))) | AV27: =IF($K$2="",1,IF($K$2="(blank)",--(K27=""),IF($K$2="(nonblank)",--(K27<>""),--ISNUMBER(SEARCH($K$2,K27))))) | AW27: =IF($L$2="",1,IF($L$2="(blank)",--(L27=""),IF($L$2="(nonblank)",--(L27<>""),--ISNUMBER(SEARCH($L$2,L27))))) | AX27: =IF($M$2="",1,IF($M$2="(blank)",--(M27=""),IF($M$2="(nonblank)",--(M27<>""),--ISNUMBER(SEARCH($M$2,M27))))) | AY27: =IF($N$2="",1,IF($N$2="(blank)",--(N27=""),IF($N$2="(nonblank)",--(N27<>""),--ISNUMBER(SEARCH($N$2,N27))))) | AZ27: =IF($O$2="",1,IF($O$2="(blank)",--(O27=""),IF($O$2="(nonblank)",--(O27<>""),--ISNUMBER(SEARCH($O$2,O27))))) | BA27: =IF($P$2="",1,IF($P$2="(blank)",--(P27=""),IF($P$2="(nonblank)",--(P27<>""),--ISNUMBER(SEARCH($P$2,P27))))) | BB27: =IF($Q$2="",1,IF($Q$2="(blank)",--(Q27=""),IF($Q$2="(nonblank)",--(Q27<>""),--ISNUMBER(SEARCH($Q$2,Q27))))) | BC27: =IF($R$2="",1,IF($R$2="(blank)",--(R27=""),IF($R$2="(nonblank)",--(R27<>""),--ISNUMBER(SEARCH($R$2,R27))))) | BD27: =IF($S$2="",1,IF($S$2="(blank)",--(S27=""),IF($S$2="(nonblank)",--(S27<>""),--ISNUMBER(SEARCH($S$2,S27))))) | BE27: =IF($T$2="",1,IF($T$2="(blank)",--(T27=""),IF($T$2="(nonblank)",--(T27<>""),--ISNUMBER(SEARCH($T$2,T27))))) | BF27: =IF($U$2="",1,IF($U$2="(blank)",--(U27=""),IF($U$2="(nonblank)",--(U27<>""),--ISNUMBER(SEARCH($U$2,U27))))) | BG27: =IF($V$2="",1,IF($V$2="(blank)",--(V27=""),IF($V$2="(nonblank)",--(V27<>""),--ISNUMBER(SEARCH($V$2,V27))))) | BH27: =IF($W$2="",1,IF($W$2="(blank)",--(W27=""),IF($W$2="(nonblank)",--(W27<>""),--ISNUMBER(SEARCH($W$2,W27))))) | BI27: =IF($X$2="",1,IF($X$2="(blank)",--(X27=""),IF($X$2="(nonblank)",--(X27<>""),--ISNUMBER(SEARCH($X$2,X27))))) | BJ27: =IF($Y$2="",1,IF($Y$2="(blank)",--(Y27=""),IF($Y$2="(nonblank)",--(Y27<>""),--ISNUMBER(SEARCH($Y$2,Y27))))) | BK27: =IF($Z$2="",1,IF($Z$2="(blank)",--(Z27=""),IF($Z$2="(nonblank)",--(Z27<>""),--ISNUMBER(SEARCH($Z$2,Z27))))) | BL27: =IF($AA$2="",1,IF($AA$2="(blank)",--(AA27=""),IF($AA$2="(nonblank)",--(AA27<>""),--ISNUMBER(SEARCH($AA$2,AA27))))) | BM27: =IF($AB$2="",1,IF($AB$2="(blank)",--(AB27=""),IF($AB$2="(nonblank)",--(AB27<>""),--ISNUMBER(SEARCH($AB$2,AB27))))) | BN27: =IF($AC$2="",1,IF($AC$2="(blank)",--(AC27=""),IF($AC$2="(nonblank)",--(AC27<>""),--ISNUMBER(SEARCH($AC$2,AC27))))) | BO27: =IF($AD$2="",1,IF($AD$2="(blank)",--(AD27=""),IF($AD$2="(nonblank)",--(AD27<>""),--ISNUMBER(SEARCH($AD$2,AD27))))) | BP27: =IF($AE$2="",1,IF($AE$2="(blank)",--(AE27=""),IF($AE$2="(nonblank)",--(AE27<>""),--ISNUMBER(SEARCH($AE$2,AE27))))) | BQ27: =IF($AF$2="",1,IF($AF$2="(blank)",--(AF27=""),IF($AF$2="(nonblank)",--(AF27<>""),--ISNUMBER(SEARCH($AF$2,AF27))))) | BR27: =IF($AG$2="",1,IF($AG$2="(blank)",--(AG27=""),IF($AG$2="(nonblank)",--(AG27<>""),--ISNUMBER(SEARCH($AG$2,AG27))))) | BS27: =IF($AH$2="",1,IF($AH$2="(blank)",--(AH27=""),IF($AH$2="(nonblank)",--(AH27<>""),--ISNUMBER(SEARCH($AH$2,AH27))))) | BT27: =IF(COUNTIF($AL27:$BS27,0)>0,0,1)
A28: 50 | B28: Scrap of empty oil Barrels | C28: 531 | D28: 21978 | E28: NO | F28: 2037 | G28: WATAN SCRAP TRADERS | H28: 26550 | I28: =ROUND(H28*18%,0) | J28: =+H28+I28 | K28: =ROUND((H28+I28)*2%,0) | L28: =H28*0.1% | M28: =H28*2.25%*118% | N28: =H28*2.25%*2% | O28: =M28-N28 | P28: =ROUND(O28+L28,0) | Q28: 0 | R28: =ROUND(H28*Q28,0) | S28: =ROUND(H28*117.65%-R28,0) | T28: =ROUND(H28*25%,0) | U28: 6638 | V28: 14.08.2026 | W28: =ROUND(H28*92.65%-R28,0) | X28: 24598 | Y28: 21.08.2026 | Z28: =IF(IF(OR(AB28="",AB28=0),TODAY(),DATE(VALUE(RIGHT(AB28,4)),VALUE(MID(AB28,4,2)),VALUE(LEFT(AB28,2))))<=DATE(2026,8,24),0,H28*0.0118*CEILING((IF(OR(AB28="",AB28=0),TODAY(),DATE(VALUE(RIGHT(AB28,4)),VALUE(MID(AB28,4,2)),VALUE(LEFT(AB28,2))))-DATE(2026,8,22))/7,1)) | AC28: =U28+X28+AA28 | AD28: =S28-AC28 | AE28: =IF(AD28="","",IF(AD28<=5,"SETTLED","OUTSTANDING")) | AF28: DR2640100043 | AG28: 1800003318 | AH28: 27.08.2026 | AL28: =IF($A$2="",1,IF($A$2="(blank)",--(A28=""),IF($A$2="(nonblank)",--(A28<>""),--ISNUMBER(SEARCH($A$2,A28))))) | AM28: =IF($B$2="",1,IF($B$2="(blank)",--(B28=""),IF($B$2="(nonblank)",--(B28<>""),--ISNUMBER(SEARCH($B$2,B28))))) | AN28: =IF($C$2="",1,IF($C$2="(blank)",--(C28=""),IF($C$2="(nonblank)",--(C28<>""),--ISNUMBER(SEARCH($C$2,C28))))) | AO28: =IF($D$2="",1,IF($D$2="(blank)",--(D28=""),IF($D$2="(nonblank)",--(D28<>""),--ISNUMBER(SEARCH($D$2,D28))))) | AP28: =IF($E$2="",1,IF($E$2="(blank)",--(E28=""),IF($E$2="(nonblank)",--(E28<>""),--ISNUMBER(SEARCH($E$2,E28))))) | AQ28: =IF($F$2="",1,IF($F$2="(blank)",--(F28=""),IF($F$2="(nonblank)",--(F28<>""),--ISNUMBER(SEARCH($F$2,F28))))) | AR28: =IF($G$2="",1,IF($G$2="(blank)",--(G28=""),IF($G$2="(nonblank)",--(G28<>""),--ISNUMBER(SEARCH($G$2,G28))))) | AS28: =IF($H$2="",1,IF($H$2="(blank)",--(H28=""),IF($H$2="(nonblank)",--(H28<>""),--ISNUMBER(SEARCH($H$2,H28))))) | AT28: =IF($I$2="",1,IF($I$2="(blank)",--(I28=""),IF($I$2="(nonblank)",--(I28<>""),--ISNUMBER(SEARCH($I$2,I28))))) | AU28: =IF($J$2="",1,IF($J$2="(blank)",--(J28=""),IF($J$2="(nonblank)",--(J28<>""),--ISNUMBER(SEARCH($J$2,J28))))) | AV28: =IF($K$2="",1,IF($K$2="(blank)",--(K28=""),IF($K$2="(nonblank)",--(K28<>""),--ISNUMBER(SEARCH($K$2,K28))))) | AW28: =IF($L$2="",1,IF($L$2="(blank)",--(L28=""),IF($L$2="(nonblank)",--(L28<>""),--ISNUMBER(SEARCH($L$2,L28))))) | AX28: =IF($M$2="",1,IF($M$2="(blank)",--(M28=""),IF($M$2="(nonblank)",--(M28<>""),--ISNUMBER(SEARCH($M$2,M28))))) | AY28: =IF($N$2="",1,IF($N$2="(blank)",--(N28=""),IF($N$2="(nonblank)",--(N28<>""),--ISNUMBER(SEARCH($N$2,N28))))) | AZ28: =IF($O$2="",1,IF($O$2="(blank)",--(O28=""),IF($O$2="(nonblank)",--(O28<>""),--ISNUMBER(SEARCH($O$2,O28))))) | BA28: =IF($P$2="",1,IF($P$2="(blank)",--(P28=""),IF($P$2="(nonblank)",--(P28<>""),--ISNUMBER(SEARCH($P$2,P28))))) | BB28: =IF($Q$2="",1,IF($Q$2="(blank)",--(Q28=""),IF($Q$2="(nonblank)",--(Q28<>""),--ISNUMBER(SEARCH($Q$2,Q28))))) | BC28: =IF($R$2="",1,IF($R$2="(blank)",--(R28=""),IF($R$2="(nonblank)",--(R28<>""),--ISNUMBER(SEARCH($R$2,R28))))) | BD28: =IF($S$2="",1,IF($S$2="(blank)",--(S28=""),IF($S$2="(nonblank)",--(S28<>""),--ISNUMBER(SEARCH($S$2,S28))))) | BE28: =IF($T$2="",1,IF($T$2="(blank)",--(T28=""),IF($T$2="(nonblank)",--(T28<>""),--ISNUMBER(SEARCH($T$2,T28))))) | BF28: =IF($U$2="",1,IF($U$2="(blank)",--(U28=""),IF($U$2="(nonblank)",--(U28<>""),--ISNUMBER(SEARCH($U$2,U28))))) | BG28: =IF($V$2="",1,IF($V$2="(blank)",--(V28=""),IF($V$2="(nonblank)",--(V28<>""),--ISNUMBER(SEARCH($V$2,V28))))) | BH28: =IF($W$2="",1,IF($W$2="(blank)",--(W28=""),IF($W$2="(nonblank)",--(W28<>""),--ISNUMBER(SEARCH($W$2,W28))))) | BI28: =IF($X$2="",1,IF($X$2="(blank)",--(X28=""),IF($X$2="(nonblank)",--(X28<>""),--ISNUMBER(SEARCH($X$2,X28))))) | BJ28: =IF($Y$2="",1,IF($Y$2="(blank)",--(Y28=""),IF($Y$2="(nonblank)",--(Y28<>""),--ISNUMBER(SEARCH($Y$2,Y28))))) | BK28: =IF($Z$2="",1,IF($Z$2="(blank)",--(Z28=""),IF($Z$2="(nonblank)",--(Z28<>""),--ISNUMBER(SEARCH($Z$2,Z28))))) | BL28: =IF($AA$2="",1,IF($AA$2="(blank)",--(AA28=""),IF($AA$2="(nonblank)",--(AA28<>""),--ISNUMBER(SEARCH($AA$2,AA28))))) | BM28: =IF($AB$2="",1,IF($AB$2="(blank)",--(AB28=""),IF($AB$2="(nonblank)",--(AB28<>""),--ISNUMBER(SEARCH($AB$2,AB28))))) | BN28: =IF($AC$2="",1,IF($AC$2="(blank)",--(AC28=""),IF($AC$2="(nonblank)",--(AC28<>""),--ISNUMBER(SEARCH($AC$2,AC28))))) | BO28: =IF($AD$2="",1,IF($AD$2="(blank)",--(AD28=""),IF($AD$2="(nonblank)",--(AD28<>""),--ISNUMBER(SEARCH($AD$2,AD28))))) | BP28: =IF($AE$2="",1,IF($AE$2="(blank)",--(AE28=""),IF($AE$2="(nonblank)",--(AE28<>""),--ISNUMBER(SEARCH($AE$2,AE28))))) | BQ28: =IF($AF$2="",1,IF($AF$2="(blank)",--(AF28=""),IF($AF$2="(nonblank)",--(AF28<>""),--ISNUMBER(SEARCH($AF$2,AF28))))) | BR28: =IF($AG$2="",1,IF($AG$2="(blank)",--(AG28=""),IF($AG$2="(nonblank)",--(AG28<>""),--ISNUMBER(SEARCH($AG$2,AG28))))) | BS28: =IF($AH$2="",1,IF($AH$2="(blank)",--(AH28=""),IF($AH$2="(nonblank)",--(AH28<>""),--ISNUMBER(SEARCH($AH$2,AH28))))) | BT28: =IF(COUNTIF($AL28:$BS28,0)>0,0,1)
A29: 3 | B29: Scrap of 33 KV CT | C29: 90002 | D29: 21978 | E29: NO | F29: 2040 | G29: STERLING ENTERPRISES | H29: 270006 | I29: =ROUND(H29*18%,0) | J29: =+H29+I29 | K29: =ROUND((H29+I29)*2%,0) | L29: =H29*0.1% | M29: =H29*2.25%*118% | N29: =H29*2.25%*2% | O29: =M29-N29 | P29: =ROUND(O29+L29,0) | Q29: 0 | R29: =ROUND(H29*Q29,0) | S29: =ROUND(H29*117.65%-R29,0) | T29: =ROUND(H29*25%,0) | U29: 67502 | V29: 11.08.2026 | W29: =ROUND(H29*92.65%-R29,0) | Y29: 0 | Z29: =IF(IF(OR(AB29="",AB29=0),TODAY(),DATE(VALUE(RIGHT(AB29,4)),VALUE(MID(AB29,4,2)),VALUE(LEFT(AB29,2))))<=DATE(2026,8,24),0,H29*0.0118*CEILING((IF(OR(AB29="",AB29=0),TODAY(),DATE(VALUE(RIGHT(AB29,4)),VALUE(MID(AB29,4,2)),VALUE(LEFT(AB29,2))))-DATE(2026,8,22))/7,1)) | AC29: =U29+X29+AA29 | AD29: =S29-AC29 | AE29: =IF(AD29="","",IF(AD29<=5,"SETTLED","OUTSTANDING")) | AL29: =IF($A$2="",1,IF($A$2="(blank)",--(A29=""),IF($A$2="(nonblank)",--(A29<>""),--ISNUMBER(SEARCH($A$2,A29))))) | AM29: =IF($B$2="",1,IF($B$2="(blank)",--(B29=""),IF($B$2="(nonblank)",--(B29<>""),--ISNUMBER(SEARCH($B$2,B29))))) | AN29: =IF($C$2="",1,IF($C$2="(blank)",--(C29=""),IF($C$2="(nonblank)",--(C29<>""),--ISNUMBER(SEARCH($C$2,C29))))) | AO29: =IF($D$2="",1,IF($D$2="(blank)",--(D29=""),IF($D$2="(nonblank)",--(D29<>""),--ISNUMBER(SEARCH($D$2,D29))))) | AP29: =IF($E$2="",1,IF($E$2="(blank)",--(E29=""),IF($E$2="(nonblank)",--(E29<>""),--ISNUMBER(SEARCH($E$2,E29))))) | AQ29: =IF($F$2="",1,IF($F$2="(blank)",--(F29=""),IF($F$2="(nonblank)",--(F29<>""),--ISNUMBER(SEARCH($F$2,F29))))) | AR29: =IF($G$2="",1,IF($G$2="(blank)",--(G29=""),IF($G$2="(nonblank)",--(G29<>""),--ISNUMBER(SEARCH($G$2,G29))))) | AS29: =IF($H$2="",1,IF($H$2="(blank)",--(H29=""),IF($H$2="(nonblank)",--(H29<>""),--ISNUMBER(SEARCH($H$2,H29))))) | AT29: =IF($I$2="",1,IF($I$2="(blank)",--(I29=""),IF($I$2="(nonblank)",--(I29<>""),--ISNUMBER(SEARCH($I$2,I29))))) | AU29: =IF($J$2="",1,IF($J$2="(blank)",--(J29=""),IF($J$2="(nonblank)",--(J29<>""),--ISNUMBER(SEARCH($J$2,J29))))) | AV29: =IF($K$2="",1,IF($K$2="(blank)",--(K29=""),IF($K$2="(nonblank)",--(K29<>""),--ISNUMBER(SEARCH($K$2,K29))))) | AW29: =IF($L$2="",1,IF($L$2="(blank)",--(L29=""),IF($L$2="(nonblank)",--(L29<>""),--ISNUMBER(SEARCH($L$2,L29))))) | AX29: =IF($M$2="",1,IF($M$2="(blank)",--(M29=""),IF($M$2="(nonblank)",--(M29<>""),--ISNUMBER(SEARCH($M$2,M29))))) | AY29: =IF($N$2="",1,IF($N$2="(blank)",--(N29=""),IF($N$2="(nonblank)",--(N29<>""),--ISNUMBER(SEARCH($N$2,N29))))) | AZ29: =IF($O$2="",1,IF($O$2="(blank)",--(O29=""),IF($O$2="(nonblank)",--(O29<>""),--ISNUMBER(SEARCH($O$2,O29))))) | BA29: =IF($P$2="",1,IF($P$2="(blank)",--(P29=""),IF($P$2="(nonblank)",--(P29<>""),--ISNUMBER(SEARCH($P$2,P29))))) | BB29: =IF($Q$2="",1,IF($Q$2="(blank)",--(Q29=""),IF($Q$2="(nonblank)",--(Q29<>""),--ISNUMBER(SEARCH($Q$2,Q29))))) | BC29: =IF($R$2="",1,IF($R$2="(blank)",--(R29=""),IF($R$2="(nonblank)",--(R29<>""),--ISNUMBER(SEARCH($R$2,R29))))) | BD29: =IF($S$2="",1,IF($S$2="(blank)",--(S29=""),IF($S$2="(nonblank)",--(S29<>""),--ISNUMBER(SEARCH($S$2,S29))))) | BE29: =IF($T$2="",1,IF($T$2="(blank)",--(T29=""),IF($T$2="(nonblank)",--(T29<>""),--ISNUMBER(SEARCH($T$2,T29))))) | BF29: =IF($U$2="",1,IF($U$2="(blank)",--(U29=""),IF($U$2="(nonblank)",--(U29<>""),--ISNUMBER(SEARCH($U$2,U29))))) | BG29: =IF($V$2="",1,IF($V$2="(blank)",--(V29=""),IF($V$2="(nonblank)",--(V29<>""),--ISNUMBER(SEARCH($V$2,V29))))) | BH29: =IF($W$2="",1,IF($W$2="(blank)",--(W29=""),IF($W$2="(nonblank)",--(W29<>""),--ISNUMBER(SEARCH($W$2,W29))))) | BI29: =IF($X$2="",1,IF($X$2="(blank)",--(X29=""),IF($X$2="(nonblank)",--(X29<>""),--ISNUMBER(SEARCH($X$2,X29))))) | BJ29: =IF($Y$2="",1,IF($Y$2="(blank)",--(Y29=""),IF($Y$2="(nonblank)",--(Y29<>""),--ISNUMBER(SEARCH($Y$2,Y29))))) | BK29: =IF($Z$2="",1,IF($Z$2="(blank)",--(Z29=""),IF($Z$2="(nonblank)",--(Z29<>""),--ISNUMBER(SEARCH($Z$2,Z29))))) | BL29: =IF($AA$2="",1,IF($AA$2="(blank)",--(AA29=""),IF($AA$2="(nonblank)",--(AA29<>""),--ISNUMBER(SEARCH($AA$2,AA29))))) | BM29: =IF($AB$2="",1,IF($AB$2="(blank)",--(AB29=""),IF($AB$2="(nonblank)",--(AB29<>""),--ISNUMBER(SEARCH($AB$2,AB29))))) | BN29: =IF($AC$2="",1,IF($AC$2="(blank)",--(AC29=""),IF($AC$2="(nonblank)",--(AC29<>""),--ISNUMBER(SEARCH($AC$2,AC29))))) | BO29: =IF($AD$2="",1,IF($AD$2="(blank)",--(AD29=""),IF($AD$2="(nonblank)",--(AD29<>""),--ISNUMBER(SEARCH($AD$2,AD29))))) | BP29: =IF($AE$2="",1,IF($AE$2="(blank)",--(AE29=""),IF($AE$2="(nonblank)",--(AE29<>""),--ISNUMBER(SEARCH($AE$2,AE29))))) | BQ29: =IF($AF$2="",1,IF($AF$2="(blank)",--(AF29=""),IF($AF$2="(nonblank)",--(AF29<>""),--ISNUMBER(SEARCH($AF$2,AF29))))) | BR29: =IF($AG$2="",1,IF($AG$2="(blank)",--(AG29=""),IF($AG$2="(nonblank)",--(AG29<>""),--ISNUMBER(SEARCH($AG$2,AG29))))) | BS29: =IF($AH$2="",1,IF($AH$2="(blank)",--(AH29=""),IF($AH$2="(nonblank)",--(AH29<>""),--ISNUMBER(SEARCH($AH$2,AH29))))) | BT29: =IF(COUNTIF($AL29:$BS29,0)>0,0,1)
A30: 5 | B30: Scrap of 132 KV CT | C30: 80000 | D30: 21979 | E30: NO | F30: 2043 | G30: NATIONAL ENTERPRISES | H30: 400000 | I30: =ROUND(H30*18%,0) | J30: =+H30+I30 | K30: =ROUND((H30+I30)*2%,0) | L30: =H30*0.1% | M30: =H30*2.25%*118% | N30: =H30*2.25%*2% | O30: =M30-N30 | P30: =ROUND(O30+L30,0) | Q30: 0 | R30: =ROUND(H30*Q30,0) | S30: =ROUND(H30*117.65%-R30,0) | T30: =ROUND(H30*25%,0) | U30: =+T30 | V30: 13.08.2026 | W30: =ROUND(H30*92.65%-R30,0) | X30: 370600 | Y30: 24.08.2026 | Z30: =IF(IF(OR(AB30="",AB30=0),TODAY(),DATE(VALUE(RIGHT(AB30,4)),VALUE(MID(AB30,4,2)),VALUE(LEFT(AB30,2))))<=DATE(2026,8,24),0,H30*0.0118*CEILING((IF(OR(AB30="",AB30=0),TODAY(),DATE(VALUE(RIGHT(AB30,4)),VALUE(MID(AB30,4,2)),VALUE(LEFT(AB30,2))))-DATE(2026,8,22))/7,1)) | AC30: =U30+X30+AA30 | AD30: =S30-AC30 | AE30: =IF(AD30="","",IF(AD30<=5,"SETTLED","OUTSTANDING")) | AF30: DR2640100038 | AG30: 1800003311 | AH30: 27.08.2026 | AL30: =IF($A$2="",1,IF($A$2="(blank)",--(A30=""),IF($A$2="(nonblank)",--(A30<>""),--ISNUMBER(SEARCH($A$2,A30))))) | AM30: =IF($B$2="",1,IF($B$2="(blank)",--(B30=""),IF($B$2="(nonblank)",--(B30<>""),--ISNUMBER(SEARCH($B$2,B30))))) | AN30: =IF($C$2="",1,IF($C$2="(blank)",--(C30=""),IF($C$2="(nonblank)",--(C30<>""),--ISNUMBER(SEARCH($C$2,C30))))) | AO30: =IF($D$2="",1,IF($D$2="(blank)",--(D30=""),IF($D$2="(nonblank)",--(D30<>""),--ISNUMBER(SEARCH($D$2,D30))))) | AP30: =IF($E$2="",1,IF($E$2="(blank)",--(E30=""),IF($E$2="(nonblank)",--(E30<>""),--ISNUMBER(SEARCH($E$2,E30))))) | AQ30: =IF($F$2="",1,IF($F$2="(blank)",--(F30=""),IF($F$2="(nonblank)",--(F30<>""),--ISNUMBER(SEARCH($F$2,F30))))) | AR30: =IF($G$2="",1,IF($G$2="(blank)",--(G30=""),IF($G$2="(nonblank)",--(G30<>""),--ISNUMBER(SEARCH($G$2,G30))))) | AS30: =IF($H$2="",1,IF($H$2="(blank)",--(H30=""),IF($H$2="(nonblank)",--(H30<>""),--ISNUMBER(SEARCH($H$2,H30))))) | AT30: =IF($I$2="",1,IF($I$2="(blank)",--(I30=""),IF($I$2="(nonblank)",--(I30<>""),--ISNUMBER(SEARCH($I$2,I30))))) | AU30: =IF($J$2="",1,IF($J$2="(blank)",--(J30=""),IF($J$2="(nonblank)",--(J30<>""),--ISNUMBER(SEARCH($J$2,J30))))) | AV30: =IF($K$2="",1,IF($K$2="(blank)",--(K30=""),IF($K$2="(nonblank)",--(K30<>""),--ISNUMBER(SEARCH($K$2,K30))))) | AW30: =IF($L$2="",1,IF($L$2="(blank)",--(L30=""),IF($L$2="(nonblank)",--(L30<>""),--ISNUMBER(SEARCH($L$2,L30))))) | AX30: =IF($M$2="",1,IF($M$2="(blank)",--(M30=""),IF($M$2="(nonblank)",--(M30<>""),--ISNUMBER(SEARCH($M$2,M30))))) | AY30: =IF($N$2="",1,IF($N$2="(blank)",--(N30=""),IF($N$2="(nonblank)",--(N30<>""),--ISNUMBER(SEARCH($N$2,N30))))) | AZ30: =IF($O$2="",1,IF($O$2="(blank)",--(O30=""),IF($O$2="(nonblank)",--(O30<>""),--ISNUMBER(SEARCH($O$2,O30))))) | BA30: =IF($P$2="",1,IF($P$2="(blank)",--(P30=""),IF($P$2="(nonblank)",--(P30<>""),--ISNUMBER(SEARCH($P$2,P30))))) | BB30: =IF($Q$2="",1,IF($Q$2="(blank)",--(Q30=""),IF($Q$2="(nonblank)",--(Q30<>""),--ISNUMBER(SEARCH($Q$2,Q30))))) | BC30: =IF($R$2="",1,IF($R$2="(blank)",--(R30=""),IF($R$2="(nonblank)",--(R30<>""),--ISNUMBER(SEARCH($R$2,R30))))) | BD30: =IF($S$2="",1,IF($S$2="(blank)",--(S30=""),IF($S$2="(nonblank)",--(S30<>""),--ISNUMBER(SEARCH($S$2,S30))))) | BE30: =IF($T$2="",1,IF($T$2="(blank)",--(T30=""),IF($T$2="(nonblank)",--(T30<>""),--ISNUMBER(SEARCH($T$2,T30))))) | BF30: =IF($U$2="",1,IF($U$2="(blank)",--(U30=""),IF($U$2="(nonblank)",--(U30<>""),--ISNUMBER(SEARCH($U$2,U30))))) | BG30: =IF($V$2="",1,IF($V$2="(blank)",--(V30=""),IF($V$2="(nonblank)",--(V30<>""),--ISNUMBER(SEARCH($V$2,V30))))) | BH30: =IF($W$2="",1,IF($W$2="(blank)",--(W30=""),IF($W$2="(nonblank)",--(W30<>""),--ISNUMBER(SEARCH($W$2,W30))))) | BI30: =IF($X$2="",1,IF($X$2="(blank)",--(X30=""),IF($X$2="(nonblank)",--(X30<>""),--ISNUMBER(SEARCH($X$2,X30))))) | BJ30: =IF($Y$2="",1,IF($Y$2="(blank)",--(Y30=""),IF($Y$2="(nonblank)",--(Y30<>""),--ISNUMBER(SEARCH($Y$2,Y30))))) | BK30: =IF($Z$2="",1,IF($Z$2="(blank)",--(Z30=""),IF($Z$2="(nonblank)",--(Z30<>""),--ISNUMBER(SEARCH($Z$2,Z30))))) | BL30: =IF($AA$2="",1,IF($AA$2="(blank)",--(AA30=""),IF($AA$2="(nonblank)",--(AA30<>""),--ISNUMBER(SEARCH($AA$2,AA30))))) | BM30: =IF($AB$2="",1,IF($AB$2="(blank)",--(AB30=""),IF($AB$2="(nonblank)",--(AB30<>""),--ISNUMBER(SEARCH($AB$2,AB30))))) | BN30: =IF($AC$2="",1,IF($AC$2="(blank)",--(AC30=""),IF($AC$2="(nonblank)",--(AC30<>""),--ISNUMBER(SEARCH($AC$2,AC30))))) | BO30: =IF($AD$2="",1,IF($AD$2="(blank)",--(AD30=""),IF($AD$2="(nonblank)",--(AD30<>""),--ISNUMBER(SEARCH($AD$2,AD30))))) | BP30: =IF($AE$2="",1,IF($AE$2="(blank)",--(AE30=""),IF($AE$2="(nonblank)",--(AE30<>""),--ISNUMBER(SEARCH($AE$2,AE30))))) | BQ30: =IF($AF$2="",1,IF($AF$2="(blank)",--(AF30=""),IF($AF$2="(nonblank)",--(AF30<>""),--ISNUMBER(SEARCH($AF$2,AF30))))) | BR30: =IF($AG$2="",1,IF($AG$2="(blank)",--(AG30=""),IF($AG$2="(nonblank)",--(AG30<>""),--ISNUMBER(SEARCH($AG$2,AG30))))) | BS30: =IF($AH$2="",1,IF($AH$2="(blank)",--(AH30=""),IF($AH$2="(nonblank)",--(AH30<>""),--ISNUMBER(SEARCH($AH$2,AH30))))) | BT30: =IF(COUNTIF($AL30:$BS30,0)>0,0,1)
A31: 670 | B31: Scrap of AAAC Earth wire | C31: 309 | D31: 21979 | E31: KG | F31: 2046 | G31: SAHARA ENTERPRISES | H31: 207030 | I31: =ROUND(H31*18%,0) | J31: =+H31+I31 | K31: =ROUND((H31+I31)*2%,0) | L31: =H31*0.1% | M31: =H31*2.25%*118% | N31: =H31*2.25%*2% | O31: =M31-N31 | P31: =ROUND(O31+L31,0) | Q31: 0 | R31: =ROUND(H31*Q31,0) | S31: =ROUND(H31*117.65%-R31,0) | T31: =ROUND(H31*25%,0) | U31: 51758 | V31: 11.08.2026 | W31: =ROUND(H31*92.65%-R31,0) | X31: 191812 | Y31: 21.08.2026 | Z31: =IF(IF(OR(AB31="",AB31=0),TODAY(),DATE(VALUE(RIGHT(AB31,4)),VALUE(MID(AB31,4,2)),VALUE(LEFT(AB31,2))))<=DATE(2026,8,24),0,H31*0.0118*CEILING((IF(OR(AB31="",AB31=0),TODAY(),DATE(VALUE(RIGHT(AB31,4)),VALUE(MID(AB31,4,2)),VALUE(LEFT(AB31,2))))-DATE(2026,8,22))/7,1)) | AC31: =U31+X31+AA31 | AD31: =S31-AC31 | AE31: =IF(AD31="","",IF(AD31<=5,"SETTLED","OUTSTANDING")) | AF31: DR2640100041 | AG31: 1800003316 | AH31: 27.08.2026 | AL31: =IF($A$2="",1,IF($A$2="(blank)",--(A31=""),IF($A$2="(nonblank)",--(A31<>""),--ISNUMBER(SEARCH($A$2,A31))))) | AM31: =IF($B$2="",1,IF($B$2="(blank)",--(B31=""),IF($B$2="(nonblank)",--(B31<>""),--ISNUMBER(SEARCH($B$2,B31))))) | AN31: =IF($C$2="",1,IF($C$2="(blank)",--(C31=""),IF($C$2="(nonblank)",--(C31<>""),--ISNUMBER(SEARCH($C$2,C31))))) | AO31: =IF($D$2="",1,IF($D$2="(blank)",--(D31=""),IF($D$2="(nonblank)",--(D31<>""),--ISNUMBER(SEARCH($D$2,D31))))) | AP31: =IF($E$2="",1,IF($E$2="(blank)",--(E31=""),IF($E$2="(nonblank)",--(E31<>""),--ISNUMBER(SEARCH($E$2,E31))))) | AQ31: =IF($F$2="",1,IF($F$2="(blank)",--(F31=""),IF($F$2="(nonblank)",--(F31<>""),--ISNUMBER(SEARCH($F$2,F31))))) | AR31: =IF($G$2="",1,IF($G$2="(blank)",--(G31=""),IF($G$2="(nonblank)",--(G31<>""),--ISNUMBER(SEARCH($G$2,G31))))) | AS31: =IF($H$2="",1,IF($H$2="(blank)",--(H31=""),IF($H$2="(nonblank)",--(H31<>""),--ISNUMBER(SEARCH($H$2,H31))))) | AT31: =IF($I$2="",1,IF($I$2="(blank)",--(I31=""),IF($I$2="(nonblank)",--(I31<>""),--ISNUMBER(SEARCH($I$2,I31))))) | AU31: =IF($J$2="",1,IF($J$2="(blank)",--(J31=""),IF($J$2="(nonblank)",--(J31<>""),--ISNUMBER(SEARCH($J$2,J31))))) | AV31: =IF($K$2="",1,IF($K$2="(blank)",--(K31=""),IF($K$2="(nonblank)",--(K31<>""),--ISNUMBER(SEARCH($K$2,K31))))) | AW31: =IF($L$2="",1,IF($L$2="(blank)",--(L31=""),IF($L$2="(nonblank)",--(L31<>""),--ISNUMBER(SEARCH($L$2,L31))))) | AX31: =IF($M$2="",1,IF($M$2="(blank)",--(M31=""),IF($M$2="(nonblank)",--(M31<>""),--ISNUMBER(SEARCH($M$2,M31))))) | AY31: =IF($N$2="",1,IF($N$2="(blank)",--(N31=""),IF($N$2="(nonblank)",--(N31<>""),--ISNUMBER(SEARCH($N$2,N31))))) | AZ31: =IF($O$2="",1,IF($O$2="(blank)",--(O31=""),IF($O$2="(nonblank)",--(O31<>""),--ISNUMBER(SEARCH($O$2,O31))))) | BA31: =IF($P$2="",1,IF($P$2="(blank)",--(P31=""),IF($P$2="(nonblank)",--(P31<>""),--ISNUMBER(SEARCH($P$2,P31))))) | BB31: =IF($Q$2="",1,IF($Q$2="(blank)",--(Q31=""),IF($Q$2="(nonblank)",--(Q31<>""),--ISNUMBER(SEARCH($Q$2,Q31))))) | BC31: =IF($R$2="",1,IF($R$2="(blank)",--(R31=""),IF($R$2="(nonblank)",--(R31<>""),--ISNUMBER(SEARCH($R$2,R31))))) | BD31: =IF($S$2="",1,IF($S$2="(blank)",--(S31=""),IF($S$2="(nonblank)",--(S31<>""),--ISNUMBER(SEARCH($S$2,S31))))) | BE31: =IF($T$2="",1,IF($T$2="(blank)",--(T31=""),IF($T$2="(nonblank)",--(T31<>""),--ISNUMBER(SEARCH($T$2,T31))))) | BF31: =IF($U$2="",1,IF($U$2="(blank)",--(U31=""),IF($U$2="(nonblank)",--(U31<>""),--ISNUMBER(SEARCH($U$2,U31))))) | BG31: =IF($V$2="",1,IF($V$2="(blank)",--(V31=""),IF($V$2="(nonblank)",--(V31<>""),--ISNUMBER(SEARCH($V$2,V31))))) | BH31: =IF($W$2="",1,IF($W$2="(blank)",--(W31=""),IF($W$2="(nonblank)",--(W31<>""),--ISNUMBER(SEARCH($W$2,W31))))) | BI31: =IF($X$2="",1,IF($X$2="(blank)",--(X31=""),IF($X$2="(nonblank)",--(X31<>""),--ISNUMBER(SEARCH($X$2,X31))))) | BJ31: =IF($Y$2="",1,IF($Y$2="(blank)",--(Y31=""),IF($Y$2="(nonblank)",--(Y31<>""),--ISNUMBER(SEARCH($Y$2,Y31))))) | BK31: =IF($Z$2="",1,IF($Z$2="(blank)",--(Z31=""),IF($Z$2="(nonblank)",--(Z31<>""),--ISNUMBER(SEARCH($Z$2,Z31))))) | BL31: =IF($AA$2="",1,IF($AA$2="(blank)",--(AA31=""),IF($AA$2="(nonblank)",--(AA31<>""),--ISNUMBER(SEARCH($AA$2,AA31))))) | BM31: =IF($AB$2="",1,IF($AB$2="(blank)",--(AB31=""),IF($AB$2="(nonblank)",--(AB31<>""),--ISNUMBER(SEARCH($AB$2,AB31))))) | BN31: =IF($AC$2="",1,IF($AC$2="(blank)",--(AC31=""),IF($AC$2="(nonblank)",--(AC31<>""),--ISNUMBER(SEARCH($AC$2,AC31))))) | BO31: =IF($AD$2="",1,IF($AD$2="(blank)",--(AD31=""),IF($AD$2="(nonblank)",--(AD31<>""),--ISNUMBER(SEARCH($AD$2,AD31))))) | BP31: =IF($AE$2="",1,IF($AE$2="(blank)",--(AE31=""),IF($AE$2="(nonblank)",--(AE31<>""),--ISNUMBER(SEARCH($AE$2,AE31))))) | BQ31: =IF($AF$2="",1,IF($AF$2="(blank)",--(AF31=""),IF($AF$2="(nonblank)",--(AF31<>""),--ISNUMBER(SEARCH($AF$2,AF31))))) | BR31: =IF($AG$2="",1,IF($AG$2="(blank)",--(AG31=""),IF($AG$2="(nonblank)",--(AG31<>""),--ISNUMBER(SEARCH($AG$2,AG31))))) | BS31: =IF($AH$2="",1,IF($AH$2="(blank)",--(AH31=""),IF($AH$2="(nonblank)",--(AH31<>""),--ISNUMBER(SEARCH($AH$2,AH31))))) | BT31: =IF(COUNTIF($AL31:$BS31,0)>0,0,1)
A32: 2 | B32: Scrap of 220 KV CT | C32: 80006 | D32: 21979 | E32: NO | F32: 2055 | G32: NATIONAL ENTERPRISES | H32: 160012 | I32: =ROUND(H32*18%,0) | J32: =+H32+I32 | K32: =ROUND((H32+I32)*2%,0) | L32: =H32*0.1% | M32: =H32*2.25%*118% | N32: =H32*2.25%*2% | O32: =M32-N32 | P32: =ROUND(O32+L32,0) | Q32: 0 | R32: =ROUND(H32*Q32,0) | S32: =ROUND(H32*117.65%-R32,0) | T32: =ROUND(H32*25%,0) | U32: =+T32 | V32: 13.08.2026 | W32: =ROUND(H32*92.65%-R32,0) | X32: 148251 | Y32: 24.08.2026 | Z32: =IF(IF(OR(AB32="",AB32=0),TODAY(),DATE(VALUE(RIGHT(AB32,4)),VALUE(MID(AB32,4,2)),VALUE(LEFT(AB32,2))))<=DATE(2026,8,24),0,H32*0.0118*CEILING((IF(OR(AB32="",AB32=0),TODAY(),DATE(VALUE(RIGHT(AB32,4)),VALUE(MID(AB32,4,2)),VALUE(LEFT(AB32,2))))-DATE(2026,8,22))/7,1)) | AC32: =U32+X32+AA32 | AD32: =S32-AC32 | AE32: =IF(AD32="","",IF(AD32<=5,"SETTLED","OUTSTANDING")) | AF32: DR2640100039 | AG32: 1800003312 | AH32: 27.08.2026 | AL32: =IF($A$2="",1,IF($A$2="(blank)",--(A32=""),IF($A$2="(nonblank)",--(A32<>""),--ISNUMBER(SEARCH($A$2,A32))))) | AM32: =IF($B$2="",1,IF($B$2="(blank)",--(B32=""),IF($B$2="(nonblank)",--(B32<>""),--ISNUMBER(SEARCH($B$2,B32))))) | AN32: =IF($C$2="",1,IF($C$2="(blank)",--(C32=""),IF($C$2="(nonblank)",--(C32<>""),--ISNUMBER(SEARCH($C$2,C32))))) | AO32: =IF($D$2="",1,IF($D$2="(blank)",--(D32=""),IF($D$2="(nonblank)",--(D32<>""),--ISNUMBER(SEARCH($D$2,D32))))) | AP32: =IF($E$2="",1,IF($E$2="(blank)",--(E32=""),IF($E$2="(nonblank)",--(E32<>""),--ISNUMBER(SEARCH($E$2,E32))))) | AQ32: =IF($F$2="",1,IF($F$2="(blank)",--(F32=""),IF($F$2="(nonblank)",--(F32<>""),--ISNUMBER(SEARCH($F$2,F32))))) | AR32: =IF($G$2="",1,IF($G$2="(blank)",--(G32=""),IF($G$2="(nonblank)",--(G32<>""),--ISNUMBER(SEARCH($G$2,G32))))) | AS32: =IF($H$2="",1,IF($H$2="(blank)",--(H32=""),IF($H$2="(nonblank)",--(H32<>""),--ISNUMBER(SEARCH($H$2,H32))))) | AT32: =IF($I$2="",1,IF($I$2="(blank)",--(I32=""),IF($I$2="(nonblank)",--(I32<>""),--ISNUMBER(SEARCH($I$2,I32))))) | AU32: =IF($J$2="",1,IF($J$2="(blank)",--(J32=""),IF($J$2="(nonblank)",--(J32<>""),--ISNUMBER(SEARCH($J$2,J32))))) | AV32: =IF($K$2="",1,IF($K$2="(blank)",--(K32=""),IF($K$2="(nonblank)",--(K32<>""),--ISNUMBER(SEARCH($K$2,K32))))) | AW32: =IF($L$2="",1,IF($L$2="(blank)",--(L32=""),IF($L$2="(nonblank)",--(L32<>""),--ISNUMBER(SEARCH($L$2,L32))))) | AX32: =IF($M$2="",1,IF($M$2="(blank)",--(M32=""),IF($M$2="(nonblank)",--(M32<>""),--ISNUMBER(SEARCH($M$2,M32))))) | AY32: =IF($N$2="",1,IF($N$2="(blank)",--(N32=""),IF($N$2="(nonblank)",--(N32<>""),--ISNUMBER(SEARCH($N$2,N32))))) | AZ32: =IF($O$2="",1,IF($O$2="(blank)",--(O32=""),IF($O$2="(nonblank)",--(O32<>""),--ISNUMBER(SEARCH($O$2,O32))))) | BA32: =IF($P$2="",1,IF($P$2="(blank)",--(P32=""),IF($P$2="(nonblank)",--(P32<>""),--ISNUMBER(SEARCH($P$2,P32))))) | BB32: =IF($Q$2="",1,IF($Q$2="(blank)",--(Q32=""),IF($Q$2="(nonblank)",--(Q32<>""),--ISNUMBER(SEARCH($Q$2,Q32))))) | BC32: =IF($R$2="",1,IF($R$2="(blank)",--(R32=""),IF($R$2="(nonblank)",--(R32<>""),--ISNUMBER(SEARCH($R$2,R32))))) | BD32: =IF($S$2="",1,IF($S$2="(blank)",--(S32=""),IF($S$2="(nonblank)",--(S32<>""),--ISNUMBER(SEARCH($S$2,S32))))) | BE32: =IF($T$2="",1,IF($T$2="(blank)",--(T32=""),IF($T$2="(nonblank)",--(T32<>""),--ISNUMBER(SEARCH($T$2,T32))))) | BF32: =IF($U$2="",1,IF($U$2="(blank)",--(U32=""),IF($U$2="(nonblank)",--(U32<>""),--ISNUMBER(SEARCH($U$2,U32))))) | BG32: =IF($V$2="",1,IF($V$2="(blank)",--(V32=""),IF($V$2="(nonblank)",--(V32<>""),--ISNUMBER(SEARCH($V$2,V32))))) | BH32: =IF($W$2="",1,IF($W$2="(blank)",--(W32=""),IF($W$2="(nonblank)",--(W32<>""),--ISNUMBER(SEARCH($W$2,W32))))) | BI32: =IF($X$2="",1,IF($X$2="(blank)",--(X32=""),IF($X$2="(nonblank)",--(X32<>""),--ISNUMBER(SEARCH($X$2,X32))))) | BJ32: =IF($Y$2="",1,IF($Y$2="(blank)",--(Y32=""),IF($Y$2="(nonblank)",--(Y32<>""),--ISNUMBER(SEARCH($Y$2,Y32))))) | BK32: =IF($Z$2="",1,IF($Z$2="(blank)",--(Z32=""),IF($Z$2="(nonblank)",--(Z32<>""),--ISNUMBER(SEARCH($Z$2,Z32))))) | BL32: =IF($AA$2="",1,IF($AA$2="(blank)",--(AA32=""),IF($AA$2="(nonblank)",--(AA32<>""),--ISNUMBER(SEARCH($AA$2,AA32))))) | BM32: =IF($AB$2="",1,IF($AB$2="(blank)",--(AB32=""),IF($AB$2="(nonblank)",--(AB32<>""),--ISNUMBER(SEARCH($AB$2,AB32))))) | BN32: =IF($AC$2="",1,IF($AC$2="(blank)",--(AC32=""),IF($AC$2="(nonblank)",--(AC32<>""),--ISNUMBER(SEARCH($AC$2,AC32))))) | BO32: =IF($AD$2="",1,IF($AD$2="(blank)",--(AD32=""),IF($AD$2="(nonblank)",--(AD32<>""),--ISNUMBER(SEARCH($AD$2,AD32))))) | BP32: =IF($AE$2="",1,IF($AE$2="(blank)",--(AE32=""),IF($AE$2="(nonblank)",--(AE32<>""),--ISNUMBER(SEARCH($AE$2,AE32))))) | BQ32: =IF($AF$2="",1,IF($AF$2="(blank)",--(AF32=""),IF($AF$2="(nonblank)",--(AF32<>""),--ISNUMBER(SEARCH($AF$2,AF32))))) | BR32: =IF($AG$2="",1,IF($AG$2="(blank)",--(AG32=""),IF($AG$2="(nonblank)",--(AG32<>""),--ISNUMBER(SEARCH($AG$2,AG32))))) | BS32: =IF($AH$2="",1,IF($AH$2="(blank)",--(AH32=""),IF($AH$2="(nonblank)",--(AH32<>""),--ISNUMBER(SEARCH($AH$2,AH32))))) | BT32: =IF(COUNTIF($AL32:$BS32,0)>0,0,1)
A33: 1 | B33: Scrap of 33 KV GCB | C33: 29502 | D33: 21979 | E33: NO | F33: 2059 | G33: NATIONAL ENTERPRISES | H33: 29502 | I33: =ROUND(H33*18%,0) | J33: =+H33+I33 | K33: =ROUND((H33+I33)*2%,0) | L33: =H33*0.1% | M33: =H33*2.25%*118% | N33: =H33*2.25%*2% | O33: =M33-N33 | P33: =ROUND(O33+L33,0) | Q33: 0 | R33: =ROUND(H33*Q33,0) | S33: =ROUND(H33*117.65%-R33,0) | T33: =ROUND(H33*25%,0) | U33: =+T33 | V33: 13.08.2026 | W33: =ROUND(H33*92.65%-R33,0) | X33: 27332 | Y33: 24.08.2026 | Z33: =IF(IF(OR(AB33="",AB33=0),TODAY(),DATE(VALUE(RIGHT(AB33,4)),VALUE(MID(AB33,4,2)),VALUE(LEFT(AB33,2))))<=DATE(2026,8,24),0,H33*0.0118*CEILING((IF(OR(AB33="",AB33=0),TODAY(),DATE(VALUE(RIGHT(AB33,4)),VALUE(MID(AB33,4,2)),VALUE(LEFT(AB33,2))))-DATE(2026,8,22))/7,1)) | AC33: =U33+X33+AA33 | AD33: =S33-AC33 | AE33: =IF(AD33="","",IF(AD33<=5,"SETTLED","OUTSTANDING")) | AF33: DR2640100046 | AG33: 1800003313 | AH33: 27.08.2026 | AL33: =IF($A$2="",1,IF($A$2="(blank)",--(A33=""),IF($A$2="(nonblank)",--(A33<>""),--ISNUMBER(SEARCH($A$2,A33))))) | AM33: =IF($B$2="",1,IF($B$2="(blank)",--(B33=""),IF($B$2="(nonblank)",--(B33<>""),--ISNUMBER(SEARCH($B$2,B33))))) | AN33: =IF($C$2="",1,IF($C$2="(blank)",--(C33=""),IF($C$2="(nonblank)",--(C33<>""),--ISNUMBER(SEARCH($C$2,C33))))) | AO33: =IF($D$2="",1,IF($D$2="(blank)",--(D33=""),IF($D$2="(nonblank)",--(D33<>""),--ISNUMBER(SEARCH($D$2,D33))))) | AP33: =IF($E$2="",1,IF($E$2="(blank)",--(E33=""),IF($E$2="(nonblank)",--(E33<>""),--ISNUMBER(SEARCH($E$2,E33))))) | AQ33: =IF($F$2="",1,IF($F$2="(blank)",--(F33=""),IF($F$2="(nonblank)",--(F33<>""),--ISNUMBER(SEARCH($F$2,F33))))) | AR33: =IF($G$2="",1,IF($G$2="(blank)",--(G33=""),IF($G$2="(nonblank)",--(G33<>""),--ISNUMBER(SEARCH($G$2,G33))))) | AS33: =IF($H$2="",1,IF($H$2="(blank)",--(H33=""),IF($H$2="(nonblank)",--(H33<>""),--ISNUMBER(SEARCH($H$2,H33))))) | AT33: =IF($I$2="",1,IF($I$2="(blank)",--(I33=""),IF($I$2="(nonblank)",--(I33<>""),--ISNUMBER(SEARCH($I$2,I33))))) | AU33: =IF($J$2="",1,IF($J$2="(blank)",--(J33=""),IF($J$2="(nonblank)",--(J33<>""),--ISNUMBER(SEARCH($J$2,J33))))) | AV33: =IF($K$2="",1,IF($K$2="(blank)",--(K33=""),IF($K$2="(nonblank)",--(K33<>""),--ISNUMBER(SEARCH($K$2,K33))))) | AW33: =IF($L$2="",1,IF($L$2="(blank)",--(L33=""),IF($L$2="(nonblank)",--(L33<>""),--ISNUMBER(SEARCH($L$2,L33))))) | AX33: =IF($M$2="",1,IF($M$2="(blank)",--(M33=""),IF($M$2="(nonblank)",--(M33<>""),--ISNUMBER(SEARCH($M$2,M33))))) | AY33: =IF($N$2="",1,IF($N$2="(blank)",--(N33=""),IF($N$2="(nonblank)",--(N33<>""),--ISNUMBER(SEARCH($N$2,N33))))) | AZ33: =IF($O$2="",1,IF($O$2="(blank)",--(O33=""),IF($O$2="(nonblank)",--(O33<>""),--ISNUMBER(SEARCH($O$2,O33))))) | BA33: =IF($P$2="",1,IF($P$2="(blank)",--(P33=""),IF($P$2="(nonblank)",--(P33<>""),--ISNUMBER(SEARCH($P$2,P33))))) | BB33: =IF($Q$2="",1,IF($Q$2="(blank)",--(Q33=""),IF($Q$2="(nonblank)",--(Q33<>""),--ISNUMBER(SEARCH($Q$2,Q33))))) | BC33: =IF($R$2="",1,IF($R$2="(blank)",--(R33=""),IF($R$2="(nonblank)",--(R33<>""),--ISNUMBER(SEARCH($R$2,R33))))) | BD33: =IF($S$2="",1,IF($S$2="(blank)",--(S33=""),IF($S$2="(nonblank)",--(S33<>""),--ISNUMBER(SEARCH($S$2,S33))))) | BE33: =IF($T$2="",1,IF($T$2="(blank)",--(T33=""),IF($T$2="(nonblank)",--(T33<>""),--ISNUMBER(SEARCH($T$2,T33))))) | BF33: =IF($U$2="",1,IF($U$2="(blank)",--(U33=""),IF($U$2="(nonblank)",--(U33<>""),--ISNUMBER(SEARCH($U$2,U33))))) | BG33: =IF($V$2="",1,IF($V$2="(blank)",--(V33=""),IF($V$2="(nonblank)",--(V33<>""),--ISNUMBER(SEARCH($V$2,V33))))) | BH33: =IF($W$2="",1,IF($W$2="(blank)",--(W33=""),IF($W$2="(nonblank)",--(W33<>""),--ISNUMBER(SEARCH($W$2,W33))))) | BI33: =IF($X$2="",1,IF($X$2="(blank)",--(X33=""),IF($X$2="(nonblank)",--(X33<>""),--ISNUMBER(SEARCH($X$2,X33))))) | BJ33: =IF($Y$2="",1,IF($Y$2="(blank)",--(Y33=""),IF($Y$2="(nonblank)",--(Y33<>""),--ISNUMBER(SEARCH($Y$2,Y33))))) | BK33: =IF($Z$2="",1,IF($Z$2="(blank)",--(Z33=""),IF($Z$2="(nonblank)",--(Z33<>""),--ISNUMBER(SEARCH($Z$2,Z33))))) | BL33: =IF($AA$2="",1,IF($AA$2="(blank)",--(AA33=""),IF($AA$2="(nonblank)",--(AA33<>""),--ISNUMBER(SEARCH($AA$2,AA33))))) | BM33: =IF($AB$2="",1,IF($AB$2="(blank)",--(AB33=""),IF($AB$2="(nonblank)",--(AB33<>""),--ISNUMBER(SEARCH($AB$2,AB33))))) | BN33: =IF($AC$2="",1,IF($AC$2="(blank)",--(AC33=""),IF($AC$2="(nonblank)",--(AC33<>""),--ISNUMBER(SEARCH($AC$2,AC33))))) | BO33: =IF($AD$2="",1,IF($AD$2="(blank)",--(AD33=""),IF($AD$2="(nonblank)",--(AD33<>""),--ISNUMBER(SEARCH($AD$2,AD33))))) | BP33: =IF($AE$2="",1,IF($AE$2="(blank)",--(AE33=""),IF($AE$2="(nonblank)",--(AE33<>""),--ISNUMBER(SEARCH($AE$2,AE33))))) | BQ33: =IF($AF$2="",1,IF($AF$2="(blank)",--(AF33=""),IF($AF$2="(nonblank)",--(AF33<>""),--ISNUMBER(SEARCH($AF$2,AF33))))) | BR33: =IF($AG$2="",1,IF($AG$2="(blank)",--(AG33=""),IF($AG$2="(nonblank)",--(AG33<>""),--ISNUMBER(SEARCH($AG$2,AG33))))) | BS33: =IF($AH$2="",1,IF($AH$2="(blank)",--(AH33=""),IF($AH$2="(nonblank)",--(AH33<>""),--ISNUMBER(SEARCH($AH$2,AH33))))) | BT33: =IF(COUNTIF($AL33:$BS33,0)>0,0,1)
A34: 30 | B34: Scrap of Empty oil Barrels | C34: 702 | D34: 21979 | E34: NO | F34: 2062 | G34: STERLING ENTERPRISES | H34: 21060 | I34: =ROUND(H34*18%,0) | J34: =+H34+I34 | K34: =ROUND((H34+I34)*2%,0) | L34: =H34*0.1% | M34: =H34*2.25%*118% | N34: =H34*2.25%*2% | O34: =M34-N34 | P34: =ROUND(O34+L34,0) | Q34: 0 | R34: =ROUND(H34*Q34,0) | S34: =ROUND(H34*117.65%-R34,0) | T34: =ROUND(H34*25%,0) | U34: 5265 | V34: 11.08.2026 | W34: =ROUND(H34*92.65%-R34,0) | X34: 19512 | Y34: 11.08.2026 | Z34: =IF(IF(OR(AB34="",AB34=0),TODAY(),DATE(VALUE(RIGHT(AB34,4)),VALUE(MID(AB34,4,2)),VALUE(LEFT(AB34,2))))<=DATE(2026,8,24),0,H34*0.0118*CEILING((IF(OR(AB34="",AB34=0),TODAY(),DATE(VALUE(RIGHT(AB34,4)),VALUE(MID(AB34,4,2)),VALUE(LEFT(AB34,2))))-DATE(2026,8,22))/7,1)) | AC34: =U34+X34+AA34 | AD34: =S34-AC34 | AE34: =IF(AD34="","",IF(AD34<=5,"SETTLED","OUTSTANDING")) | AF34: DR2640100022 | AG34: 1800003161 | AH34: 14.08.2026 | AL34: =IF($A$2="",1,IF($A$2="(blank)",--(A34=""),IF($A$2="(nonblank)",--(A34<>""),--ISNUMBER(SEARCH($A$2,A34))))) | AM34: =IF($B$2="",1,IF($B$2="(blank)",--(B34=""),IF($B$2="(nonblank)",--(B34<>""),--ISNUMBER(SEARCH($B$2,B34))))) | AN34: =IF($C$2="",1,IF($C$2="(blank)",--(C34=""),IF($C$2="(nonblank)",--(C34<>""),--ISNUMBER(SEARCH($C$2,C34))))) | AO34: =IF($D$2="",1,IF($D$2="(blank)",--(D34=""),IF($D$2="(nonblank)",--(D34<>""),--ISNUMBER(SEARCH($D$2,D34))))) | AP34: =IF($E$2="",1,IF($E$2="(blank)",--(E34=""),IF($E$2="(nonblank)",--(E34<>""),--ISNUMBER(SEARCH($E$2,E34))))) | AQ34: =IF($F$2="",1,IF($F$2="(blank)",--(F34=""),IF($F$2="(nonblank)",--(F34<>""),--ISNUMBER(SEARCH($F$2,F34))))) | AR34: =IF($G$2="",1,IF($G$2="(blank)",--(G34=""),IF($G$2="(nonblank)",--(G34<>""),--ISNUMBER(SEARCH($G$2,G34))))) | AS34: =IF($H$2="",1,IF($H$2="(blank)",--(H34=""),IF($H$2="(nonblank)",--(H34<>""),--ISNUMBER(SEARCH($H$2,H34))))) | AT34: =IF($I$2="",1,IF($I$2="(blank)",--(I34=""),IF($I$2="(nonblank)",--(I34<>""),--ISNUMBER(SEARCH($I$2,I34))))) | AU34: =IF($J$2="",1,IF($J$2="(blank)",--(J34=""),IF($J$2="(nonblank)",--(J34<>""),--ISNUMBER(SEARCH($J$2,J34))))) | AV34: =IF($K$2="",1,IF($K$2="(blank)",--(K34=""),IF($K$2="(nonblank)",--(K34<>""),--ISNUMBER(SEARCH($K$2,K34))))) | AW34: =IF($L$2="",1,IF($L$2="(blank)",--(L34=""),IF($L$2="(nonblank)",--(L34<>""),--ISNUMBER(SEARCH($L$2,L34))))) | AX34: =IF($M$2="",1,IF($M$2="(blank)",--(M34=""),IF($M$2="(nonblank)",--(M34<>""),--ISNUMBER(SEARCH($M$2,M34))))) | AY34: =IF($N$2="",1,IF($N$2="(blank)",--(N34=""),IF($N$2="(nonblank)",--(N34<>""),--ISNUMBER(SEARCH($N$2,N34))))) | AZ34: =IF($O$2="",1,IF($O$2="(blank)",--(O34=""),IF($O$2="(nonblank)",--(O34<>""),--ISNUMBER(SEARCH($O$2,O34))))) | BA34: =IF($P$2="",1,IF($P$2="(blank)",--(P34=""),IF($P$2="(nonblank)",--(P34<>""),--ISNUMBER(SEARCH($P$2,P34))))) | BB34: =IF($Q$2="",1,IF($Q$2="(blank)",--(Q34=""),IF($Q$2="(nonblank)",--(Q34<>""),--ISNUMBER(SEARCH($Q$2,Q34))))) | BC34: =IF($R$2="",1,IF($R$2="(blank)",--(R34=""),IF($R$2="(nonblank)",--(R34<>""),--ISNUMBER(SEARCH($R$2,R34))))) | BD34: =IF($S$2="",1,IF($S$2="(blank)",--(S34=""),IF($S$2="(nonblank)",--(S34<>""),--ISNUMBER(SEARCH($S$2,S34))))) | BE34: =IF($T$2="",1,IF($T$2="(blank)",--(T34=""),IF($T$2="(nonblank)",--(T34<>""),--ISNUMBER(SEARCH($T$2,T34))))) | BF34: =IF($U$2="",1,IF($U$2="(blank)",--(U34=""),IF($U$2="(nonblank)",--(U34<>""),--ISNUMBER(SEARCH($U$2,U34))))) | BG34: =IF($V$2="",1,IF($V$2="(blank)",--(V34=""),IF($V$2="(nonblank)",--(V34<>""),--ISNUMBER(SEARCH($V$2,V34))))) | BH34: =IF($W$2="",1,IF($W$2="(blank)",--(W34=""),IF($W$2="(nonblank)",--(W34<>""),--ISNUMBER(SEARCH($W$2,W34))))) | BI34: =IF($X$2="",1,IF($X$2="(blank)",--(X34=""),IF($X$2="(nonblank)",--(X34<>""),--ISNUMBER(SEARCH($X$2,X34))))) | BJ34: =IF($Y$2="",1,IF($Y$2="(blank)",--(Y34=""),IF($Y$2="(nonblank)",--(Y34<>""),--ISNUMBER(SEARCH($Y$2,Y34))))) | BK34: =IF($Z$2="",1,IF($Z$2="(blank)",--(Z34=""),IF($Z$2="(nonblank)",--(Z34<>""),--ISNUMBER(SEARCH($Z$2,Z34))))) | BL34: =IF($AA$2="",1,IF($AA$2="(blank)",--(AA34=""),IF($AA$2="(nonblank)",--(AA34<>""),--ISNUMBER(SEARCH($AA$2,AA34))))) | BM34: =IF($AB$2="",1,IF($AB$2="(blank)",--(AB34=""),IF($AB$2="(nonblank)",--(AB34<>""),--ISNUMBER(SEARCH($AB$2,AB34))))) | BN34: =IF($AC$2="",1,IF($AC$2="(blank)",--(AC34=""),IF($AC$2="(nonblank)",--(AC34<>""),--ISNUMBER(SEARCH($AC$2,AC34))))) | BO34: =IF($AD$2="",1,IF($AD$2="(blank)",--(AD34=""),IF($AD$2="(nonblank)",--(AD34<>""),--ISNUMBER(SEARCH($AD$2,AD34))))) | BP34: =IF($AE$2="",1,IF($AE$2="(blank)",--(AE34=""),IF($AE$2="(nonblank)",--(AE34<>""),--ISNUMBER(SEARCH($AE$2,AE34))))) | BQ34: =IF($AF$2="",1,IF($AF$2="(blank)",--(AF34=""),IF($AF$2="(nonblank)",--(AF34<>""),--ISNUMBER(SEARCH($AF$2,AF34))))) | BR34: =IF($AG$2="",1,IF($AG$2="(blank)",--(AG34=""),IF($AG$2="(nonblank)",--(AG34<>""),--ISNUMBER(SEARCH($AG$2,AG34))))) | BS34: =IF($AH$2="",1,IF($AH$2="(blank)",--(AH34=""),IF($AH$2="(nonblank)",--(AH34<>""),--ISNUMBER(SEARCH($AH$2,AH34))))) | BT34: =IF(COUNTIF($AL34:$BS34,0)>0,0,1)
A35: 150 | B35: Scrap of empty oil drums | C35: 571 | D35: 21980 | E35: NO | F35: 2067 | G35: WATAN SCRAP TRADERS | H35: 85650 | I35: =ROUND(H35*18%,0) | J35: =+H35+I35 | K35: =ROUND((H35+I35)*2%,0) | L35: =H35*0.1% | M35: =H35*2.25%*118% | N35: =H35*2.25%*2% | O35: =M35-N35 | P35: =ROUND(O35+L35,0) | Q35: 0 | R35: =ROUND(H35*Q35,0) | S35: =ROUND(H35*117.65%-R35,0) | T35: =ROUND(H35*25%,0) | U35: 21413 | V35: 14.08.2026 | W35: =ROUND(H35*92.65%-R35,0) | X35: 79354 | Y35: 20.08.2026 | Z35: =IF(IF(OR(AB35="",AB35=0),TODAY(),DATE(VALUE(RIGHT(AB35,4)),VALUE(MID(AB35,4,2)),VALUE(LEFT(AB35,2))))<=DATE(2026,8,24),0,H35*0.0118*CEILING((IF(OR(AB35="",AB35=0),TODAY(),DATE(VALUE(RIGHT(AB35,4)),VALUE(MID(AB35,4,2)),VALUE(LEFT(AB35,2))))-DATE(2026,8,22))/7,1)) | AC35: =U35+X35+AA35 | AD35: =S35-AC35 | AE35: =IF(AD35="","",IF(AD35<=5,"SETTLED","OUTSTANDING")) | AF35: DR2640100027 | AG35: 1800003248 | AH35: 20.08.2026 | AL35: =IF($A$2="",1,IF($A$2="(blank)",--(A35=""),IF($A$2="(nonblank)",--(A35<>""),--ISNUMBER(SEARCH($A$2,A35))))) | AM35: =IF($B$2="",1,IF($B$2="(blank)",--(B35=""),IF($B$2="(nonblank)",--(B35<>""),--ISNUMBER(SEARCH($B$2,B35))))) | AN35: =IF($C$2="",1,IF($C$2="(blank)",--(C35=""),IF($C$2="(nonblank)",--(C35<>""),--ISNUMBER(SEARCH($C$2,C35))))) | AO35: =IF($D$2="",1,IF($D$2="(blank)",--(D35=""),IF($D$2="(nonblank)",--(D35<>""),--ISNUMBER(SEARCH($D$2,D35))))) | AP35: =IF($E$2="",1,IF($E$2="(blank)",--(E35=""),IF($E$2="(nonblank)",--(E35<>""),--ISNUMBER(SEARCH($E$2,E35))))) | AQ35: =IF($F$2="",1,IF($F$2="(blank)",--(F35=""),IF($F$2="(nonblank)",--(F35<>""),--ISNUMBER(SEARCH($F$2,F35))))) | AR35: =IF($G$2="",1,IF($G$2="(blank)",--(G35=""),IF($G$2="(nonblank)",--(G35<>""),--ISNUMBER(SEARCH($G$2,G35))))) | AS35: =IF($H$2="",1,IF($H$2="(blank)",--(H35=""),IF($H$2="(nonblank)",--(H35<>""),--ISNUMBER(SEARCH($H$2,H35))))) | AT35: =IF($I$2="",1,IF($I$2="(blank)",--(I35=""),IF($I$2="(nonblank)",--(I35<>""),--ISNUMBER(SEARCH($I$2,I35))))) | AU35: =IF($J$2="",1,IF($J$2="(blank)",--(J35=""),IF($J$2="(nonblank)",--(J35<>""),--ISNUMBER(SEARCH($J$2,J35))))) | AV35: =IF($K$2="",1,IF($K$2="(blank)",--(K35=""),IF($K$2="(nonblank)",--(K35<>""),--ISNUMBER(SEARCH($K$2,K35))))) | AW35: =IF($L$2="",1,IF($L$2="(blank)",--(L35=""),IF($L$2="(nonblank)",--(L35<>""),--ISNUMBER(SEARCH($L$2,L35))))) | AX35: =IF($M$2="",1,IF($M$2="(blank)",--(M35=""),IF($M$2="(nonblank)",--(M35<>""),--ISNUMBER(SEARCH($M$2,M35))))) | AY35: =IF($N$2="",1,IF($N$2="(blank)",--(N35=""),IF($N$2="(nonblank)",--(N35<>""),--ISNUMBER(SEARCH($N$2,N35))))) | AZ35: =IF($O$2="",1,IF($O$2="(blank)",--(O35=""),IF($O$2="(nonblank)",--(O35<>""),--ISNUMBER(SEARCH($O$2,O35))))) | BA35: =IF($P$2="",1,IF($P$2="(blank)",--(P35=""),IF($P$2="(nonblank)",--(P35<>""),--ISNUMBER(SEARCH($P$2,P35))))) | BB35: =IF($Q$2="",1,IF($Q$2="(blank)",--(Q35=""),IF($Q$2="(nonblank)",--(Q35<>""),--ISNUMBER(SEARCH($Q$2,Q35))))) | BC35: =IF($R$2="",1,IF($R$2="(blank)",--(R35=""),IF($R$2="(nonblank)",--(R35<>""),--ISNUMBER(SEARCH($R$2,R35))))) | BD35: =IF($S$2="",1,IF($S$2="(blank)",--(S35=""),IF($S$2="(nonblank)",--(S35<>""),--ISNUMBER(SEARCH($S$2,S35))))) | BE35: =IF($T$2="",1,IF($T$2="(blank)",--(T35=""),IF($T$2="(nonblank)",--(T35<>""),--ISNUMBER(SEARCH($T$2,T35))))) | BF35: =IF($U$2="",1,IF($U$2="(blank)",--(U35=""),IF($U$2="(nonblank)",--(U35<>""),--ISNUMBER(SEARCH($U$2,U35))))) | BG35: =IF($V$2="",1,IF($V$2="(blank)",--(V35=""),IF($V$2="(nonblank)",--(V35<>""),--ISNUMBER(SEARCH($V$2,V35))))) | BH35: =IF($W$2="",1,IF($W$2="(blank)",--(W35=""),IF($W$2="(nonblank)",--(W35<>""),--ISNUMBER(SEARCH($W$2,W35))))) | BI35: =IF($X$2="",1,IF($X$2="(blank)",--(X35=""),IF($X$2="(nonblank)",--(X35<>""),--ISNUMBER(SEARCH($X$2,X35))))) | BJ35: =IF($Y$2="",1,IF($Y$2="(blank)",--(Y35=""),IF($Y$2="(nonblank)",--(Y35<>""),--ISNUMBER(SEARCH($Y$2,Y35))))) | BK35: =IF($Z$2="",1,IF($Z$2="(blank)",--(Z35=""),IF($Z$2="(nonblank)",--(Z35<>""),--ISNUMBER(SEARCH($Z$2,Z35))))) | BL35: =IF($AA$2="",1,IF($AA$2="(blank)",--(AA35=""),IF($AA$2="(nonblank)",--(AA35<>""),--ISNUMBER(SEARCH($AA$2,AA35))))) | BM35: =IF($AB$2="",1,IF($AB$2="(blank)",--(AB35=""),IF($AB$2="(nonblank)",--(AB35<>""),--ISNUMBER(SEARCH($AB$2,AB35))))) | BN35: =IF($AC$2="",1,IF($AC$2="(blank)",--(AC35=""),IF($AC$2="(nonblank)",--(AC35<>""),--ISNUMBER(SEARCH($AC$2,AC35))))) | BO35: =IF($AD$2="",1,IF($AD$2="(blank)",--(AD35=""),IF($AD$2="(nonblank)",--(AD35<>""),--ISNUMBER(SEARCH($AD$2,AD35))))) | BP35: =IF($AE$2="",1,IF($AE$2="(blank)",--(AE35=""),IF($AE$2="(nonblank)",--(AE35<>""),--ISNUMBER(SEARCH($AE$2,AE35))))) | BQ35: =IF($AF$2="",1,IF($AF$2="(blank)",--(AF35=""),IF($AF$2="(nonblank)",--(AF35<>""),--ISNUMBER(SEARCH($AF$2,AF35))))) | BR35: =IF($AG$2="",1,IF($AG$2="(blank)",--(AG35=""),IF($AG$2="(nonblank)",--(AG35<>""),--ISNUMBER(SEARCH($AG$2,AG35))))) | BS35: =IF($AH$2="",1,IF($AH$2="(blank)",--(AH35=""),IF($AH$2="(nonblank)",--(AH35<>""),--ISNUMBER(SEARCH($AH$2,AH35))))) | BT35: =IF(COUNTIF($AL35:$BS35,0)>0,0,1)
A36: 1 | B36: Scrap of 33 KV CB | C36: 54000 | D36: 21980 | E36: NO | F36: 2069 | G36: STERLING ENTERPRISES | H36: 54000 | I36: =ROUND(H36*18%,0) | J36: =+H36+I36 | K36: =ROUND((H36+I36)*2%,0) | L36: =H36*0.1% | M36: =H36*2.25%*118% | N36: =H36*2.25%*2% | O36: =M36-N36 | P36: =ROUND(O36+L36,0) | Q36: 0 | R36: =ROUND(H36*Q36,0) | S36: =ROUND(H36*117.65%-R36,0) | T36: =ROUND(H36*25%,0) | U36: 13500 | V36: 11.08.2026 | W36: =ROUND(H36*92.65%-R36,0) | Y36: 0 | Z36: =IF(IF(OR(AB36="",AB36=0),TODAY(),DATE(VALUE(RIGHT(AB36,4)),VALUE(MID(AB36,4,2)),VALUE(LEFT(AB36,2))))<=DATE(2026,8,24),0,H36*0.0118*CEILING((IF(OR(AB36="",AB36=0),TODAY(),DATE(VALUE(RIGHT(AB36,4)),VALUE(MID(AB36,4,2)),VALUE(LEFT(AB36,2))))-DATE(2026,8,22))/7,1)) | AC36: =U36+X36+AA36 | AD36: =S36-AC36 | AE36: =IF(AD36="","",IF(AD36<=5,"SETTLED","OUTSTANDING")) | AL36: =IF($A$2="",1,IF($A$2="(blank)",--(A36=""),IF($A$2="(nonblank)",--(A36<>""),--ISNUMBER(SEARCH($A$2,A36))))) | AM36: =IF($B$2="",1,IF($B$2="(blank)",--(B36=""),IF($B$2="(nonblank)",--(B36<>""),--ISNUMBER(SEARCH($B$2,B36))))) | AN36: =IF($C$2="",1,IF($C$2="(blank)",--(C36=""),IF($C$2="(nonblank)",--(C36<>""),--ISNUMBER(SEARCH($C$2,C36))))) | AO36: =IF($D$2="",1,IF($D$2="(blank)",--(D36=""),IF($D$2="(nonblank)",--(D36<>""),--ISNUMBER(SEARCH($D$2,D36))))) | AP36: =IF($E$2="",1,IF($E$2="(blank)",--(E36=""),IF($E$2="(nonblank)",--(E36<>""),--ISNUMBER(SEARCH($E$2,E36))))) | AQ36: =IF($F$2="",1,IF($F$2="(blank)",--(F36=""),IF($F$2="(nonblank)",--(F36<>""),--ISNUMBER(SEARCH($F$2,F36))))) | AR36: =IF($G$2="",1,IF($G$2="(blank)",--(G36=""),IF($G$2="(nonblank)",--(G36<>""),--ISNUMBER(SEARCH($G$2,G36))))) | AS36: =IF($H$2="",1,IF($H$2="(blank)",--(H36=""),IF($H$2="(nonblank)",--(H36<>""),--ISNUMBER(SEARCH($H$2,H36))))) | AT36: =IF($I$2="",1,IF($I$2="(blank)",--(I36=""),IF($I$2="(nonblank)",--(I36<>""),--ISNUMBER(SEARCH($I$2,I36))))) | AU36: =IF($J$2="",1,IF($J$2="(blank)",--(J36=""),IF($J$2="(nonblank)",--(J36<>""),--ISNUMBER(SEARCH($J$2,J36))))) | AV36: =IF($K$2="",1,IF($K$2="(blank)",--(K36=""),IF($K$2="(nonblank)",--(K36<>""),--ISNUMBER(SEARCH($K$2,K36))))) | AW36: =IF($L$2="",1,IF($L$2="(blank)",--(L36=""),IF($L$2="(nonblank)",--(L36<>""),--ISNUMBER(SEARCH($L$2,L36))))) | AX36: =IF($M$2="",1,IF($M$2="(blank)",--(M36=""),IF($M$2="(nonblank)",--(M36<>""),--ISNUMBER(SEARCH($M$2,M36))))) | AY36: =IF($N$2="",1,IF($N$2="(blank)",--(N36=""),IF($N$2="(nonblank)",--(N36<>""),--ISNUMBER(SEARCH($N$2,N36))))) | AZ36: =IF($O$2="",1,IF($O$2="(blank)",--(O36=""),IF($O$2="(nonblank)",--(O36<>""),--ISNUMBER(SEARCH($O$2,O36))))) | BA36: =IF($P$2="",1,IF($P$2="(blank)",--(P36=""),IF($P$2="(nonblank)",--(P36<>""),--ISNUMBER(SEARCH($P$2,P36))))) | BB36: =IF($Q$2="",1,IF($Q$2="(blank)",--(Q36=""),IF($Q$2="(nonblank)",--(Q36<>""),--ISNUMBER(SEARCH($Q$2,Q36))))) | BC36: =IF($R$2="",1,IF($R$2="(blank)",--(R36=""),IF($R$2="(nonblank)",--(R36<>""),--ISNUMBER(SEARCH($R$2,R36))))) | BD36: =IF($S$2="",1,IF($S$2="(blank)",--(S36=""),IF($S$2="(nonblank)",--(S36<>""),--ISNUMBER(SEARCH($S$2,S36))))) | BE36: =IF($T$2="",1,IF($T$2="(blank)",--(T36=""),IF($T$2="(nonblank)",--(T36<>""),--ISNUMBER(SEARCH($T$2,T36))))) | BF36: =IF($U$2="",1,IF($U$2="(blank)",--(U36=""),IF($U$2="(nonblank)",--(U36<>""),--ISNUMBER(SEARCH($U$2,U36))))) | BG36: =IF($V$2="",1,IF($V$2="(blank)",--(V36=""),IF($V$2="(nonblank)",--(V36<>""),--ISNUMBER(SEARCH($V$2,V36))))) | BH36: =IF($W$2="",1,IF($W$2="(blank)",--(W36=""),IF($W$2="(nonblank)",--(W36<>""),--ISNUMBER(SEARCH($W$2,W36))))) | BI36: =IF($X$2="",1,IF($X$2="(blank)",--(X36=""),IF($X$2="(nonblank)",--(X36<>""),--ISNUMBER(SEARCH($X$2,X36))))) | BJ36: =IF($Y$2="",1,IF($Y$2="(blank)",--(Y36=""),IF($Y$2="(nonblank)",--(Y36<>""),--ISNUMBER(SEARCH($Y$2,Y36))))) | BK36: =IF($Z$2="",1,IF($Z$2="(blank)",--(Z36=""),IF($Z$2="(nonblank)",--(Z36<>""),--ISNUMBER(SEARCH($Z$2,Z36))))) | BL36: =IF($AA$2="",1,IF($AA$2="(blank)",--(AA36=""),IF($AA$2="(nonblank)",--(AA36<>""),--ISNUMBER(SEARCH($AA$2,AA36))))) | BM36: =IF($AB$2="",1,IF($AB$2="(blank)",--(AB36=""),IF($AB$2="(nonblank)",--(AB36<>""),--ISNUMBER(SEARCH($AB$2,AB36))))) | BN36: =IF($AC$2="",1,IF($AC$2="(blank)",--(AC36=""),IF($AC$2="(nonblank)",--(AC36<>""),--ISNUMBER(SEARCH($AC$2,AC36))))) | BO36: =IF($AD$2="",1,IF($AD$2="(blank)",--(AD36=""),IF($AD$2="(nonblank)",--(AD36<>""),--ISNUMBER(SEARCH($AD$2,AD36))))) | BP36: =IF($AE$2="",1,IF($AE$2="(blank)",--(AE36=""),IF($AE$2="(nonblank)",--(AE36<>""),--ISNUMBER(SEARCH($AE$2,AE36))))) | BQ36: =IF($AF$2="",1,IF($AF$2="(blank)",--(AF36=""),IF($AF$2="(nonblank)",--(AF36<>""),--ISNUMBER(SEARCH($AF$2,AF36))))) | BR36: =IF($AG$2="",1,IF($AG$2="(blank)",--(AG36=""),IF($AG$2="(nonblank)",--(AG36<>""),--ISNUMBER(SEARCH($AG$2,AG36))))) | BS36: =IF($AH$2="",1,IF($AH$2="(blank)",--(AH36=""),IF($AH$2="(nonblank)",--(AH36<>""),--ISNUMBER(SEARCH($AH$2,AH36))))) | BT36: =IF(COUNTIF($AL36:$BS36,0)>0,0,1)
A37: 3 | B37: Scrap of 66 KV Isolater | C37: 25001 | D37: 21980 | E37: NO | F37: 2071 | G37: NATIONAL ENTERPRISES | H37: 75003 | I37: =ROUND(H37*18%,0) | J37: =+H37+I37 | K37: =ROUND((H37+I37)*2%,0) | L37: =H37*0.1% | M37: =H37*2.25%*118% | N37: =H37*2.25%*2% | O37: =M37-N37 | P37: =ROUND(O37+L37,0) | Q37: 0 | R37: =ROUND(H37*Q37,0) | S37: =ROUND(H37*117.65%-R37,0) | T37: =ROUND(H37*25%,0) | U37: =+T37 | V37: 13.08.2026 | W37: =ROUND(H37*92.65%-R37,0) | X37: 69491 | Y37: 24.08.2026 | Z37: =IF(IF(OR(AB37="",AB37=0),TODAY(),DATE(VALUE(RIGHT(AB37,4)),VALUE(MID(AB37,4,2)),VALUE(LEFT(AB37,2))))<=DATE(2026,8,24),0,H37*0.0118*CEILING((IF(OR(AB37="",AB37=0),TODAY(),DATE(VALUE(RIGHT(AB37,4)),VALUE(MID(AB37,4,2)),VALUE(LEFT(AB37,2))))-DATE(2026,8,22))/7,1)) | AC37: =U37+X37+AA37 | AD37: =S37-AC37 | AE37: =IF(AD37="","",IF(AD37<=5,"SETTLED","OUTSTANDING")) | AF37: DR2640100040 | AG37: 1800003314 | AH37: 27.08.2026 | AL37: =IF($A$2="",1,IF($A$2="(blank)",--(A37=""),IF($A$2="(nonblank)",--(A37<>""),--ISNUMBER(SEARCH($A$2,A37))))) | AM37: =IF($B$2="",1,IF($B$2="(blank)",--(B37=""),IF($B$2="(nonblank)",--(B37<>""),--ISNUMBER(SEARCH($B$2,B37))))) | AN37: =IF($C$2="",1,IF($C$2="(blank)",--(C37=""),IF($C$2="(nonblank)",--(C37<>""),--ISNUMBER(SEARCH($C$2,C37))))) | AO37: =IF($D$2="",1,IF($D$2="(blank)",--(D37=""),IF($D$2="(nonblank)",--(D37<>""),--ISNUMBER(SEARCH($D$2,D37))))) | AP37: =IF($E$2="",1,IF($E$2="(blank)",--(E37=""),IF($E$2="(nonblank)",--(E37<>""),--ISNUMBER(SEARCH($E$2,E37))))) | AQ37: =IF($F$2="",1,IF($F$2="(blank)",--(F37=""),IF($F$2="(nonblank)",--(F37<>""),--ISNUMBER(SEARCH($F$2,F37))))) | AR37: =IF($G$2="",1,IF($G$2="(blank)",--(G37=""),IF($G$2="(nonblank)",--(G37<>""),--ISNUMBER(SEARCH($G$2,G37))))) | AS37: =IF($H$2="",1,IF($H$2="(blank)",--(H37=""),IF($H$2="(nonblank)",--(H37<>""),--ISNUMBER(SEARCH($H$2,H37))))) | AT37: =IF($I$2="",1,IF($I$2="(blank)",--(I37=""),IF($I$2="(nonblank)",--(I37<>""),--ISNUMBER(SEARCH($I$2,I37))))) | AU37: =IF($J$2="",1,IF($J$2="(blank)",--(J37=""),IF($J$2="(nonblank)",--(J37<>""),--ISNUMBER(SEARCH($J$2,J37))))) | AV37: =IF($K$2="",1,IF($K$2="(blank)",--(K37=""),IF($K$2="(nonblank)",--(K37<>""),--ISNUMBER(SEARCH($K$2,K37))))) | AW37: =IF($L$2="",1,IF($L$2="(blank)",--(L37=""),IF($L$2="(nonblank)",--(L37<>""),--ISNUMBER(SEARCH($L$2,L37))))) | AX37: =IF($M$2="",1,IF($M$2="(blank)",--(M37=""),IF($M$2="(nonblank)",--(M37<>""),--ISNUMBER(SEARCH($M$2,M37))))) | AY37: =IF($N$2="",1,IF($N$2="(blank)",--(N37=""),IF($N$2="(nonblank)",--(N37<>""),--ISNUMBER(SEARCH($N$2,N37))))) | AZ37: =IF($O$2="",1,IF($O$2="(blank)",--(O37=""),IF($O$2="(nonblank)",--(O37<>""),--ISNUMBER(SEARCH($O$2,O37))))) | BA37: =IF($P$2="",1,IF($P$2="(blank)",--(P37=""),IF($P$2="(nonblank)",--(P37<>""),--ISNUMBER(SEARCH($P$2,P37))))) | BB37: =IF($Q$2="",1,IF($Q$2="(blank)",--(Q37=""),IF($Q$2="(nonblank)",--(Q37<>""),--ISNUMBER(SEARCH($Q$2,Q37))))) | BC37: =IF($R$2="",1,IF($R$2="(blank)",--(R37=""),IF($R$2="(nonblank)",--(R37<>""),--ISNUMBER(SEARCH($R$2,R37))))) | BD37: =IF($S$2="",1,IF($S$2="(blank)",--(S37=""),IF($S$2="(nonblank)",--(S37<>""),--ISNUMBER(SEARCH($S$2,S37))))) | BE37: =IF($T$2="",1,IF($T$2="(blank)",--(T37=""),IF($T$2="(nonblank)",--(T37<>""),--ISNUMBER(SEARCH($T$2,T37))))) | BF37: =IF($U$2="",1,IF($U$2="(blank)",--(U37=""),IF($U$2="(nonblank)",--(U37<>""),--ISNUMBER(SEARCH($U$2,U37))))) | BG37: =IF($V$2="",1,IF($V$2="(blank)",--(V37=""),IF($V$2="(nonblank)",--(V37<>""),--ISNUMBER(SEARCH($V$2,V37))))) | BH37: =IF($W$2="",1,IF($W$2="(blank)",--(W37=""),IF($W$2="(nonblank)",--(W37<>""),--ISNUMBER(SEARCH($W$2,W37))))) | BI37: =IF($X$2="",1,IF($X$2="(blank)",--(X37=""),IF($X$2="(nonblank)",--(X37<>""),--ISNUMBER(SEARCH($X$2,X37))))) | BJ37: =IF($Y$2="",1,IF($Y$2="(blank)",--(Y37=""),IF($Y$2="(nonblank)",--(Y37<>""),--ISNUMBER(SEARCH($Y$2,Y37))))) | BK37: =IF($Z$2="",1,IF($Z$2="(blank)",--(Z37=""),IF($Z$2="(nonblank)",--(Z37<>""),--ISNUMBER(SEARCH($Z$2,Z37))))) | BL37: =IF($AA$2="",1,IF($AA$2="(blank)",--(AA37=""),IF($AA$2="(nonblank)",--(AA37<>""),--ISNUMBER(SEARCH($AA$2,AA37))))) | BM37: =IF($AB$2="",1,IF($AB$2="(blank)",--(AB37=""),IF($AB$2="(nonblank)",--(AB37<>""),--ISNUMBER(SEARCH($AB$2,AB37))))) | BN37: =IF($AC$2="",1,IF($AC$2="(blank)",--(AC37=""),IF($AC$2="(nonblank)",--(AC37<>""),--ISNUMBER(SEARCH($AC$2,AC37))))) | BO37: =IF($AD$2="",1,IF($AD$2="(blank)",--(AD37=""),IF($AD$2="(nonblank)",--(AD37<>""),--ISNUMBER(SEARCH($AD$2,AD37))))) | BP37: =IF($AE$2="",1,IF($AE$2="(blank)",--(AE37=""),IF($AE$2="(nonblank)",--(AE37<>""),--ISNUMBER(SEARCH($AE$2,AE37))))) | BQ37: =IF($AF$2="",1,IF($AF$2="(blank)",--(AF37=""),IF($AF$2="(nonblank)",--(AF37<>""),--ISNUMBER(SEARCH($AF$2,AF37))))) | BR37: =IF($AG$2="",1,IF($AG$2="(blank)",--(AG37=""),IF($AG$2="(nonblank)",--(AG37<>""),--ISNUMBER(SEARCH($AG$2,AG37))))) | BS37: =IF($AH$2="",1,IF($AH$2="(blank)",--(AH37=""),IF($AH$2="(nonblank)",--(AH37<>""),--ISNUMBER(SEARCH($AH$2,AH37))))) | BT37: =IF(COUNTIF($AL37:$BS37,0)>0,0,1)
A38: 3 | B38: Scrap of 132 KV CT | C38: 70001 | D38: 21980 | E38: NO | F38: 2086 | G38: KASHYAP TRADING CO | H38: 210003 | I38: =ROUND(H38*18%,0) | J38: =+H38+I38 | K38: =ROUND((H38+I38)*2%,0) | L38: =H38*0.1% | M38: =H38*2.25%*118% | N38: =H38*2.25%*2% | O38: =M38-N38 | P38: =ROUND(O38+L38,0) | Q38: 0 | R38: =ROUND(H38*Q38,0) | S38: =ROUND(H38*117.65%-R38,0) | T38: =ROUND(H38*25%,0) | U38: 52501 | V38: 17.08.2026 | W38: =ROUND(H38*92.65%-R38,0) | X38: 194568 | Y38: 17.08.2026 | Z38: =IF(IF(OR(AB38="",AB38=0),TODAY(),DATE(VALUE(RIGHT(AB38,4)),VALUE(MID(AB38,4,2)),VALUE(LEFT(AB38,2))))<=DATE(2026,8,24),0,H38*0.0118*CEILING((IF(OR(AB38="",AB38=0),TODAY(),DATE(VALUE(RIGHT(AB38,4)),VALUE(MID(AB38,4,2)),VALUE(LEFT(AB38,2))))-DATE(2026,8,22))/7,1)) | AC38: =U38+X38+AA38 | AD38: =S38-AC38 | AE38: =IF(AD38="","",IF(AD38<=5,"SETTLED","OUTSTANDING")) | AF38: DR2640100025 | AG38: 1800003226 | AH38: 19.08.2026 | AL38: =IF($A$2="",1,IF($A$2="(blank)",--(A38=""),IF($A$2="(nonblank)",--(A38<>""),--ISNUMBER(SEARCH($A$2,A38))))) | AM38: =IF($B$2="",1,IF($B$2="(blank)",--(B38=""),IF($B$2="(nonblank)",--(B38<>""),--ISNUMBER(SEARCH($B$2,B38))))) | AN38: =IF($C$2="",1,IF($C$2="(blank)",--(C38=""),IF($C$2="(nonblank)",--(C38<>""),--ISNUMBER(SEARCH($C$2,C38))))) | AO38: =IF($D$2="",1,IF($D$2="(blank)",--(D38=""),IF($D$2="(nonblank)",--(D38<>""),--ISNUMBER(SEARCH($D$2,D38))))) | AP38: =IF($E$2="",1,IF($E$2="(blank)",--(E38=""),IF($E$2="(nonblank)",--(E38<>""),--ISNUMBER(SEARCH($E$2,E38))))) | AQ38: =IF($F$2="",1,IF($F$2="(blank)",--(F38=""),IF($F$2="(nonblank)",--(F38<>""),--ISNUMBER(SEARCH($F$2,F38))))) | AR38: =IF($G$2="",1,IF($G$2="(blank)",--(G38=""),IF($G$2="(nonblank)",--(G38<>""),--ISNUMBER(SEARCH($G$2,G38))))) | AS38: =IF($H$2="",1,IF($H$2="(blank)",--(H38=""),IF($H$2="(nonblank)",--(H38<>""),--ISNUMBER(SEARCH($H$2,H38))))) | AT38: =IF($I$2="",1,IF($I$2="(blank)",--(I38=""),IF($I$2="(nonblank)",--(I38<>""),--ISNUMBER(SEARCH($I$2,I38))))) | AU38: =IF($J$2="",1,IF($J$2="(blank)",--(J38=""),IF($J$2="(nonblank)",--(J38<>""),--ISNUMBER(SEARCH($J$2,J38))))) | AV38: =IF($K$2="",1,IF($K$2="(blank)",--(K38=""),IF($K$2="(nonblank)",--(K38<>""),--ISNUMBER(SEARCH($K$2,K38))))) | AW38: =IF($L$2="",1,IF($L$2="(blank)",--(L38=""),IF($L$2="(nonblank)",--(L38<>""),--ISNUMBER(SEARCH($L$2,L38))))) | AX38: =IF($M$2="",1,IF($M$2="(blank)",--(M38=""),IF($M$2="(nonblank)",--(M38<>""),--ISNUMBER(SEARCH($M$2,M38))))) | AY38: =IF($N$2="",1,IF($N$2="(blank)",--(N38=""),IF($N$2="(nonblank)",--(N38<>""),--ISNUMBER(SEARCH($N$2,N38))))) | AZ38: =IF($O$2="",1,IF($O$2="(blank)",--(O38=""),IF($O$2="(nonblank)",--(O38<>""),--ISNUMBER(SEARCH($O$2,O38))))) | BA38: =IF($P$2="",1,IF($P$2="(blank)",--(P38=""),IF($P$2="(nonblank)",--(P38<>""),--ISNUMBER(SEARCH($P$2,P38))))) | BB38: =IF($Q$2="",1,IF($Q$2="(blank)",--(Q38=""),IF($Q$2="(nonblank)",--(Q38<>""),--ISNUMBER(SEARCH($Q$2,Q38))))) | BC38: =IF($R$2="",1,IF($R$2="(blank)",--(R38=""),IF($R$2="(nonblank)",--(R38<>""),--ISNUMBER(SEARCH($R$2,R38))))) | BD38: =IF($S$2="",1,IF($S$2="(blank)",--(S38=""),IF($S$2="(nonblank)",--(S38<>""),--ISNUMBER(SEARCH($S$2,S38))))) | BE38: =IF($T$2="",1,IF($T$2="(blank)",--(T38=""),IF($T$2="(nonblank)",--(T38<>""),--ISNUMBER(SEARCH($T$2,T38))))) | BF38: =IF($U$2="",1,IF($U$2="(blank)",--(U38=""),IF($U$2="(nonblank)",--(U38<>""),--ISNUMBER(SEARCH($U$2,U38))))) | BG38: =IF($V$2="",1,IF($V$2="(blank)",--(V38=""),IF($V$2="(nonblank)",--(V38<>""),--ISNUMBER(SEARCH($V$2,V38))))) | BH38: =IF($W$2="",1,IF($W$2="(blank)",--(W38=""),IF($W$2="(nonblank)",--(W38<>""),--ISNUMBER(SEARCH($W$2,W38))))) | BI38: =IF($X$2="",1,IF($X$2="(blank)",--(X38=""),IF($X$2="(nonblank)",--(X38<>""),--ISNUMBER(SEARCH($X$2,X38))))) | BJ38: =IF($Y$2="",1,IF($Y$2="(blank)",--(Y38=""),IF($Y$2="(nonblank)",--(Y38<>""),--ISNUMBER(SEARCH($Y$2,Y38))))) | BK38: =IF($Z$2="",1,IF($Z$2="(blank)",--(Z38=""),IF($Z$2="(nonblank)",--(Z38<>""),--ISNUMBER(SEARCH($Z$2,Z38))))) | BL38: =IF($AA$2="",1,IF($AA$2="(blank)",--(AA38=""),IF($AA$2="(nonblank)",--(AA38<>""),--ISNUMBER(SEARCH($AA$2,AA38))))) | BM38: =IF($AB$2="",1,IF($AB$2="(blank)",--(AB38=""),IF($AB$2="(nonblank)",--(AB38<>""),--ISNUMBER(SEARCH($AB$2,AB38))))) | BN38: =IF($AC$2="",1,IF($AC$2="(blank)",--(AC38=""),IF($AC$2="(nonblank)",--(AC38<>""),--ISNUMBER(SEARCH($AC$2,AC38))))) | BO38: =IF($AD$2="",1,IF($AD$2="(blank)",--(AD38=""),IF($AD$2="(nonblank)",--(AD38<>""),--ISNUMBER(SEARCH($AD$2,AD38))))) | BP38: =IF($AE$2="",1,IF($AE$2="(blank)",--(AE38=""),IF($AE$2="(nonblank)",--(AE38<>""),--ISNUMBER(SEARCH($AE$2,AE38))))) | BQ38: =IF($AF$2="",1,IF($AF$2="(blank)",--(AF38=""),IF($AF$2="(nonblank)",--(AF38<>""),--ISNUMBER(SEARCH($AF$2,AF38))))) | BR38: =IF($AG$2="",1,IF($AG$2="(blank)",--(AG38=""),IF($AG$2="(nonblank)",--(AG38<>""),--ISNUMBER(SEARCH($AG$2,AG38))))) | BS38: =IF($AH$2="",1,IF($AH$2="(blank)",--(AH38=""),IF($AH$2="(nonblank)",--(AH38<>""),--ISNUMBER(SEARCH($AH$2,AH38))))) | BT38: =IF(COUNTIF($AL38:$BS38,0)>0,0,1)
A39: 2 | B39: Scrap of 66 kv TBC C & R Panel | C39: 15006 | D39: 21980 | E39: NO | F39: 2089 | G39: S M ENTERPRISES | H39: 30012 | I39: =ROUND(H39*18%,0) | J39: =+H39+I39 | K39: =ROUND((H39+I39)*2%,0) | L39: =H39*0.1% | M39: =H39*2.25%*118% | N39: =H39*2.25%*2% | O39: =M39-N39 | P39: =ROUND(O39+L39,0) | Q39: 0 | R39: =ROUND(H39*Q39,0) | S39: =ROUND(H39*117.65%-R39,0) | T39: =ROUND(H39*25%,0) | U39: 7503 | V39: 14.08.2026 | W39: =ROUND(H39*92.65%-R39,0) | X39: 27806 | Y39: 01.09.2026 | Z39: =IF(IF(OR(AB39="",AB39=0),TODAY(),DATE(VALUE(RIGHT(AB39,4)),VALUE(MID(AB39,4,2)),VALUE(LEFT(AB39,2))))<=DATE(2026,8,24),0,H39*0.0118*CEILING((IF(OR(AB39="",AB39=0),TODAY(),DATE(VALUE(RIGHT(AB39,4)),VALUE(MID(AB39,4,2)),VALUE(LEFT(AB39,2))))-DATE(2026,8,22))/7,1)) | AA39: 708 | AB39: 01.09.2026 | AC39: =U39+X39+AA39 | AD39: =S39-AC39 | AE39: =IF(AD39="","",IF(AD39<=5,"SETTLED","OUTSTANDING")) | AL39: =IF($A$2="",1,IF($A$2="(blank)",--(A39=""),IF($A$2="(nonblank)",--(A39<>""),--ISNUMBER(SEARCH($A$2,A39))))) | AM39: =IF($B$2="",1,IF($B$2="(blank)",--(B39=""),IF($B$2="(nonblank)",--(B39<>""),--ISNUMBER(SEARCH($B$2,B39))))) | AN39: =IF($C$2="",1,IF($C$2="(blank)",--(C39=""),IF($C$2="(nonblank)",--(C39<>""),--ISNUMBER(SEARCH($C$2,C39))))) | AO39: =IF($D$2="",1,IF($D$2="(blank)",--(D39=""),IF($D$2="(nonblank)",--(D39<>""),--ISNUMBER(SEARCH($D$2,D39))))) | AP39: =IF($E$2="",1,IF($E$2="(blank)",--(E39=""),IF($E$2="(nonblank)",--(E39<>""),--ISNUMBER(SEARCH($E$2,E39))))) | AQ39: =IF($F$2="",1,IF($F$2="(blank)",--(F39=""),IF($F$2="(nonblank)",--(F39<>""),--ISNUMBER(SEARCH($F$2,F39))))) | AR39: =IF($G$2="",1,IF($G$2="(blank)",--(G39=""),IF($G$2="(nonblank)",--(G39<>""),--ISNUMBER(SEARCH($G$2,G39))))) | AS39: =IF($H$2="",1,IF($H$2="(blank)",--(H39=""),IF($H$2="(nonblank)",--(H39<>""),--ISNUMBER(SEARCH($H$2,H39))))) | AT39: =IF($I$2="",1,IF($I$2="(blank)",--(I39=""),IF($I$2="(nonblank)",--(I39<>""),--ISNUMBER(SEARCH($I$2,I39))))) | AU39: =IF($J$2="",1,IF($J$2="(blank)",--(J39=""),IF($J$2="(nonblank)",--(J39<>""),--ISNUMBER(SEARCH($J$2,J39))))) | AV39: =IF($K$2="",1,IF($K$2="(blank)",--(K39=""),IF($K$2="(nonblank)",--(K39<>""),--ISNUMBER(SEARCH($K$2,K39))))) | AW39: =IF($L$2="",1,IF($L$2="(blank)",--(L39=""),IF($L$2="(nonblank)",--(L39<>""),--ISNUMBER(SEARCH($L$2,L39))))) | AX39: =IF($M$2="",1,IF($M$2="(blank)",--(M39=""),IF($M$2="(nonblank)",--(M39<>""),--ISNUMBER(SEARCH($M$2,M39))))) | AY39: =IF($N$2="",1,IF($N$2="(blank)",--(N39=""),IF($N$2="(nonblank)",--(N39<>""),--ISNUMBER(SEARCH($N$2,N39))))) | AZ39: =IF($O$2="",1,IF($O$2="(blank)",--(O39=""),IF($O$2="(nonblank)",--(O39<>""),--ISNUMBER(SEARCH($O$2,O39))))) | BA39: =IF($P$2="",1,IF($P$2="(blank)",--(P39=""),IF($P$2="(nonblank)",--(P39<>""),--ISNUMBER(SEARCH($P$2,P39))))) | BB39: =IF($Q$2="",1,IF($Q$2="(blank)",--(Q39=""),IF($Q$2="(nonblank)",--(Q39<>""),--ISNUMBER(SEARCH($Q$2,Q39))))) | BC39: =IF($R$2="",1,IF($R$2="(blank)",--(R39=""),IF($R$2="(nonblank)",--(R39<>""),--ISNUMBER(SEARCH($R$2,R39))))) | BD39: =IF($S$2="",1,IF($S$2="(blank)",--(S39=""),IF($S$2="(nonblank)",--(S39<>""),--ISNUMBER(SEARCH($S$2,S39))))) | BE39: =IF($T$2="",1,IF($T$2="(blank)",--(T39=""),IF($T$2="(nonblank)",--(T39<>""),--ISNUMBER(SEARCH($T$2,T39))))) | BF39: =IF($U$2="",1,IF($U$2="(blank)",--(U39=""),IF($U$2="(nonblank)",--(U39<>""),--ISNUMBER(SEARCH($U$2,U39))))) | BG39: =IF($V$2="",1,IF($V$2="(blank)",--(V39=""),IF($V$2="(nonblank)",--(V39<>""),--ISNUMBER(SEARCH($V$2,V39))))) | BH39: =IF($W$2="",1,IF($W$2="(blank)",--(W39=""),IF($W$2="(nonblank)",--(W39<>""),--ISNUMBER(SEARCH($W$2,W39))))) | BI39: =IF($X$2="",1,IF($X$2="(blank)",--(X39=""),IF($X$2="(nonblank)",--(X39<>""),--ISNUMBER(SEARCH($X$2,X39))))) | BJ39: =IF($Y$2="",1,IF($Y$2="(blank)",--(Y39=""),IF($Y$2="(nonblank)",--(Y39<>""),--ISNUMBER(SEARCH($Y$2,Y39))))) | BK39: =IF($Z$2="",1,IF($Z$2="(blank)",--(Z39=""),IF($Z$2="(nonblank)",--(Z39<>""),--ISNUMBER(SEARCH($Z$2,Z39))))) | BL39: =IF($AA$2="",1,IF($AA$2="(blank)",--(AA39=""),IF($AA$2="(nonblank)",--(AA39<>""),--ISNUMBER(SEARCH($AA$2,AA39))))) | BM39: =IF($AB$2="",1,IF($AB$2="(blank)",--(AB39=""),IF($AB$2="(nonblank)",--(AB39<>""),--ISNUMBER(SEARCH($AB$2,AB39))))) | BN39: =IF($AC$2="",1,IF($AC$2="(blank)",--(AC39=""),IF($AC$2="(nonblank)",--(AC39<>""),--ISNUMBER(SEARCH($AC$2,AC39))))) | BO39: =IF($AD$2="",1,IF($AD$2="(blank)",--(AD39=""),IF($AD$2="(nonblank)",--(AD39<>""),--ISNUMBER(SEARCH($AD$2,AD39))))) | BP39: =IF($AE$2="",1,IF($AE$2="(blank)",--(AE39=""),IF($AE$2="(nonblank)",--(AE39<>""),--ISNUMBER(SEARCH($AE$2,AE39))))) | BQ39: =IF($AF$2="",1,IF($AF$2="(blank)",--(AF39=""),IF($AF$2="(nonblank)",--(AF39<>""),--ISNUMBER(SEARCH($AF$2,AF39))))) | BR39: =IF($AG$2="",1,IF($AG$2="(blank)",--(AG39=""),IF($AG$2="(nonblank)",--(AG39<>""),--ISNUMBER(SEARCH($AG$2,AG39))))) | BS39: =IF($AH$2="",1,IF($AH$2="(blank)",--(AH39=""),IF($AH$2="(nonblank)",--(AH39<>""),--ISNUMBER(SEARCH($AH$2,AH39))))) | BT39: =IF(COUNTIF($AL39:$BS39,0)>0,0,1)
A40: 3 | B40: Scrap of 132 KV CT | C40: 40003 | D40: 21980 | E40: NO | F40: 2091 | G40: S M ENTERPRISES | H40: 120009 | I40: =ROUND(H40*18%,0) | J40: =+H40+I40 | K40: =ROUND((H40+I40)*2%,0) | L40: =H40*0.1% | M40: =H40*2.25%*118% | N40: =H40*2.25%*2% | O40: =M40-N40 | P40: =ROUND(O40+L40,0) | Q40: 0 | R40: =ROUND(H40*Q40,0) | S40: =ROUND(H40*117.65%-R40,0) | T40: =ROUND(H40*25%,0) | U40: 30002 | V40: 14.08.2026 | W40: =ROUND(H40*92.65%-R40,0) | X40: 111189 | Y40: 01.09.2026 | Z40: =IF(IF(OR(AB40="",AB40=0),TODAY(),DATE(VALUE(RIGHT(AB40,4)),VALUE(MID(AB40,4,2)),VALUE(LEFT(AB40,2))))<=DATE(2026,8,24),0,H40*0.0118*CEILING((IF(OR(AB40="",AB40=0),TODAY(),DATE(VALUE(RIGHT(AB40,4)),VALUE(MID(AB40,4,2)),VALUE(LEFT(AB40,2))))-DATE(2026,8,22))/7,1)) | AA40: 2832 | AB40: 01.09.2026 | AC40: =U40+X40+AA40 | AD40: =S40-AC40 | AE40: =IF(AD40="","",IF(AD40<=5,"SETTLED","OUTSTANDING")) | AL40: =IF($A$2="",1,IF($A$2="(blank)",--(A40=""),IF($A$2="(nonblank)",--(A40<>""),--ISNUMBER(SEARCH($A$2,A40))))) | AM40: =IF($B$2="",1,IF($B$2="(blank)",--(B40=""),IF($B$2="(nonblank)",--(B40<>""),--ISNUMBER(SEARCH($B$2,B40))))) | AN40: =IF($C$2="",1,IF($C$2="(blank)",--(C40=""),IF($C$2="(nonblank)",--(C40<>""),--ISNUMBER(SEARCH($C$2,C40))))) | AO40: =IF($D$2="",1,IF($D$2="(blank)",--(D40=""),IF($D$2="(nonblank)",--(D40<>""),--ISNUMBER(SEARCH($D$2,D40))))) | AP40: =IF($E$2="",1,IF($E$2="(blank)",--(E40=""),IF($E$2="(nonblank)",--(E40<>""),--ISNUMBER(SEARCH($E$2,E40))))) | AQ40: =IF($F$2="",1,IF($F$2="(blank)",--(F40=""),IF($F$2="(nonblank)",--(F40<>""),--ISNUMBER(SEARCH($F$2,F40))))) | AR40: =IF($G$2="",1,IF($G$2="(blank)",--(G40=""),IF($G$2="(nonblank)",--(G40<>""),--ISNUMBER(SEARCH($G$2,G40))))) | AS40: =IF($H$2="",1,IF($H$2="(blank)",--(H40=""),IF($H$2="(nonblank)",--(H40<>""),--ISNUMBER(SEARCH($H$2,H40))))) | AT40: =IF($I$2="",1,IF($I$2="(blank)",--(I40=""),IF($I$2="(nonblank)",--(I40<>""),--ISNUMBER(SEARCH($I$2,I40))))) | AU40: =IF($J$2="",1,IF($J$2="(blank)",--(J40=""),IF($J$2="(nonblank)",--(J40<>""),--ISNUMBER(SEARCH($J$2,J40))))) | AV40: =IF($K$2="",1,IF($K$2="(blank)",--(K40=""),IF($K$2="(nonblank)",--(K40<>""),--ISNUMBER(SEARCH($K$2,K40))))) | AW40: =IF($L$2="",1,IF($L$2="(blank)",--(L40=""),IF($L$2="(nonblank)",--(L40<>""),--ISNUMBER(SEARCH($L$2,L40))))) | AX40: =IF($M$2="",1,IF($M$2="(blank)",--(M40=""),IF($M$2="(nonblank)",--(M40<>""),--ISNUMBER(SEARCH($M$2,M40))))) | AY40: =IF($N$2="",1,IF($N$2="(blank)",--(N40=""),IF($N$2="(nonblank)",--(N40<>""),--ISNUMBER(SEARCH($N$2,N40))))) | AZ40: =IF($O$2="",1,IF($O$2="(blank)",--(O40=""),IF($O$2="(nonblank)",--(O40<>""),--ISNUMBER(SEARCH($O$2,O40))))) | BA40: =IF($P$2="",1,IF($P$2="(blank)",--(P40=""),IF($P$2="(nonblank)",--(P40<>""),--ISNUMBER(SEARCH($P$2,P40))))) | BB40: =IF($Q$2="",1,IF($Q$2="(blank)",--(Q40=""),IF($Q$2="(nonblank)",--(Q40<>""),--ISNUMBER(SEARCH($Q$2,Q40))))) | BC40: =IF($R$2="",1,IF($R$2="(blank)",--(R40=""),IF($R$2="(nonblank)",--(R40<>""),--ISNUMBER(SEARCH($R$2,R40))))) | BD40: =IF($S$2="",1,IF($S$2="(blank)",--(S40=""),IF($S$2="(nonblank)",--(S40<>""),--ISNUMBER(SEARCH($S$2,S40))))) | BE40: =IF($T$2="",1,IF($T$2="(blank)",--(T40=""),IF($T$2="(nonblank)",--(T40<>""),--ISNUMBER(SEARCH($T$2,T40))))) | BF40: =IF($U$2="",1,IF($U$2="(blank)",--(U40=""),IF($U$2="(nonblank)",--(U40<>""),--ISNUMBER(SEARCH($U$2,U40))))) | BG40: =IF($V$2="",1,IF($V$2="(blank)",--(V40=""),IF($V$2="(nonblank)",--(V40<>""),--ISNUMBER(SEARCH($V$2,V40))))) | BH40: =IF($W$2="",1,IF($W$2="(blank)",--(W40=""),IF($W$2="(nonblank)",--(W40<>""),--ISNUMBER(SEARCH($W$2,W40))))) | BI40: =IF($X$2="",1,IF($X$2="(blank)",--(X40=""),IF($X$2="(nonblank)",--(X40<>""),--ISNUMBER(SEARCH($X$2,X40))))) | BJ40: =IF($Y$2="",1,IF($Y$2="(blank)",--(Y40=""),IF($Y$2="(nonblank)",--(Y40<>""),--ISNUMBER(SEARCH($Y$2,Y40))))) | BK40: =IF($Z$2="",1,IF($Z$2="(blank)",--(Z40=""),IF($Z$2="(nonblank)",--(Z40<>""),--ISNUMBER(SEARCH($Z$2,Z40))))) | BL40: =IF($AA$2="",1,IF($AA$2="(blank)",--(AA40=""),IF($AA$2="(nonblank)",--(AA40<>""),--ISNUMBER(SEARCH($AA$2,AA40))))) | BM40: =IF($AB$2="",1,IF($AB$2="(blank)",--(AB40=""),IF($AB$2="(nonblank)",--(AB40<>""),--ISNUMBER(SEARCH($AB$2,AB40))))) | BN40: =IF($AC$2="",1,IF($AC$2="(blank)",--(AC40=""),IF($AC$2="(nonblank)",--(AC40<>""),--ISNUMBER(SEARCH($AC$2,AC40))))) | BO40: =IF($AD$2="",1,IF($AD$2="(blank)",--(AD40=""),IF($AD$2="(nonblank)",--(AD40<>""),--ISNUMBER(SEARCH($AD$2,AD40))))) | BP40: =IF($AE$2="",1,IF($AE$2="(blank)",--(AE40=""),IF($AE$2="(nonblank)",--(AE40<>""),--ISNUMBER(SEARCH($AE$2,AE40))))) | BQ40: =IF($AF$2="",1,IF($AF$2="(blank)",--(AF40=""),IF($AF$2="(nonblank)",--(AF40<>""),--ISNUMBER(SEARCH($AF$2,AF40))))) | BR40: =IF($AG$2="",1,IF($AG$2="(blank)",--(AG40=""),IF($AG$2="(nonblank)",--(AG40<>""),--ISNUMBER(SEARCH($AG$2,AG40))))) | BS40: =IF($AH$2="",1,IF($AH$2="(blank)",--(AH40=""),IF($AH$2="(nonblank)",--(AH40<>""),--ISNUMBER(SEARCH($AH$2,AH40))))) | BT40: =IF(COUNTIF($AL40:$BS40,0)>0,0,1)
H41: =SUM(H4:H40) | I41: =SUM(I4:I40) | J41: =SUM(J4:J40) | K41: =SUM(K4:K40) | L41: =SUM(L4:L40) | M41: =SUM(M4:M40) | N41: =SUM(N4:N40) | O41: =SUM(O4:O40) | P41: =SUM(P4:P40) | R41: =SUM(R4:R40) | S41: =SUM(S4:S40) | T41: =SUM(T4:T40) | U41: =SUM(U4:U40) | W41: =SUM(W4:W40) | X41: =SUM(X4:X40) | Z41: =SUM(Z4:Z40) | AA41: =SUM(AA4:AA40) | AC41: =SUM(AC4:AC40) | AD41: =SUM(AD4:AD40) | AE41: =IF(AD41="","",IF(AD41<=5,"SETTLED","OUTSTANDING"))
H42: =+H41 | I42: =ROUND(H42*18%,0) | J42: =+H42+I42 | K42: =ROUND((H42+I42)*2%,0) | L42: =ROUND(H42*0.1%,0) | M42: =ROUND(H42*2.25%*118%,0) | N42: =ROUND(H42*2.25%*2%,0) | O42: =ROUND(M42-N42,0) | P42: =ROUND(O42+L42,0) | R42: =+R41 | S42: =H42*117.65%-R42 | U42: =+T41-U41 | X42: =+W41-X41
U43: Bal SD O/s | X43: Bal FP O/s

Sheet Live Search
A1: MSTC LIMITED • LIVE SEARCH (results grouped by the value you typed, each group totalled, TOTAL MATCHED beneath them, the misses greyed in a REMAINING block, a GRAND TOTAL of both at the foot)
A2: HOW TO USE ▶ click the yellow box B3 and type - a lot number (1874), part of one (187), a buyer (NATIONAL), part of a buyer name, a lot name (COPPER). • WILDCARD / MATCH ANY - separate values with a comma or a slash: 1874, 1923, OMKAR or 1874 / 1923 - and every lot containing ANY of them lights up. • COLUMN SEARCHES - type above any column header in row 4; comma or slash means ANY value in that column, * matches any text and ? matches one character. Filters entered in different columns are combined as ALL. • FACETED / FILTERED - separate them with + or &: NATIONAL + COPPER - and a lot lights up only if it matches EVERY facet. • the two mix: OMKAR, STERLING + COPPER = (OMKAR or STERLING) and COPPER. Up to 8 values, empty ones ignored, spaces around a separator are fine. • THE RESULT IS GROUPED BY THE VALUE YOU TYPED: every value gets its own block of lots with a shaded ∑ total row beneath it, then a blue TOTAL MATCHED row adds every group up at once - the grand total of the rows your search actually hit, sitting right beneath them. Under that a greyed REMAINING block holds the lots that did not match, with its own total, and the green GRAND TOTAL of both sits at the foot. A lot matching two values is counted under the first one only, so TOTAL MATCHED + REMAINING always equals GRAND TOTAL, and with nothing typed the matched row is the whole list. • clear the box and all 37 come back in one ALL LOTS block. • cell F3 narrows what the text is looked for in (lot no. + buyer + name by default). • matching is contains, not case sensitive. • nothing here is typed in: every figure is a live link to Final Calculation Sheet. • columns AK..CU are hidden helpers. • use the +/- outline control above columns D:H to expand/collapse Lot Name through Rate under Buyer. • BLANK CELLS - type blank (or just press the spacebar) in the yellow cell above any column to show only the rows where that column is empty (brackets are optional, (blank) works the same; e.g. above LPP Received to list the lots with nothing received yet); nonblank or <> shows only the rows where it is filled. Case does not matter. Combines with other columns as ALL, and with comma-separated values in the same cell as ANY. • Also see the Buyer Groups sheet for the same lots grouped by buyer with subtotals. • AUTO-SUGGEST - every yellow search cell has a dropdown arrow with values already in the sheet: click it to pick, or just type - newer Excel filters the list as you type, like Google; every list is sorted ascending so values are easy to find. Typing stays completely free: comma lists, + facets, blank / spacebar and nonblank all still work. Live matches for the B3 box also appear in column AJ. • the (Expected) columns of Security Deposit, Final Payment and LPP each collapse via their own +/- button above the column. • SETTLED TOLERANCE - a lot received short by up to Rs. 5 counts as SETTLED (rounding tolerance); only shortfalls above Rs. 5 show OUTSTANDING. CASCADING DROPDOWNS — every yellow column dropdown (A4:AI4) narrows to values still possible given your other search cells and the search box; pick a buyer and Lot No. only shows that buyer’s lots, and so on. Clear a cell to widen its list again. Buyer Groups has the same cascading behaviour on its SEARCH row.
A3: 🔍 SEARCH ▸ | C3: BUYER 2 ▸ | E3: SEARCH IN ▸ | F3: Lot No. + Buyer + Name | G3: MATCHES ▸ | H3: =SUM($AM$5:$AM$41)&" of 37" | I3: =IF(AND($B$3="",COUNTIF($A$4:$AI$4,"<>")=0),"◀ type in the yellow box B3 or a yellow cell above any header - a lot no., a buyer, a lot name... several values: comma or / = ANY of them, + or & = ALL of them","matching "&SUM($AM$5:$AM$41)&" of 37 lots • search: "&IF($B$3="","(column fields)",$B$3)&" • in: "&$F$3&" • column fields are AND filters; grouped by the value typed, the misses greyed in REMAINING, TOTAL MATCHED totals the hits") | AJ3: SUGGESTIONS ▸ | AK3: the text this lot is searched in | AM3: 1 = this lot matches the search box | AO3: the 'search in' list | AQ3: the box with & -> + and / -> , | AR3: term 1 - rows 4..9: text left, delimiter pos, the term, delimiter, running facet, facet no. | CW3: =$C$4&IF($D$3<>"",",","")&$D$3
AJ4: =IF($B$3="","type in B3…",AL$41&" match(es)") | AO4: Lot No. + Buyer + Name | AQ4: =SUBSTITUTE(SUBSTITUTE($B$3,"&","+"),"/",",") | AR4: =$AQ$4 | AS4: =IF(OR($AR$4="",$AR$5=99999),"",MID($AR$4,$AR$5+1,99999)) | AT4: =IF(OR($AS$4="",$AS$5=99999),"",MID($AS$4,$AS$5+1,99999)) | AU4: =IF(OR($AT$4="",$AT$5=99999),"",MID($AT$4,$AT$5+1,99999)) | AV4: =IF(OR($AU$4="",$AU$5=99999),"",MID($AU$4,$AU$5+1,99999)) | AW4: =IF(OR($AV$4="",$AV$5=99999),"",MID($AV$4,$AV$5+1,99999)) | AX4: =IF(OR($AW$4="",$AW$5=99999),"",MID($AW$4,$AW$5+1,99999)) | AY4: =IF(OR($AX$4="",$AX$5=99999),"",MID($AX$4,$AX$5+1,99999)) | BD4: =COUNTIF($AZ$5:$AZ$41,1) | BE4: 5 | BF4: =IF($BD4=0,0,$BE4+$BD4) | BG4: =IF($BD12=0,$BE12,$BF12+1)
